Workbook

Sheet Start Here
B2: TRADING JOURNAL SYSTEM
B3: A journal that teaches you HOW to journal — and does every calculation for you.
B5: SET UP IN 10 MINUTES
B6: 1. Settings tab → choose what you trade (Futures, Stocks, Options, Forex or Crypto). Then enter your real fees and your risk rules. The fees shown are examples.
B7: 2. Accounts tab → add each account you trade. Prop-firm traders: enter your firm's drawdown, daily limit, profit target and consistency rule.
B8: 3. Setup Playbook tab → replace the 4 example setups with the 2–4 setups you actually trade.
B9: 4. Clear the examples: Trade Log → select the WHITE cells in rows 6–33 and press Delete. Do the same for the sample notes on the Daily Journal and Weekly Review tabs, then type your own start dates in their B6 cells. Never delete rows or the grey columns.
B10: 5. Log your next trade. The grey columns, the Dashboard, the Daily Journal and the Weekly Review all fill in by themselves.
B12: THE SYSTEM — HOW TO ACTUALLY JOURNAL
B13: Most traders log trades and never learn from them. This system runs on three loops:
B14: EVERY TRADE (30 seconds). Log it right after you close it. Write your stop and target BEFORE you enter — your R is measured against them. Tag the setup, how you felt, and any mistake. Be honest on 'Followed rules?' — a losing trade can still be a Yes.
B15: EVERY DAY (5 minutes). Daily Journal tab: what the market did, what you did, and whether you'd repeat it or delete it. Grade your execution, not your P&L.
... B23: 5. Missed a day? Fill it in and keep going. Consistency beats perfection.
B25: ="YOUR MODE: "&UPPER(Settings!$C$6)&" (change it on the Settings tab)" -> YOUR MODE: FUTURES (change it on the Settings tab)
B26: =CHOOSE(IFERROR(MATCH(Settings!$C$6,{"Futures","Stocks","Options","Forex","Crypto"},0),1),"Qty = contracts. Point values come from the Instruments tab (micros and minis included), so P&L is exact per contract. Fees = per contract, per side.","Qty = shares. P&L = price change × shares. Fees = per share, per side (set 0 if your broker is commission-free).","Enter the option PREMIUM as Entry/Exit (e.g. 2.35) and Qty in contracts. Each contract = 100 shares. Fees = per contract, per side.","Qty = standard lots (0.10 = a mini lot). P&L converts automatically for pairs that include your account currency. For crosses like EURJPY on a USD account, type your broker's P&L in Gross P&L.","Qty = coins (e.g. 0.05 BTC), not dollars. Fees: maker % for Limit entries and Target exits, taker % otherwise. Fill in Leverage to track your max-leverage rule. Add funding fees in the Fees column.") -> Qty = contracts. Point values come from the Instruments tab (micros and minis included), so P&L is exact per contract. Fees = per contract, per side.
B28: FAQ & TROUBLESHOOTING
B29: Net P&L is blank → the symbol isn't on the Instruments tab for that market. Add it (with its point value) or type your broker's P&L in 'Gross P&L (broker)'.
B30: My P&L doesn't match my broker → type your broker's numbers in the two optional columns (Gross P&L and Fees). The sheet then uses yours.
B31: Rule check says something I didn't expect → it reads the rules on the Settings tab. Blank a rule there to switch that check off.
B32: Futures fees → set a default on Settings, or a per-symbol fee on the Instruments tab (micros usually cost less than minis).
B33: Requirements → Excel 2019 or newer, Microsoft 365, or Google Sheets (File → Import or open the file in Drive). Apple Numbers is not supported.
B34: Sorting → keep the Trade Log in time order (oldest at the top). Streaks and running balances read top to bottom.
B36: IMPORTANT
B37: Contract specs on the Instruments tab were checked against CME Group's published specifications in October 2026. Exchanges can change them — verify before relying on them.
B38: Prop-firm rules differ by firm and change often. The Accounts tracker uses closed trades only. Your firm's own dashboard is the final word.
B39: All fees, accounts and trades in this file are examples. This is a journaling tool, not financial advice.

Sheet Settings
B2: SETTINGS
B3: Set these once. Yellow cells are yours to change. Everything else in the journal reads from here.
B5: 1 · WHAT YOU TRADE — this is the mode switch
B6: What do you mainly trade? | C6: Futures | D6: Changes the Qty label, session list, symbol dropdown and default market. Each account on the Accounts tab can also have its own market, so mixed traders get correct math on every trade.
B7: Account currency (3 letters) | C7: USD | D7: Shown in P&L headers. Forex P&L converts automatically for pairs that include this currency.
B8: Scratch zone (± R) | C8: 0.1 | D8: Trades that close within ±0.10R count as scratches, not wins or losses.
B9: Journal name | C9: My Trading Journal | D9: Shows at the top of the Dashboard.
B10: Daily Journal includes weekends? | C10: No | D10: Yes for crypto traders. No skips Saturday and Sunday.
B12: 2 · MARKET DEFAULTS — sizes and fees for each market
B13: Market | C13: Qty means | D13: Multiplier (if no symbol match) | E13: Fee model | F13: Fee per unit, per side | G13: Maker fee % | H13: Taker fee % | I13: How it works
B14: Futures | C14: contracts | D14: per symbol | E14: Per unit | F14: 0.5 | I14: Point value per symbol comes from the Instruments tab. Fee = per contract, per side.
B15: Stocks | C15: shares | D15: 1 | E15: Per unit | F15: 0 | I15: Qty = shares. Fee = per share, per side (0 if your broker is commission-free).
B16: Options | C16: contracts x100 | D16: 100 | E16: Per unit | F16: 0.65 | I16: Entry/Exit = option premium (e.g. 2.35). Qty = contracts. 1 contract = 100 shares.
B17: Forex | C17: lots | D17: 100000 | E17: Per unit | F17: 3.5 | I17: Qty = lots. 1 standard lot = 100,000 units at most brokers - check yours. Fee = commission per lot, per side.
B18: Crypto | C18: coins | D18: 1 | E18: % of notional | G18: 0.0002 | H18: 0.0006 | I18: Qty = coins (0.05 BTC), not dollars. Maker % on Limit entries and Target exits; taker % on everything else.
B19: ⚠ The fees above are EXAMPLES, not any broker's real rates. Replace them with yours. Futures can also have a per-symbol fee on the Instruments tab (micros usually cost less than minis).
B21: 3 · YOUR RISK RULES — leave a cell blank to switch that check off
B22: Max risk per trade ($) | C22: 250 | D22: Flags any trade risking more than this. Risk = stop distance × size × point value.
B23: Max risk per trade (% of account) | C23: 0.01 | D23: Uses the account balance before the trade. Needs a starting balance on the Accounts tab.
B24: Max leverage (x) | C24: 20 | D24: For crypto/forex trades where you fill in Leverage.
B25: Max trades per day | C25: 4 | D25: Flags every trade after this number on the same day.
B26: Daily max loss ($) | C26: 400 | D26: Flags trades taken after the day's losses reached this (all accounts combined).
B27: Minimum planned R:R | C27: 1.5 | D27: Flags trades planned below this reward-to-risk.
B29: 4 · SESSION NAMES — rename them to match how you trade
B30: # | C30: Futures | D30: Stocks | E30: Options | F30: Forex | G30: Crypto
B31: 1 | C31: Overnight | D31: Pre-market | E31: Pre-market | F31: Sydney | G31: Asia
B32: 2 | C32: London | D32: Open | E32: Open | F32: Tokyo | G32: Europe
B33: 3 | C33: NY Open | D33: Morning | E33: Morning | F33: London | G33: US
B34: 4 | C34: NY Midday | D34: Midday | E34: Midday | F34: London/NY Overlap | G34: US Close
B35: 5 | C35: NY Afternoon | D35: Power Hour | E35: Power Hour | F35: New York | G35: Weekend
B36: 6 | C36: NY Close | D36: After-hours | E36: After-hours | F36: Late NY | G36: Overnight
B38: The Session dropdown in the Trade Log shows the column for your mode. You can still type any session name.

Sheet Trade Log
A1: TRADE LOG
A2: Log each trade right after you close it. White = you type · Grey = automatic. Keep trades in time order (oldest at the top). Hover over a header for help.
A3: Sample trades are in rows 6–33. When you're ready, select the WHITE cells in those rows and press Delete. Never delete rows or the grey columns.
A4: YOUR TRADE (type here) | Q4: RESULTS (automatic) | X4: REVIEW (type here) | AF4: HELPER COLUMNS (automatic — don't edit)
A5: Date | B5: Time | C5: Account | D5: Market (optional) | E5: Symbol | F5: Long / Short | G5: ="Qty ("&IFERROR(INDEX(Settings!$C$14:$C$18,MATCH(Settings!$C$6,Settings!$B$14:$B$18,0)),"units")&")" -> Qty (contracts) | H5: Entry price | I5: Stop loss (original) | J5: Target | K5: Exit price (avg) | L5: Entry order | M5: Exit reason | N5: Leverage (x) | O5: Gross P&L (broker) optional | P5: Fees (broker) optional | Q5: ="Net P&L ("&Settings!$C$7&")" -> Net P&L (USD) | R5: R multiple | S5: Result | T5: Planned R:R | U5: R short of target | V5: $ Risk | W5: Rule check | X5: Session | Y5: Setup | Z5: Followed rules? | AA5: Emotion | AB5: Mistake | AC5: Why I took it | AD5: Review note | AE5: Screenshot link | AF5: Market used | AG5: Point value | AH5: FX factor | AI5: Gross (calc) | AJ5: Fees (calc) | AK5: Gross used | AL5: Fees used | AM5: Valid | AN5: Week of | AO5: Weekday | AP5: Acct balance after | AQ5: Acct day net | AR5: Acct EOD balance | AS5: In dashboard filter | AT5: Cum P&L (filter) | AU5: Peak (filter) | AV5: Drawdown (filter) | AW5: Win streak | AX5: Loss streak | AY5: Filter trade # | AZ5: Chart X | BA5: First of day | BB5: Day net (filter) | BC5: Has R | BD5: $ short of target | BE5: Instrument row | BF5: Market row | BG5: Flags (raw) | BH5: Has net | BI5: Setup tagged | BJ5: Mistake tagged | BK5: Flagged | BL5: Chart Y | BM5: After max loss
A6: 46286 | B6: 0.40416667 | C6: Prop Eval 50K | E6: MNQ | F6: Long | G6: 2 | H6: 29640 | I6: 29610 | J6: 29700 | K6: 29700 | L6: Limit | M6: Target | Q6: =IF($AM6=0,"",IF(ISNUMBER($AK6),$AK6-N($AL6),"")) -> 238 | R6: =IF(OR($Q6="",NOT(ISNUMBER($V6))),"",$AK6/$V6) -> 2 | S6: =IF($Q6="","",IF(AND(ISNUMBER($R6),ABS(N($R6))<N(Settings!$C$8)),"Scratch",IF($Q6>0,"Win",IF($Q6<0,"Loss","Scratch")))) -> Win | T6: =IF(OR($AM6=0,NOT(ISNUMBER($H6)),NOT(ISNUMBER($I6)),NOT(ISNUMBER($J6))),"",IF($H6=$I6,"",ROUND(ABS($J6-$H6)/ABS($H6-$I6),6))) -> 2 | U6: =IF(OR($S6<>"Win",NOT(ISNUMBER($T6)),NOT(ISNUMBER($R6))),"",MAX(0,$T6-$R6)) -> 0 | V6: =IF(OR($AM6=0,NOT(ISNUMBER($H6)),NOT(ISNUMBER($I6)),NOT(ISNUMBER($G6))),"",IF(OR($AG6="",$AH6=""),"",IF(ROUND(ABS($H6-$I6)*ABS($G6)*$AG6*$AH6,6)=0,"",ROUND(ABS($H6-$I6)*ABS($G6)*$AG6*$AH6,6)))) -> 120 | W6: =IF($AM6=0,"",IF($BG6="","OK",LEFT($BG6,LEN($BG6)-2))) -> OK | X6: NY Open | Y6: Breakout & Retest | Z6: Yes | AA6: Calm | AC6: Retest of overnight high held on volume | AD6: Textbook. Held to target. | AF6: =IF($AM6=0,"",IF($D6<>"",$D6,IF(IFERROR(INDEX(Accounts!$C$7:$C$16,MATCH($C6,Accounts!$B$7:$B$16,0))&"","")<>"",INDEX(Accounts!$C$7:$C$16,MATCH($C6,Accounts!$B$7:$B$16,0)),Settings!$C$6))) -> Futures | AG6: =IF($AM6=0,"",IF(AND($BE6>0,N(INDEX(Instruments!$D$6:$D$205,MAX(1,$BE6)))>0),INDEX(Instruments!$D$6:$D$205,MAX(1,$BE6)),IF(N(INDEX(Settings!$D$14:$D$18,$BF6))>0,INDEX(Settings!$D$14:$D$18,$BF6),""))) -> 2 | AH6: =IF($AM6=0,"",IF($AF6<>"Forex",1,IF(MID(UPPER(SUBSTITUTE(TRIM($E6),"/","")),4,3)=UPPER(TRIM(Settings!$C$7)),1,IF(LEFT(UPPER(SUBSTITUTE(TRIM($E6),"/","")),3)=UPPER(TRIM(Settings!$C$7)),IF(AND(ISNUMBER($K6),N($K6)<>0),1/$K6,""),"")))) -> 1 | AI6: =IF($AM6=0,"",IF(OR(NOT(ISNUMBER($H6)),NOT(ISNUMBER($K6)),NOT(ISNUMBER($G6)),$AG6="",$AH6=""),"",ROUND(($K6-$H6)*IF($F6="Short",-1,1)*$G6*$AG6*$AH6,6))) -> 240 | AJ6: =IF($AM6=0,"",IF(INDEX(Settings!$E$14:$E$18,$BF6)="% of notional",IF(OR($AG6="",NOT(ISNUMBER($H6)),NOT(ISNUMBER($G6))),"",ROUND(ABS($H6*$G6*$AG6*N($AH6))*IF($L6="Limit",N(INDEX(Settings!$G$14:$G$18,$BF6)),N(INDEX(Settings!$H$14:$H$18,$BF6)))+IF(ISNUMBER($K6),ABS($K6*$G6*$AG6*N($AH6))*IF($M6="Target",N(INDEX(Settings!$G$14:$G$18,$BF6)),N(INDEX(Settings!$H$14:$H$18,$BF6))),0),6)),IF(NOT(ISNUMBER($G6)),"",ROUND(ABS($G6)*2*IF(AND($BE6>0,ISNUMBER(INDEX(Instruments!$G$6:$G$205,MAX(1,$BE6)))),INDEX(Instruments!$G$6:$G$205,MAX(1,$BE6)),N(INDEX(Settings!$F$14:$F$18,$BF6))),6)))) -> 2 | AK6: =IF($AM6=0,"",IF(ISNUMBER($O6),$O6,$AI6)) -> 240 | AL6: =IF($AM6=0,"",IF(ISNUMBER($P6),$P6,N($AJ6))) -> 2 | AM6: =IF(AND($A6<>"",$E6<>"",OR(AND(ISNUMBER($G6),ISNUMBER($H6),ISNUMBER($K6)),ISNUMBER($O6))),1,0) -> 1 | AN6: =IF($A6="","",$A6-WEEKDAY($A6,3)) -> 46286 | AO6: =IF($A6="","",WEEKDAY($A6,2)) -> 1 | AP6: =IF(OR($AM6=0,$C6=""),"",IFERROR(N(INDEX(Accounts!$E$7:$E$16,MATCH($C6,Accounts!$B$7:$B$16,0))),0)+SUMIFS($Q$6:$Q6,$C$6:$C6,$C6)) -> 50238 | AQ6: =IF(OR($AM6=0,$C6=""),"",SUMIFS($Q$6:$Q$1005,$C$6:$C$1005,$C6,$A$6:$A$1005,$A6)) -> 298.5 | AR6: =IF(OR($AM6=0,$C6=""),"",IFERROR(N(INDEX(Accounts!$E$7:$E$16,MATCH($C6,Accounts!$B$7:$B$16,0))),0)+SUMIFS($Q$6:$Q$1005,$C$6:$C$1005,$C6,$A$6:$A$1005,"<="&$A6)) -> 50298.5 | AS6: =IF(OR($AM6=0,$Q6=""),0,IF(AND($A6>=Lists!$W$6,$A6<=Lists!$W$7,OR(Dashboard!$D$6="All accounts",$C6=Dashboard!$D$6),OR(Dashboard!$D$7="All markets",$AF6=Dashboard!$D$7)),1,0)) -> 1 | AT6: =IF($AS6=1,N(AT5)+$Q6,N(AT5)) -> 238 | AU6: =MAX(N(AU5),$AT6) -> 238 | AV6: =$AT6-$AU6 -> 0 | AW6: =IF($AS6=1,IF($S6="Win",N(AW5)+1,IF($S6="Loss",0,N(AW5))),N(AW5)) -> 1 | AX6: =IF($AS6=1,IF($S6="Loss",N(AX5)+1,IF($S6="Win",0,N(AX5))),N(AX5)) -> 0 | AY6: =IF($AS6=1,COUNTIF($AS$6:$AS6,1),"") -> 1 | AZ6: =MIN(0,N(Lists!$W$8)) -> 0 | BA6: =IF($AS6=1,IF(COUNTIFS($A$6:$A6,$A6,$AS$6:$AS6,1)=1,1,0),0) -> 1 | BB6: =IF($BA6=1,SUMIFS($Q$6:$Q$1005,$A$6:$A$1005,$A6,$AS$6:$AS$1005,1),"") -> 298.5 | BC6: =IF(ISNUMBER($R6),1,0) -> 1 | BD6: =IF(ISNUMBER($U6),$U6*$V6,"") -> 0 | BE6: =IF($AM6=0,"",IFERROR(MATCH($AF6&"|"&UPPER(TRIM($E6)),Lists!$A$6:$A$205,0),0)) -> 3 | BF6: =IF($AM6=0,"",IFERROR(MATCH($AF6,Settings!$B$14:$B$18,0),IFERROR(MATCH(Settings!$C$6,Settings!$B$14:$B$18,0),1))) -> 1 | BG6: =IF($AM6=0,"",IF(NOT(ISNUMBER($I6)),"No stop; ","")&IF(AND(ISNUMBER($H6),ISNUMBER($I6)),IF(OR(AND($F6<>"Short",$I6>=$H6),AND($F6="Short",$I6<=$H6)),"Stop on wrong side; ",""),"")&IF($F6="","No direction; ","")&IF(AND(ISNUMBER(Settings!$C$22),ISNUMBER($V6)),IF($V6>Settings!$C$22,"Risk over max $; ",""),"")&IF(AND(ISNUMBER(Settings!$C$23),ISNUMBER($V6),ISNUMBER($AP6),IFERROR(N(INDEX(Accounts!$E$7:$E$16,MATCH($C6,Accounts!$B$7:$B$16,0))),0)>0),IF($V6>Settings!$C$23*($AP6-N($Q6)),"Risk over max %; ",""),"")&IF(AND(ISNUMBER(Settings!$C$24),ISNUMBER($N6)),IF($N6>Settings!$C$24,"Leverage over max; ",""),"")&IF(AND(ISNUMBER(Settings!$C$27),ISNUMBER($T6)),IF($T6<Settings!$C$27,"R:R below min; ",""),"")&IF(ISNUMBER(Settings!$C$25),IF(COUNTIFS($A$6:$A6,$A6,$AM$6:$AM6,1)>Settings!$C$25,"Over max trades/day; ",""),"")&IF(ISNUMBER(Settings!$C$26),IF(SUMIFS($Q$5:$Q5,$A$5:$A5,$A6)<=-Settings!$C$26,"Traded after daily max loss; ",""),"")&IF(AND($AG6="",NOT(ISNUMBER($O6))),"Symbol not in Instruments; ","")&IF(AND($AH6="",NOT(ISNUMBER($O6))),"Forex cross: type Gross P&L; ","")) | BH6: =IF(ISNUMBER($Q6),1,0) -> 1 | BI6: =IF($Y6="",0,1) -> 1 | BJ6: =IF($AB6="",0,1) -> 0 | BK6: =IF(AND($BH6=1,$W6<>"OK"),1,0) -> 0 | BL6: =IF(N($AZ6)=0,0,IFERROR(INDEX($AT$6:$AT$1005,MATCH($AZ6,$AY$6:$AY$1005,0)),0)) -> 0 | BM6: =IF(ISNUMBER(SEARCH("daily max loss",$BG6)),1,0) -> 0
A7: 46286 | B7: 0.43819444 | C7: Prop Eval 50K | E7: MES | F7: Long | G7: 2 | H7: 7662.5 | I7: 7655 | J7: 7677.5 | K7: 7668.75 | L7: Limit | M7: Manual | Q7: =IF($AM7=0,"",IF(ISNUMBER($AK7),$AK7-N($AL7),"")) -> 60.5 | R7: =IF(OR($Q7="",NOT(ISNUMBER($V7))),"",$AK7/$V7) -> 0.83333333 | S7: =IF($Q7="","",IF(AND(ISNUMBER($R7),ABS(N($R7))<N(Settings!$C$8)),"Scratch",IF($Q7>0,"Win",IF($Q7<0,"Loss","Scratch")))) -> Win | T7: =IF(OR($AM7=0,NOT(ISNUMBER($H7)),NOT(ISNUMBER($I7)),NOT(ISNUMBER($J7))),"",IF($H7=$I7,"",ROUND(ABS($J7-$H7)/ABS($H7-$I7),6))) -> 2 | U7: =IF(OR($S7<>"Win",NOT(ISNUMBER($T7)),NOT(ISNUMBER($R7))),"",MAX(0,$T7-$R7)) -> 1.1666667 | V7: =IF(OR($AM7=0,NOT(ISNUMBER($H7)),NOT(ISNUMBER($I7)),NOT(ISNUMBER($G7))),"",IF(OR($AG7="",$AH7=""),"",IF(ROUND(ABS($H7-$I7)*ABS($G7)*$AG7*$AH7,6)=0,"",ROUND(ABS($H7-$I7)*ABS($G7)*$AG7*$AH7,6)))) -> 75 | W7: =IF($AM7=0,"",IF($BG7="","OK",LEFT($BG7,LEN($BG7)-2))) -> OK | X7: NY Open | Y7: Trend Pullback | Z7: No | AA7: Hesitant | AB7: Took profit too early | AC7: Pullback to 20 EMA in an uptrend | AD7: Got nervous at the prior high and bailed early. | AF7: =IF($AM7=0,"",IF($D7<>"",$D7,IF(IFERROR(INDEX(Accounts!$C$7:$C$16,MATCH($C7,Accounts!$B$7:$B$16,0))&"","")<>"",INDEX(Accounts!$C$7:$C$16,MATCH($C7,Accounts!$B$7:$B$16,0)),Settings!$C$6))) -> Futures | AG7: =IF($AM7=0,"",IF(AND($BE7>0,N(INDEX(Instruments!$D$6:$D$205,MAX(1,$BE7)))>0),INDEX(Instruments!$D$6:$D$205,MAX(1,$BE7)),IF(N(INDEX(Settings!$D$14:$D$18,$BF7))>0,INDEX(Settings!$D$14:$D$18,$BF7),""))) -> 5 | AH7: =IF($AM7=0,"",IF($AF7<>"Forex",1,IF(MID(UPPER(SUBSTITUTE(TRIM($E7),"/","")),4,3)=UPPER(TRIM(Settings!$C$7)),1,IF(LEFT(UPPER(SUBSTITUTE(TRIM($E7),"/","")),3)=UPPER(TRIM(Settings!$C$7)),IF(AND(ISNUMBER($K7),N($K7)<>0),1/$K7,""),"")))) -> 1 | AI7: =IF($AM7=0,"",IF(OR(NOT(ISNUMBER($H7)),NOT(ISNUMBER($K7)),NOT(ISNUMBER($G7)),$AG7="",$AH7=""),"",ROUND(($K7-$H7)*IF($F7="Short",-1,1)*$G7*$AG7*$AH7,6))) -> 62.5 | AJ7: =IF($AM7=0,"",IF(INDEX(Settings!$E$14:$E$18,$BF7)="% of notional",IF(OR($AG7="",NOT(ISNUMBER($H7)),NOT(ISNUMBER($G7))),"",ROUND(ABS($H7*$G7*$AG7*N($AH7))*IF($L7="Limit",N(INDEX(Settings!$G$14:$G$18,$BF7)),N(INDEX(Settings!$H$14:$H$18,$BF7)))+IF(ISNUMBER($K7),ABS($K7*$G7*$AG7*N($AH7))*IF($M7="Target",N(INDEX(Settings!$G$14:$G$18,$BF7)),N(INDEX(Settings!$H$14:$H$18,$BF7))),0),6)),IF(NOT(ISNUMBER($G7)),"",ROUND(ABS($G7)*2*IF(AND($BE7>0,ISNUMBER(INDEX(Instruments!$G$6:$G$205,MAX(1,$BE7)))),INDEX(Instruments!$G$6:$G$205,MAX(1,$BE7)),N(INDEX(Settings!$F$14:$F$18,$BF7))),6)))) -> 2 | AK7: =IF($AM7=0,"",IF(ISNUMBER($O7),$O7,$AI7)) -> 62.5 | AL7: =IF($AM7=0,"",IF(ISNUMBER($P7),$P7,N($AJ7))) -> 2 | AM7: =IF(AND($A7<>"",$E7<>"",OR(AND(ISNUMBER($G7),ISNUMBER($H7),ISNUMBER($K7)),ISNUMBER($O7))),1,0) -> 1 | AN7: =IF($A7="","",$A7-WEEKDAY($A7,3)) -> 46286 | AO7: =IF($A7="","",WEEKDAY($A7,2)) -> 1 | AP7: =IF(OR($AM7=0,$C7=""),"",IFERROR(N(INDEX(Accounts!$E$7:$E$16,MATCH($C7,Accounts!$B$7:$B$16,0))),0)+SUMIFS($Q$6:$Q7,$C$6:$C7,$C7)) -> 50298.5 | AQ7: =IF(OR($AM7=0,$C7=""),"",SUMIFS($Q$6:$Q$1005,$C$6:$C$1005,$C7,$A$6:$A$1005,$A7)) -> 298.5 | AR7: =IF(OR($AM7=0,$C7=""),"",IFERROR(N(INDEX(Accounts!$E$7:$E$16,MATCH($C7,Accounts!$B$7:$B$16,0))),0)+SUMIFS($Q$6:$Q$1005,$C$6:$C$1005,$C7,$A$6:$A$1005,"<="&$A7)) -> 50298.5 | AS7: =IF(OR($AM7=0,$Q7=""),0,IF(AND($A7>=Lists!$W$6,$A7<=Lists!$W$7,OR(Dashboard!$D$6="All accounts",$C7=Dashboard!$D$6),OR(Dashboard!$D$7="All markets",$AF7=Dashboard!$D$7)),1,0)) -> 1 | AT7: =IF($AS7=1,N(AT6)+$Q7,N(AT6)) -> 298.5 | AU7: =MAX(N(AU6),$AT7) -> 298.5 | AV7: =$AT7-$AU7 -> 0 | AW7: =IF($AS7=1,IF($S7="Win",N(AW6)+1,IF($S7="Loss",0,N(AW6))),N(AW6)) -> 2 | AX7: =IF($AS7=1,IF($S7="Loss",N(AX6)+1,IF($S7="Win",0,N(AX6))),N(AX6)) -> 0 | AY7: =IF($AS7=1,COUNTIF($AS$6:$AS7,1),"") -> 2 | AZ7: =MIN(1,N(Lists!$W$8)) -> 1 | BA7: =IF($AS7=1,IF(COUNTIFS($A$6:$A7,$A7,$AS$6:$AS7,1)=1,1,0),0) -> 0 | BB7: =IF($BA7=1,SUMIFS($Q$6:$Q$1005,$A$6:$A$1005,$A7,$AS$6:$AS$1005,1),"") | BC7: =IF(ISNUMBER($R7),1,0) -> 1 | BD7: =IF(ISNUMBER($U7),$U7*$V7,"") -> 87.5 | BE7: =IF($AM7=0,"",IFERROR(MATCH($AF7&"|"&UPPER(TRIM($E7)),Lists!$A$6:$A$205,0),0)) -> 1 | BF7: =IF($AM7=0,"",IFERROR(MATCH($AF7,Settings!$B$14:$B$18,0),IFERROR(MATCH(Settings!$C$6,Settings!$B$14:$B$18,0),1))) -> 1 | BG7: =IF($AM7=0,"",IF(NOT(ISNUMBER($I7)),"No stop; ","")&IF(AND(ISNUMBER($H7),ISNUMBER($I7)),IF(OR(AND($F7<>"Short",$I7>=$H7),AND($F7="Short",$I7<=$H7)),"Stop on wrong side; ",""),"")&IF($F7="","No direction; ","")&IF(AND(ISNUMBER(Settings!$C$22),ISNUMBER($V7)),IF($V7>Settings!$C$22,"Risk over max $; ",""),"")&IF(AND(ISNUMBER(Settings!$C$23),ISNUMBER($V7),ISNUMBER($AP7),IFERROR(N(INDEX(Accounts!$E$7:$E$16,MATCH($C7,Accounts!$B$7:$B$16,0))),0)>0),IF($V7>Settings!$C$23*($AP7-N($Q7)),"Risk over max %; ",""),"")&IF(AND(ISNUMBER(Settings!$C$24),ISNUMBER($N7)),IF($N7>Settings!$C$24,"Leverage over max; ",""),"")&IF(AND(ISNUMBER(Settings!$C$27),ISNUMBER($T7)),IF($T7<Settings!$C$27,"R:R below min; ",""),"")&IF(ISNUMBER(Settings!$C$25),IF(COUNTIFS($A$6:$A7,$A7,$AM$6:$AM7,1)>Settings!$C$25,"Over max trades/day; ",""),"")&IF(ISNUMBER(Settings!$C$26),IF(SUMIFS($Q$5:$Q6,$A$5:$A6,$A7)<=-Settings!$C$26,"Traded after daily max loss; ",""),"")&IF(AND($AG7="",NOT(ISNUMBER($O7))),"Symbol not in Instruments; ","")&IF(AND($AH7="",NOT(ISNUMBER($O7))),"Forex cross: type Gross P&L; ","")) | BH7: =IF(ISNUMBER($Q7),1,0) -> 1 | BI7: =IF($Y7="",0,1) -> 1 | BJ7: =IF($AB7="",0,1) -> 1 | BK7: =IF(AND($BH7=1,$W7<>"OK"),1,0) -> 0 | BL7: =IF(N($AZ7)=0,0,IFERROR(INDEX($AT$6:$AT$1005,MATCH($AZ7,$AY$6:$AY$1005,0)),0)) -> 238 | BM7: =IF(ISNUMBER(SEARCH("daily max loss",$BG7)),1,0) -> 0
A8: 46287 | B8: 0.4 | C8: Prop Eval 50K | E8: MGC | F8: Long | G8: 1 | H8: 4052 | I8: 4046 | J8: 4064 | K8: 4064 | L8: Limit | M8: Target | Q8: =IF($AM8=0,"",IF(ISNUMBER($AK8),$AK8-N($AL8),"")) -> 119 | R8: =IF(OR($Q8="",NOT(ISNUMBER($V8))),"",$AK8/$V8) -> 2 | S8: =IF($Q8="","",IF(AND(ISNUMBER($R8),ABS(N($R8))<N(Settings!$C$8)),"Scratch",IF($Q8>0,"Win",IF($Q8<0,"Loss","Scratch")))) -> Win | T8: =IF(OR($AM8=0,NOT(ISNUMBER($H8)),NOT(ISNUMBER($I8)),NOT(ISNUMBER($J8))),"",IF($H8=$I8,"",ROUND(ABS($J8-$H8)/ABS($H8-$I8),6))) -> 2 | U8: =IF(OR($S8<>"Win",NOT(ISNUMBER($T8)),NOT(ISNUMBER($R8))),"",MAX(0,$T8-$R8)) -> 0 | V8: =IF(OR($AM8=0,NOT(ISNUMBER($H8)),NOT(ISNUMBER($I8)),NOT(ISNUMBER($G8))),"",IF(OR($AG8="",$AH8=""),"",IF(ROUND(ABS($H8-$I8)*ABS($G8)*$AG8*$AH8,6)=0,"",ROUND(ABS($H8-$I8)*ABS($G8)*$AG8*$AH8,6)))) -> 60 | W8: =IF($AM8=0,"",IF($BG8="","OK",LEFT($BG8,LEN($BG8)-2))) -> OK | X8: NY Open | Y8: Breakout & Retest | Z8: Yes | AA8: Calm | AC8: Gold held its breakout above the Asia high | AD8: Clean. | AF8: =IF($AM8=0,"",IF($D8<>"",$D8,IF(IFERROR(INDEX(Accounts!$C$7:$C$16,MATCH($C8,Accounts!$B$7:$B$16,0))&"","")<>"",INDEX(Accounts!$C$7:$C$16,MATCH($C8,Accounts!$B$7:$B$16,0)),Settings!$C$6))) -> Futures | AG8: =IF($AM8=0,"",IF(AND($BE8>0,N(INDEX(Instruments!$D$6:$D$205,MAX(1,$BE8)))>0),INDEX(Instruments!$D$6:$D$205,MAX(1,$BE8)),IF(N(INDEX(Settings!$D$14:$D$18,$BF8))>0,INDEX(Settings!$D$14:$D$18,$BF8),""))) -> 10 | AH8: =IF($AM8=0,"",IF($AF8<>"Forex",1,IF(MID(UPPER(SUBSTITUTE(TRIM($E8),"/","")),4,3)=UPPER(TRIM(Settings!$C$7)),1,IF(LEFT(UPPER(SUBSTITUTE(TRIM($E8),"/","")),3)=UPPER(TRIM(Settings!$C$7)),IF(AND(ISNUMBER($K8),N($K8)<>0),1/$K8,""),"")))) -> 1 | AI8: =IF($AM8=0,"",IF(OR(NOT(ISNUMBER($H8)),NOT(ISNUMBER($K8)),NOT(ISNUMBER($G8)),$AG8="",$AH8=""),"",ROUND(($K8-$H8)*IF($F8="Short",-1,1)*$G8*$AG8*$AH8,6))) -> 120 | AJ8: =IF($AM8=0,"",IF(INDEX(Settings!$E$14:$E$18,$BF8)="% of notional",IF(OR($AG8="",NOT(ISNUMBER($H8)),NOT(ISNUMBER($G8))),"",ROUND(ABS($H8*$G8*$AG8*N($AH8))*IF($L8="Limit",N(INDEX(Settings!$G$14:$G$18,$BF8)),N(INDEX(Settings!$H$14:$H$18,$BF8)))+IF(ISNUMBER($K8),ABS($K8*$G8*$AG8*N($AH8))*IF($M8="Target",N(INDEX(Settings!$G$14:$G$18,$BF8)),N(INDEX(Settings!$H$14:$H$18,$BF8))),0),6)),IF(NOT(ISNUMBER($G8)),"",ROUND(ABS($G8)*2*IF(AND($BE8>0,ISNUMBER(INDEX(Instruments!$G$6:$G$205,MAX(1,$BE8)))),INDEX(Instruments!$G$6:$G$205,MAX(1,$BE8)),N(INDEX(Settings!$F$14:$F$18,$BF8))),6)))) -> 1 | AK8: =IF($AM8=0,"",IF(ISNUMBER($O8),$O8,$AI8)) -> 120 | AL8: =IF($AM8=0,"",IF(ISNUMBER($P8),$P8,N($AJ8))) -> 1 | AM8: =IF(AND($A8<>"",$E8<>"",OR(AND(ISNUMBER($G8),ISNUMBER($H8),ISNUMBER($K8)),ISNUMBER($O8))),1,0) -> 1 | AN8: =IF($A8="","",$A8-WEEKDAY($A8,3)) -> 46286 | AO8: =IF($A8="","",WEEKDAY($A8,2)) -> 2 | AP8: =IF(OR($AM8=0,$C8=""),"",IFERROR(N(INDEX(Accounts!$E$7:$E$16,MATCH($C8,Accounts!$B$7:$B$16,0))),0)+SUMIFS($Q$6:$Q8,$C$6:$C8,$C8)) -> 50417.5 | AQ8: =IF(OR($AM8=0,$C8=""),"",SUMIFS($Q$6:$Q$1005,$C$6:$C$1005,$C8,$A$6:$A$1005,$A8)) -> 57 | AR8: =IF(OR($AM8=0,$C8=""),"",IFERROR(N(INDEX(Accounts!$E$7:$E$16,MATCH($C8,Accounts!$B$7:$B$16,0))),0)+SUMIFS($Q$6:$Q$1005,$C$6:$C$1005,$C8,$A$6:$A$1005,"<="&$A8)) -> 50355.5 | AS8: =IF(OR($AM8=0,$Q8=""),0,IF(AND($A8>=Lists!$W$6,$A8<=Lists!$W$7,OR(Dashboard!$D$6="All accounts",$C8=Dashboard!$D$6),OR(Dashboard!$D$7="All markets",$AF8=Dashboard!$D$7)),1,0)) -> 1 | AT8: =IF($AS8=1,N(AT7)+$Q8,N(AT7)) -> 417.5 | AU8: =MAX(N(AU7),$AT8) -> 417.5 | AV8: =$AT8-$AU8 -> 0 | AW8: =IF($AS8=1,IF($S8="Win",N(AW7)+1,IF($S8="Loss",0,N(AW7))),N(AW7)) -> 3 | AX8: =IF($AS8=1,IF($S8="Loss",N(AX7)+1,IF($S8="Win",0,N(AX7))),N(AX7)) -> 0 | AY8: =IF($AS8=1,COUNTIF($AS$6:$AS8,1),"") -> 3 | AZ8: =MIN(2,N(Lists!$W$8)) -> 2 | BA8: =IF($AS8=1,IF(COUNTIFS($A$6:$A8,$A8,$AS$6:$AS8,1)=1,1,0),0) -> 1 | BB8: =IF($BA8=1,SUMIFS($Q$6:$Q$1005,$A$6:$A$1005,$A8,$AS$6:$AS$1005,1),"") -> 115.704 | BC8: =IF(ISNUMBER($R8),1,0) -> 1 | BD8: =IF(ISNUMBER($U8),$U8*$V8,"") -> 0 | BE8: =IF($AM8=0,"",IFERROR(MATCH($AF8&"|"&UPPER(TRIM($E8)),Lists!$A$6:$A$205,0),0)) -> 14 | BF8: =IF($AM8=0,"",IFERROR(MATCH($AF8,Settings!$B$14:$B$18,0),IFERROR(MATCH(Settings!$C$6,Settings!$B$14:$B$18,0),1))) -> 1 | BG8: =IF($AM8=0,"",IF(NOT(ISNUMBER($I8)),"No stop; ","")&IF(AND(ISNUMBER($H8),ISNUMBER($I8)),IF(OR(AND($F8<>"Short",$I8>=$H8),AND($F8="Short",$I8<=$H8)),"Stop on wrong side; ",""),"")&IF($F8="","No direction; ","")&IF(AND(ISNUMBER(Settings!$C$22),ISNUMBER($V8)),IF($V8>Settings!$C$22,"Risk over max $; ",""),"")&IF(AND(ISNUMBER(Settings!$C$23),ISNUMBER($V8),ISNUMBER($AP8),IFERROR(N(INDEX(Accounts!$E$7:$E$16,MATCH($C8,Accounts!$B$7:$B$16,0))),0)>0),IF($V8>Settings!$C$23*($AP8-N($Q8)),"Risk over max %; ",""),"")&IF(AND(ISNUMBER(Settings!$C$24),ISNUMBER($N8)),IF($N8>Settings!$C$24,"Leverage over max; ",""),"")&IF(AND(ISNUMBER(Settings!$C$27),ISNUMBER($T8)),IF($T8<Settings!$C$27,"R:R below min; ",""),"")&IF(ISNUMBER(Settings!$C$25),IF(COUNTIFS($A$6:$A8,$A8,$AM$6:$AM8,1)>Settings!$C$25,"Over max trades/day; ",""),"")&IF(ISNUMBER(Settings!$C$26),IF(SUMIFS($Q$5:$Q7,$A$5:$A7,$A8)<=-Settings!$C$26,"Traded after daily max loss; ",""),"")&IF(AND($AG8="",NOT(ISNUMBER($O8))),"Symbol not in Instruments; ","")&IF(AND($AH8="",NOT(ISNUMBER($O8))),"Forex cross: type Gross P&L; ","")) | BH8: =IF(ISNUMBER($Q8),1,0) -> 1 | BI8: =IF($Y8="",0,1) -> 1 | BJ8: =IF($AB8="",0,1) -> 0 | BK8: =IF(AND($BH8=1,$W8<>"OK"),1,0) -> 0 | BL8: =IF(N($AZ8)=0,0,IFERROR(INDEX($AT$6:$AT$1005,MATCH($AZ8,$AY$6:$AY$1005,0)),0)) -> 298.5 | BM8: =IF(ISNUMBER(SEARCH("daily max loss",$BG8)),1,0) -> 0
A9: 46287 | B9: 0.46875 | C9: Prop Eval 50K | E9: MCL | F9: Short | G9: 2 | H9: 69.85 | I9: 70.15 | J9: 69.25 | K9: 70.15 | L9: Market | M9: Stop loss | Q9: =IF($AM9=0,"",IF(ISNUMBER($AK9),$AK9-N($AL9),"")) -> -62 | R9: =IF(OR($Q9="",NOT(ISNUMBER($V9))),"",$AK9/$V9) -> -1 | S9: =IF($Q9="","",IF(AND(ISNUMBER($R9),ABS(N($R9))<N(Settings!$C$8)),"Scratch",IF($Q9>0,"Win",IF($Q9<0,"Loss","Scratch")))) -> Loss | T9: =IF(OR($AM9=0,NOT(ISNUMBER($H9)),NOT(ISNUMBER($I9)),NOT(ISNUMBER($J9))),"",IF($H9=$I9,"",ROUND(ABS($J9-$H9)/ABS($H9-$I9),6))) -> 2 | U9: =IF(OR($S9<>"Win",NOT(ISNUMBER($T9)),NOT(ISNUMBER($R9))),"",MAX(0,$T9-$R9)) | V9: =IF(OR($AM9=0,NOT(ISNUMBER($H9)),NOT(ISNUMBER($I9)),NOT(ISNUMBER($G9))),"",IF(OR($AG9="",$AH9=""),"",IF(ROUND(ABS($H9-$I9)*ABS($G9)*$AG9*$AH9,6)=0,"",ROUND(ABS($H9-$I9)*ABS($G9)*$AG9*$AH9,6)))) -> 60 | W9: =IF($AM9=0,"",IF($BG9="","OK",LEFT($BG9,LEN($BG9)-2))) -> OK | X9: NY Midday | Y9: Failed Breakout Reversal | Z9: No | AA9: FOMO | AB9: Late entry (chased) | AC9: Chased the rejection after it already dropped | AD9: Late fill made the stop too tight. | AF9: =IF($AM9=0,"",IF($D9<>"",$D9,IF(IFERROR(INDEX(Accounts!$C$7:$C$16,MATCH($C9,Accounts!$B$7:$B$16,0))&"","")<>"",INDEX(Accounts!$C$7:$C$16,MATCH($C9,Accounts!$B$7:$B$16,0)),Settings!$C$6))) -> Futures | AG9: =IF($AM9=0,"",IF(AND($BE9>0,N(INDEX(Instruments!$D$6:$D$205,MAX(1,$BE9)))>0),INDEX(Instruments!$D$6:$D$205,MAX(1,$BE9)),IF(N(INDEX(Settings!$D$14:$D$18,$BF9))>0,INDEX(Settings!$D$14:$D$18,$BF9),""))) -> 100 | AH9: =IF($AM9=0,"",IF($AF9<>"Forex",1,IF(MID(UPPER(SUBSTITUTE(TRIM($E9),"/","")),4,3)=UPPER(TRIM(Settings!$C$7)),1,IF(LEFT(UPPER(SUBSTITUTE(TRIM($E9),"/","")),3)=UPPER(TRIM(Settings!$C$7)),IF(AND(ISNUMBER($K9),N($K9)<>0),1/$K9,""),"")))) -> 1 | AI9: =IF($AM9=0,"",IF(OR(NOT(ISNUMBER($H9)),NOT(ISNUMBER($K9)),NOT(ISNUMBER($G9)),$AG9="",$AH9=""),"",ROUND(($K9-$H9)*IF($F9="Short",-1,1)*$G9*$AG9*$AH9,6))) -> -60 | AJ9: =IF($AM9=0,"",IF(INDEX(Settings!$E$14:$E$18,$BF9)="% of notional",IF(OR($AG9="",NOT(ISNUMBER($H9)),NOT(ISNUMBER($G9))),"",ROUND(ABS($H9*$G9*$AG9*N($AH9))*IF($L9="Limit",N(INDEX(Settings!$G$14:$G$18,$BF9)),N(INDEX(Settings!$H$14:$H$18,$BF9)))+IF(ISNUMBER($K9),ABS($K9*$G9*$AG9*N($AH9))*IF($M9="Target",N(INDEX(Settings!$G$14:$G$18,$BF9)),N(INDEX(Settings!$H$14:$H$18,$BF9))),0),6)),IF(NOT(ISNUMBER($G9)),"",ROUND(ABS($G9)*2*IF(AND($BE9>0,ISNUMBER(INDEX(Instruments!$G$6:$G$205,MAX(1,$BE9)))),INDEX(Instruments!$G$6:$G$205,MAX(1,$BE9)),N(INDEX(Settings!$F$14:$F$18,$BF9))),6)))) -> 2 | AK9: =IF($AM9=0,"",IF(ISNUMBER($O9),$O9,$AI9)) -> -60 | AL9: =IF($AM9=0,"",IF(ISNUMBER($P9),$P9,N($AJ9))) -> 2 | AM9: =IF(AND($A9<>"",$E9<>"",OR(AND(ISNUMBER($G9),ISNUMBER($H9),ISNUMBER($K9)),ISNUMBER($O9))),1,0) -> 1 | AN9: =IF($A9="","",$A9-WEEKDAY($A9,3)) -> 46286 | AO9: =IF($A9="","",WEEKDAY($A9,2)) -> 2 | AP9: =IF(OR($AM9=0,$C9=""),"",IFERROR(N(INDEX(Accounts!$E$7:$E$16,MATCH($C9,Accounts!$B$7:$B$16,0))),0)+SUMIFS($Q$6:$Q9,$C$6:$C9,$C9)) -> 50355.5 | AQ9: =IF(OR($AM9=0,$C9=""),"",SUMIFS($Q$6:$Q$1005,$C$6:$C$1005,$C9,$A$6:$A$1005,$A9)) -> 57 | AR9: =IF(OR($AM9=0,$C9=""),"",IFERROR(N(INDEX(Accounts!$E$7:$E$16,MATCH($C9,Accounts!$B$7:$B$16,0))),0)+SUMIFS($Q$6:$Q$1005,$C$6:$C$1005,$C9,$A$6:$A$1005,"<="&$A9)) -> 50355.5 | AS9: =IF(OR($AM9=0,$Q9=""),0,IF(AND($A9>=Lists!$W$6,$A9<=Lists!$W$7,OR(Dashboard!$D$6="All accounts",$C9=Dashboard!$D$6),OR(Dashboard!$D$7="All markets",$AF9=Dashboard!$D$7)),1,0)) -> 1 | AT9: =IF($AS9=1,N(AT8)+$Q9,N(AT8)) -> 355.5 | AU9: =MAX(N(AU8),$AT9) -> 417.5 | AV9: =$AT9-$AU9 -> -62 | AW9: =IF($AS9=1,IF($S9="Win",N(AW8)+1,IF($S9="Loss",0,N(AW8))),N(AW8)) -> 0 | AX9: =IF($AS9=1,IF($S9="Loss",N(AX8)+1,IF($S9="Win",0,N(AX8))),N(AX8)) -> 1 | AY9: =IF($AS9=1,COUNTIF($AS$6:$AS9,1),"") -> 4 | AZ9: =MIN(3,N(Lists!$W$8)) -> 3 | BA9: =IF($AS9=1,IF(COUNTIFS($A$6:$A9,$A9,$AS$6:$AS9,1)=1,1,0),0) -> 0 | BB9: =IF($BA9=1,SUMIFS($Q$6:$Q$1005,$A$6:$A$1005,$A9,$AS$6:$AS$1005,1),"") | BC9: =IF(ISNUMBER($R9),1,0) -> 1 | BD9: =IF(ISNUMBER($U9),$U9*$V9,"") | BE9: =IF($AM9=0,"",IFERROR(MATCH($AF9&"|"&UPPER(TRIM($E9)),Lists!$A$6:$A$205,0),0)) -> 9 | BF9: =IF($AM9=0,"",IFERROR(MATCH($AF9,Settings!$B$14:$B$18,0),IFERROR(MATCH(Settings!$C$6,Settings!$B$14:$B$18,0),1))) -> 1 | BG9: =IF($AM9=0,"",IF(NOT(ISNUMBER($I9)),"No stop; ","")&IF(AND(ISNUMBER($H9),ISNUMBER($I9)),IF(OR(AND($F9<>"Short",$I9>=$H9),AND($F9="Short",$I9<=$H9)),"Stop on wrong side; ",""),"")&IF($F9="","No direction; ","")&IF(AND(ISNUMBER(Settings!$C$22),ISNUMBER($V9)),IF($V9>Settings!$C$22,"Risk over max $; ",""),"")&IF(AND(ISNUMBER(Settings!$C$23),ISNUMBER($V9),ISNUMBER($AP9),IFERROR(N(INDEX(Accounts!$E$7:$E$16,MATCH($C9,Accounts!$B$7:$B$16,0))),0)>0),IF($V9>Settings!$C$23*($AP9-N($Q9)),"Risk over max %; ",""),"")&IF(AND(ISNUMBER(Settings!$C$24),ISNUMBER($N9)),IF($N9>Settings!$C$24,"Leverage over max; ",""),"")&IF(AND(ISNUMBER(Settings!$C$27),ISNUMBER($T9)),IF($T9<Settings!$C$27,"R:R below min; ",""),"")&IF(ISNUMBER(Settings!$C$25),IF(COUNTIFS($A$6:$A9,$A9,$AM$6:$AM9,1)>Settings!$C$25,"Over max trades/day; ",""),"")&IF(ISNUMBER(Settings!$C$26),IF(SUMIFS($Q$5:$Q8,$A$5:$A8,$A9)<=-Settings!$C$26,"Traded after daily max loss; ",""),"")&IF(AND($AG9="",NOT(ISNUMBER($O9))),"Symbol not in Instruments; ","")&IF(AND($AH9="",NOT(ISNUMBER($O9))),"Forex cross: type Gross P&L; ","")) | BH9: =IF(ISNUMBER($Q9),1,0) -> 1 | BI9: =IF($Y9="",0,1) -> 1 | BJ9: =IF($AB9="",0,1) -> 1 | BK9: =IF(AND($BH9=1,$W9<>"OK"),1,0) -> 0 | BL9: =IF(N($AZ9)=0,0,IFERROR(INDEX($AT$6:$AT$1005,MATCH($AZ9,$AY$6:$AY$1005,0)),0)) -> 417.5 | BM9: =IF(ISNUMBER(SEARCH("daily max loss",$BG9)),1,0) -> 0
A10: 46287 | B10: 0.88541667 | C10: Crypto Main | E10: BTCUSDT | F10: Long | G10: 0.05 | H10: 64200 | I10: 63600 | J10: 65400 | K10: 65400 | L10: Limit | M10: Target | N10: 10 | Q10: =IF($AM10=0,"",IF(ISNUMBER($AK10),$AK10-N($AL10),"")) -> 58.704 | R10: =IF(OR($Q10="",NOT(ISNUMBER($V10))),"",$AK10/$V10) -> 2 | S10: =IF($Q10="","",IF(AND(ISNUMBER($R10),ABS(N($R10))<N(Settings!$C$8)),"Scratch",IF($Q10>0,"Win",IF($Q10<0,"Loss","Scratch")))) -> Win | T10: =IF(OR($AM10=0,NOT(ISNUMBER($H10)),NOT(ISNUMBER($I10)),NOT(ISNUMBER($J10))),"",IF($H10=$I10,"",ROUND(ABS($J10-$H10)/ABS($H10-$I10),6))) -> 2 | U10: =IF(OR($S10<>"Win",NOT(ISNUMBER($T10)),NOT(ISNUMBER($R10))),"",MAX(0,$T10-$R10)) -> 0 | V10: =IF(OR($AM10=0,NOT(ISNUMBER($H10)),NOT(ISNUMBER($I10)),NOT(ISNUMBER($G10))),"",IF(OR($AG10="",$AH10=""),"",IF(ROUND(ABS($H10-$I10)*ABS($G10)*$AG10*$AH10,6)=0,"",ROUND(ABS($H10-$I10)*ABS($G10)*$AG10*$AH10,6)))) -> 30 | W10: =IF($AM10=0,"",IF($BG10="","OK",LEFT($BG10,LEN($BG10)-2))) -> OK | X10: US | Y10: Breakout & Retest | Z10: Yes | AA10: Calm | AC10: Reclaimed 64k and held | AD10: Clean. | AF10: =IF($AM10=0,"",IF($D10<>"",$D10,IF(IFERROR(INDEX(Accounts!$C$7:$C$16,MATCH($C10,Accounts!$B$7:$B$16,0))&"","")<>"",INDEX(Accounts!$C$7:$C$16,MATCH($C10,Accounts!$B$7:$B$16,0)),Settings!$C$6))) -> Crypto | AG10: =IF($AM10=0,"",IF(AND($BE10>0,N(INDEX(Instruments!$D$6:$D$205,MAX(1,$BE10)))>0),INDEX(Instruments!$D$6:$D$205,MAX(1,$BE10)),IF(N(INDEX(Settings!$D$14:$D$18,$BF10))>0,INDEX(Settings!$D$14:$D$18,$BF10),""))) -> 1 | AH10: =IF($AM10=0,"",IF($AF10<>"Forex",1,IF(MID(UPPER(SUBSTITUTE(TRIM($E10),"/","")),4,3)=UPPER(TRIM(Settings!$C$7)),1,IF(LEFT(UPPER(SUBSTITUTE(TRIM($E10),"/","")),3)=UPPER(TRIM(Settings!$C$7)),IF(AND(ISNUMBER($K10),N($K10)<>0),1/$K10,""),"")))) -> 1 | AI10: =IF($AM10=0,"",IF(OR(NOT(ISNUMBER($H10)),NOT(ISNUMBER($K10)),NOT(ISNUMBER($G10)),$AG10="",$AH10=""),"",ROUND(($K10-$H10)*IF($F10="Short",-1,1)*$G10*$AG10*$AH10,6))) -> 60 | AJ10: =IF($AM10=0,"",IF(INDEX(Settings!$E$14:$E$18,$BF10)="% of notional",IF(OR($AG10="",NOT(ISNUMBER($H10)),NOT(ISNUMBER($G10))),"",ROUND(ABS($H10*$G10*$AG10*N($AH10))*IF($L10="Limit",N(INDEX(Settings!$G$14:$G$18,$BF10)),N(INDEX(Settings!$H$14:$H$18,$BF10)))+IF(ISNUMBER($K10),ABS($K10*$G10*$AG10*N($AH10))*IF($M10="Target",N(INDEX(Settings!$G$14:$G$18,$BF10)),N(INDEX(Settings!$H$14:$H$18,$BF10))),0),6)),IF(NOT(ISNUMBER($G10)),"",ROUND(ABS($G10)*2*IF(AND($BE10>0,ISNUMBER(INDEX(Instruments!$G$6:$G$205,MAX(1,$BE10)))),INDEX(Instruments!$G$6:$G$205,MAX(1,$BE10)),N(INDEX(Settings!$F$14:$F$18,$BF10))),6)))) -> 1.296 | AK10: =IF($AM10=0,"",IF(ISNUMBER($O10),$O10,$AI10)) -> 60 | AL10: =IF($AM10=0,"",IF(ISNUMBER($P10),$P10,N($AJ10))) -> 1.296 | AM10: =IF(AND($A10<>"",$E10<>"",OR(AND(ISNUMBER($G10),ISNUMBER($H10),ISNUMBER($K10)),ISNUMBER($O10))),1,0) -> 1 | AN10: =IF($A10="","",$A10-WEEKDAY($A10,3)) -> 46286 | AO10: =IF($A10="","",WEEKDAY($A10,2)) -> 2 | AP10: =IF(OR($AM10=0,$C10=""),"",IFERROR(N(INDEX(Accounts!$E$7:$E$16,MATCH($C10,Accounts!$B$7:$B$16,0))),0)+SUMIFS($Q$6:$Q10,$C$6:$C10,$C10)) -> 5058.704 | AQ10: =IF(OR($AM10=0,$C10=""),"",SUMIFS($Q$6:$Q$1005,$C$6:$C$1005,$C10,$A$6:$A$1005,$A10)) -> 58.704 | AR10: =IF(OR($AM10=0,$C10=""),"",IFERROR(N(INDEX(Accounts!$E$7:$E$16,MATCH($C10,Accounts!$B$7:$B$16,0))),0)+SUMIFS($Q$6:$Q$1005,$C$6:$C$1005,$C10,$A$6:$A$1005,"<="&$A10)) -> 5058.704 | AS10: =IF(OR($AM10=0,$Q10=""),0,IF(AND($A10>=Lists!$W$6,$A10<=Lists!$W$7,OR(Dashboard!$D$6="All accounts",$C10=Dashboard!$D$6),OR(Dashboard!$D$7="All markets",$AF10=Dashboard!$D$7)),1,0)) -> 1 | AT10: =IF($AS10=1,N(AT9)+$Q10,N(AT9)) -> 414.204 | AU10: =MAX(N(AU9),$AT10) -> 417.5 | AV10: =$AT10-$AU10 -> -3.296 | AW10: =IF($AS10=1,IF($S10="Win",N(AW9)+1,IF($S10="Loss",0,N(AW9))),N(AW9)) -> 1 | AX10: =IF($AS10=1,IF($S10="Loss",N(AX9)+1,IF($S10="Win",0,N(AX9))),N(AX9)) -> 0 | AY10: =IF($AS10=1,COUNTIF($AS$6:$AS10,1),"") -> 5 | AZ10: =MIN(4,N(Lists!$W$8)) -> 4 | BA10: =IF($AS10=1,IF(COUNTIFS($A$6:$A10,$A10,$AS$6:$AS10,1)=1,1,0),0) -> 0 | BB10: =IF($BA10=1,SUMIFS($Q$6:$Q$1005,$A$6:$A$1005,$A10,$AS$6:$AS$1005,1),"") | BC10: =IF(ISNUMBER($R10),1,0) -> 1 | BD10: =IF(ISNUMBER($U10),$U10*$V10,"") -> 0 | BE10: =IF($AM10=0,"",IFERROR(MATCH($AF10&"|"&UPPER(TRIM($E10)),Lists!$A$6:$A$205,0),0)) -> 46 | BF10: =IF($AM10=0,"",IFERROR(MATCH($AF10,Settings!$B$14:$B$18,0),IFERROR(MATCH(Settings!$C$6,Settings!$B$14:$B$18,0),1))) -> 5 | BG10: =IF($AM10=0,"",IF(NOT(ISNUMBER($I10)),"No stop; ","")&IF(AND(ISNUMBER($H10),ISNUMBER($I10)),IF(OR(AND($F10<>"Short",$I10>=$H10),AND($F10="Short",$I10<=$H10)),"Stop on wrong side; ",""),"")&IF($F10="","No direction; ","")&IF(AND(ISNUMBER(Settings!$C$22),ISNUMBER($V10)),IF($V10>Settings!$C$22,"Risk over max $; ",""),"")&IF(AND(ISNUMBER(Settings!$C$23),ISNUMBER($V10),ISNUMBER($AP10),IFERROR(N(INDEX(Accounts!$E$7:$E$16,MATCH($C10,Accounts!$B$7:$B$16,0))),0)>0),IF($V10>Settings!$C$23*($AP10-N($Q10)),"Risk over max %; ",""),"")&IF(AND(ISNUMBER(Settings!$C$24),ISNUMBER($N10)),IF($N10>Settings!$C$24,"Leverage over max; ",""),"")&IF(AND(ISNUMBER(Settings!$C$27),ISNUMBER($T10)),IF($T10<Settings!$C$27,"R:R below min; ",""),"")&IF(ISNUMBER(Settings!$C$25),IF(COUNTIFS($A$6:$A10,$A10,$AM$6:$AM10,1)>Settings!$C$25,"Over max trades/day; ",""),"")&IF(ISNUMBER(Settings!$C$26),IF(SUMIFS($Q$5:$Q9,$A$5:$A9,$A10)<=-Settings!$C$26,"Traded after daily max loss; ",""),"")&IF(AND($AG10="",NOT(ISNUMBER($O10))),"Symbol not in Instruments; ","")&IF(AND($AH10="",NOT(ISNUMBER($O10))),"Forex cross: type Gross P&L; ","")) | BH10: =IF(ISNUMBER($Q10),1,0) -> 1 | BI10: =IF($Y10="",0,1) -> 1 | BJ10: =IF($AB10="",0,1) -> 0 | BK10: =IF(AND($BH10=1,$W10<>"OK"),1,0) -> 0 | BL10: =IF(N($AZ10)=0,0,IFERROR(INDEX($AT$6:$AT$1005,MATCH($AZ10,$AY$6:$AY$1005,0)),0)) -> 355.5 | BM10: =IF(ISNUMBER(SEARCH("daily max loss",$BG10)),1,0) -> 0
A11: 46288 | B11: 0.40833333 | C11: Prop Eval 50K | E11: MNQ | F11: Short | G11: 1 | H11: 29815 | I11: 29845 | J11: 29755 | K11: 29757.5 | L11: Limit | M11: Manual | Q11: =IF($AM11=0,"",IF(ISNUMBER($AK11),$AK11-N($AL11),"")) -> 114 | R11: =IF(OR($Q11="",NOT(ISNUMBER($V11))),"",$AK11/$V11) -> 1.9166667 | S11: =IF($Q11="","",IF(AND(ISNUMBER($R11),ABS(N($R11))<N(Settings!$C$8)),"Scratch",IF($Q11>0,"Win",IF($Q11<0,"Loss","Scratch")))) -> Win | T11: =IF(OR($AM11=0,NOT(ISNUMBER($H11)),NOT(ISNUMBER($I11)),NOT(ISNUMBER($J11))),"",IF($H11=$I11,"",ROUND(ABS($J11-$H11)/ABS($H11-$I11),6))) -> 2 | U11: =IF(OR($S11<>"Win",NOT(ISNUMBER($T11)),NOT(ISNUMBER($R11))),"",MAX(0,$T11-$R11)) -> 0.083333333 | V11: =IF(OR($AM11=0,NOT(ISNUMBER($H11)),NOT(ISNUMBER($I11)),NOT(ISNUMBER($G11))),"",IF(OR($AG11="",$AH11=""),"",IF(ROUND(ABS($H11-$I11)*ABS($G11)*$AG11*$AH11,6)=0,"",ROUND(ABS($H11-$I11)*ABS($G11)*$AG11*$AH11,6)))) -> 60 | W11: =IF($AM11=0,"",IF($BG11="","OK",LEFT($BG11,LEN($BG11)-2))) -> OK | X11: NY Open | Y11: Range Fade | Z11: Yes | AA11: Confident | AC11: Faded the top of a 2-day range | AD11: Closed 2 ticks before target. Fine. | AF11: =IF($AM11=0,"",IF($D11<>"",$D11,IF(IFERROR(INDEX(Accounts!$C$7:$C$16,MATCH($C11,Accounts!$B$7:$B$16,0))&"","")<>"",INDEX(Accounts!$C$7:$C$16,MATCH($C11,Accounts!$B$7:$B$16,0)),Settings!$C$6))) -> Futures | AG11: =IF($AM11=0,"",IF(AND($BE11>0,N(INDEX(Instruments!$D$6:$D$205,MAX(1,$BE11)))>0),INDEX(Instruments!$D$6:$D$205,MAX(1,$BE11)),IF(N(INDEX(Settings!$D$14:$D$18,$BF11))>0,INDEX(Settings!$D$14:$D$18,$BF11),""))) -> 2 | AH11: =IF($AM11=0,"",IF($AF11<>"Forex",1,IF(MID(UPPER(SUBSTITUTE(TRIM($E11),"/","")),4,3)=UPPER(TRIM(Settings!$C$7)),1,IF(LEFT(UPPER(SUBSTITUTE(TRIM($E11),"/","")),3)=UPPER(TRIM(Settings!$C$7)),IF(AND(ISNUMBER($K11),N($K11)<>0),1/$K11,""),"")))) -> 1 | AI11: =IF($AM11=0,"",IF(OR(NOT(ISNUMBER($H11)),NOT(ISNUMBER($K11)),NOT(ISNUMBER($G11)),$AG11="",$AH11=""),"",ROUND(($K11-$H11)*IF($F11="Short",-1,1)*$G11*$AG11*$AH11,6))) -> 115 | AJ11: =IF($AM11=0,"",IF(INDEX(Settings!$E$14:$E$18,$BF11)="% of notional",IF(OR($AG11="",NOT(ISNUMBER($H11)),NOT(ISNUMBER($G11))),"",ROUND(ABS($H11*$G11*$AG11*N($AH11))*IF($L11="Limit",N(INDEX(Settings!$G$14:$G$18,$BF11)),N(INDEX(Settings!$H$14:$H$18,$BF11)))+IF(ISNUMBER($K11),ABS($K11*$G11*$AG11*N($AH11))*IF($M11="Target",N(INDEX(Settings!$G$14:$G$18,$BF11)),N(INDEX(Settings!$H$14:$H$18,$BF11))),0),6)),IF(NOT(ISNUMBER($G11)),"",ROUND(ABS($G11)*2*IF(AND($BE11>0,ISNUMBER(INDEX(Instruments!$G$6:$G$205,MAX(1,$BE11)))),INDEX(Instruments!$G$6:$G$205,MAX(1,$BE11)),N(INDEX(Settings!$F$14:$F$18,$BF11))),6)))) -> 1 | AK11: =IF($AM11=0,"",IF(ISNUMBER($O11),$O11,$AI11)) -> 115 | AL11: =IF($AM11=0,"",IF(ISNUMBER($P11),$P11,N($AJ11))) -> 1 | AM11: =IF(AND($A11<>"",$E11<>"",OR(AND(ISNUMBER($G11),ISNUMBER($H11),ISNUMBER($K11)),ISNUMBER($O11))),1,0) -> 1 | AN11: =IF($A11="","",$A11-WEEKDAY($A11,3)) -> 46286 | AO11: =IF($A11="","",WEEKDAY($A11,2)) -> 3 | AP11: =IF(OR($AM11=0,$C11=""),"",IFERROR(N(INDEX(Accounts!$E$7:$E$16,MATCH($C11,Accounts!$B$7:$B$16,0))),0)+SUMIFS($Q$6:$Q11,$C$6:$C11,$C11)) -> 50469.5 | AQ11: =IF(OR($AM11=0,$C11=""),"",SUMIFS($Q$6:$Q$1005,$C$6:$C$1005,$C11,$A$6:$A$1005,$A11)) -> 6 | AR11: =IF(OR($AM11=0,$C11=""),"",IFERROR(N(INDEX(Accounts!$E$7:$E$16,MATCH($C11,Accounts!$B$7:$B$16,0))),0)+SUMIFS($Q$6:$Q$1005,$C$6:$C$1005,$C11,$A$6:$A$1005,"<="&$A11)) -> 50361.5 | AS11: =IF(OR($AM11=0,$Q11=""),0,IF(AND($A11>=Lists!$W$6,$A11<=Lists!$W$7,OR(Dashboard!$D$6="All accounts",$C11=Dashboard!$D$6),OR(Dashboard!$D$7="All markets",$AF11=Dashboard!$D$7)),1,0)) -> 1 | AT11: =IF($AS11=1,N(AT10)+$Q11,N(AT10)) -> 528.204 | AU11: =MAX(N(AU10),$AT11) -> 528.204 | AV11: =$AT11-$AU11 -> 0 | AW11: =IF($AS11=1,IF($S11="Win",N(AW10)+1,IF($S11="Loss",0,N(AW10))),N(AW10)) -> 2 | AX11: =IF($AS11=1,IF($S11="Loss",N(AX10)+1,IF($S11="Win",0,N(AX10))),N(AX10)) -> 0 | AY11: =IF($AS11=1,COUNTIF($AS$6:$AS11,1),"") -> 6 | AZ11: =MIN(5,N(Lists!$W$8)) -> 5 | BA11: =IF($AS11=1,IF(COUNTIFS($A$6:$A11,$A11,$AS$6:$AS11,1)=1,1,0),0) -> 1 | BB11: =IF($BA11=1,SUMIFS($Q$6:$Q$1005,$A$6:$A$1005,$A11,$AS$6:$AS$1005,1),"") -> 6 | BC11: =IF(ISNUMBER($R11),1,0) -> 1 | BD11: =IF(ISNUMBER($U11),$U11*$V11,"") -> 5 | BE11: =IF($AM11=0,"",IFERROR(MATCH($AF11&"|"&UPPER(TRIM($E11)),Lists!$A$6:$A$205,0),0)) -> 3 | BF11: =IF($AM11=0,"",IFERROR(MATCH($AF11,Settings!$B$14:$B$18,0),IFERROR(MATCH(Settings!$C$6,Settings!$B$14:$B$18,0),1))) -> 1 | BG11: =IF($AM11=0,"",IF(NOT(ISNUMBER($I11)),"No stop; ","")&IF(AND(ISNUMBER($H11),ISNUMBER($I11)),IF(OR(AND($F11<>"Short",$I11>=$H11),AND($F11="Short",$I11<=$H11)),"Stop on wrong side; ",""),"")&IF($F11="","No direction; ","")&IF(AND(ISNUMBER(Settings!$C$22),ISNUMBER($V11)),IF($V11>Settings!$C$22,"Risk over max $; ",""),"")&IF(AND(ISNUMBER(Settings!$C$23),ISNUMBER($V11),ISNUMBER($AP11),IFERROR(N(INDEX(Accounts!$E$7:$E$16,MATCH($C11,Accounts!$B$7:$B$16,0))),0)>0),IF($V11>Settings!$C$23*($AP11-N($Q11)),"Risk over max %; ",""),"")&IF(AND(ISNUMBER(Settings!$C$24),ISNUMBER($N11)),IF($N11>Settings!$C$24,"Leverage over max; ",""),"")&IF(AND(ISNUMBER(Settings!$C$27),ISNUMBER($T11)),IF($T11<Settings!$C$27,"R:R below min; ",""),"")&IF(ISNUMBER(Settings!$C$25),IF(COUNTIFS($A$6:$A11,$A11,$AM$6:$AM11,1)>Settings!$C$25,"Over max trades/day; ",""),"")&IF(ISNUMBER(Settings!$C$26),IF(SUMIFS($Q$5:$Q10,$A$5:$A10,$A11)<=-Settings!$C$26,"Traded after daily max loss; ",""),"")&IF(AND($AG11="",NOT(ISNUMBER($O11))),"Symbol not in Instruments; ","")&IF(AND($AH11="",NOT(ISNUMBER($O11))),"Forex cross: type Gross P&L; ","")) | BH11: =IF(ISNUMBER($Q11),1,0) -> 1 | BI11: =IF($Y11="",0,1) -> 1 | BJ11: =IF($AB11="",0,1) -> 0 | BK11: =IF(AND($BH11=1,$W11<>"OK"),1,0) -> 0 | BL11: =IF(N($AZ11)=0,0,IFERROR(INDEX($AT$6:$AT$1005,MATCH($AZ11,$AY$6:$AY$1005,0)),0)) -> 414.204 | BM11: =IF(ISNUMBER(SEARCH("daily max loss",$BG11)),1,0) -> 0
A12: 46288 | B12: 0.55555556 | C12: Prop Eval 50K | E12: MES | F12: Long | G12: 3 | H12: 7690 | I12: 7683 | J12: 7704 | K12: 7683 | L12: Market | M12: Stop loss | Q12: =IF($AM12=0,"",IF(ISNUMBER($AK12),$AK12-N($AL12),"")) -> -108 | R12: =IF(OR($Q12="",NOT(ISNUMBER($V12))),"",$AK12/$V12) -> -1 | S12: =IF($Q12="","",IF(AND(ISNUMBER($R12),ABS(N($R12))<N(Settings!$C$8)),"Scratch",IF($Q12>0,"Win",IF($Q12<0,"Loss","Scratch")))) -> Loss | T12: =IF(OR($AM12=0,NOT(ISNUMBER($H12)),NOT(ISNUMBER($I12)),NOT(ISNUMBER($J12))),"",IF($H12=$I12,"",ROUND(ABS($J12-$H12)/ABS($H12-$I12),6))) -> 2 | U12: =IF(OR($S12<>"Win",NOT(ISNUMBER($T12)),NOT(ISNUMBER($R12))),"",MAX(0,$T12-$R12)) | V12: =IF(OR($AM12=0,NOT(ISNUMBER($H12)),NOT(ISNUMBER($I12)),NOT(ISNUMBER($G12))),"",IF(OR($AG12="",$AH12=""),"",IF(ROUND(ABS($H12-$I12)*ABS($G12)*$AG12*$AH12,6)=0,"",ROUND(ABS($H12-$I12)*ABS($G12)*$AG12*$AH12,6)))) -> 105 | W12: =IF($AM12=0,"",IF($BG12="","OK",LEFT($BG12,LEN($BG12)-2))) -> OK | X12: NY Afternoon | Z12: No | AA12: Bored | AB12: No setup (impulse) | AC12: Chop. Wanted action. | AD12: No setup. Should have walked away. | AF12: =IF($AM12=0,"",IF($D12<>"",$D12,IF(IFERROR(INDEX(Accounts!$C$7:$C$16,MATCH($C12,Accounts!$B$7:$B$16,0))&"","")<>"",INDEX(Accounts!$C$7:$C$16,MATCH($C12,Accounts!$B$7:$B$16,0)),Settings!$C$6))) -> Futures | AG12: =IF($AM12=0,"",IF(AND($BE12>0,N(INDEX(Instruments!$D$6:$D$205,MAX(1,$BE12)))>0),INDEX(Instruments!$D$6:$D$205,MAX(1,$BE12)),IF(N(INDEX(Settings!$D$14:$D$18,$BF12))>0,INDEX(Settings!$D$14:$D$18,$BF12),""))) -> 5 | AH12: =IF($AM12=0,"",IF($AF12<>"Forex",1,IF(MID(UPPER(SUBSTITUTE(TRIM($E12),"/","")),4,3)=UPPER(TRIM(Settings!$C$7)),1,IF(LEFT(UPPER(SUBSTITUTE(TRIM($E12),"/","")),3)=UPPER(TRIM(Settings!$C$7)),IF(AND(ISNUMBER($K12),N($K12)<>0),1/$K12,""),"")))) -> 1 | AI12: =IF($AM12=0,"",IF(OR(NOT(ISNUMBER($H12)),NOT(ISNUMBER($K12)),NOT(ISNUMBER($G12)),$AG12="",$AH12=""),"",ROUND(($K12-$H12)*IF($F12="Short",-1,1)*$G12*$AG12*$AH12,6))) -> -105 | AJ12: =IF($AM12=0,"",IF(INDEX(Settings!$E$14:$E$18,$BF12)="% of notional",IF(OR($AG12="",NOT(ISNUMBER($H12)),NOT(ISNUMBER($G12))),"",ROUND(ABS($H12*$G12*$AG12*N($AH12))*IF($L12="Limit",N(INDEX(Settings!$G$14:$G$18,$BF12)),N(INDEX(Settings!$H$14:$H$18,$BF12)))+IF(ISNUMBER($K12),ABS($K12*$G12*$AG12*N($AH12))*IF($M12="Target",N(INDEX(Settings!$G$14:$G$18,$BF12)),N(INDEX(Settings!$H$14:$H$18,$BF12))),0),6)),IF(NOT(ISNUMBER($G12)),"",ROUND(ABS($G12)*2*IF(AND($BE12>0,ISNUMBER(INDEX(Instruments!$G$6:$G$205,MAX(1,$BE12)))),INDEX(Instruments!$G$6:$G$205,MAX(1,$BE12)),N(INDEX(Settings!$F$14:$F$18,$BF12))),6)))) -> 3 | AK12: =IF($AM12=0,"",IF(ISNUMBER($O12),$O12,$AI12)) -> -105 | AL12: =IF($AM12=0,"",IF(ISNUMBER($P12),$P12,N($AJ12))) -> 3 | AM12: =IF(AND($A12<>"",$E12<>"",OR(AND(ISNUMBER($G12),ISNUMBER($H12),ISNUMBER($K12)),ISNUMBER($O12))),1,0) -> 1 | AN12: =IF($A12="","",$A12-WEEKDAY($A12,3)) -> 46286 | AO12: =IF($A12="","",WEEKDAY($A12,2)) -> 3 | AP12: =IF(OR($AM12=0,$C12=""),"",IFERROR(N(INDEX(Accounts!$E$7:$E$16,MATCH($C12,Accounts!$B$7:$B$16,0))),0)+SUMIFS($Q$6:$Q12,$C$6:$C12,$C12)) -> 50361.5 | AQ12: =IF(OR($AM12=0,$C12=""),"",SUMIFS($Q$6:$Q$1005,$C$6:$C$1005,$C12,$A$6:$A$1005,$A12)) -> 6 | AR12: =IF(OR($AM12=0,$C12=""),"",IFERROR(N(INDEX(Accounts!$E$7:$E$16,MATCH($C12,Accounts!$B$7:$B$16,0))),0)+SUMIFS($Q$6:$Q$1005,$C$6:$C$1005,$C12,$A$6:$A$1005,"<="&$A12)) -> 50361.5 | AS12: =IF(OR($AM12=0,$Q12=""),0,IF(AND($A12>=Lists!$W$6,$A12<=Lists!$W$7,OR(Dashboard!$D$6="All accounts",$C12=Dashboard!$D$6),OR(Dashboard!$D$7="All markets",$AF12=Dashboard!$D$7)),1,0)) -> 1 | AT12: =IF($AS12=1,N(AT11)+$Q12,N(AT11)) -> 420.204 | AU12: =MAX(N(AU11),$AT12) -> 528.204 | AV12: =$AT12-$AU12 -> -108 | AW12: =IF($AS12=1,IF($S12="Win",N(AW11)+1,IF($S12="Loss",0,N(AW11))),N(AW11)) -> 0 | AX12: =IF($AS12=1,IF($S12="Loss",N(AX11)+1,IF($S12="Win",0,N(AX11))),N(AX11)) -> 1 | AY12: =IF($AS12=1,COUNTIF($AS$6:$AS12,1),"") -> 7 | AZ12: =MIN(6,N(Lists!$W$8)) -> 6 | BA12: =IF($AS12=1,IF(COUNTIFS($A$6:$A12,$A12,$AS$6:$AS12,1)=1,1,0),0) -> 0 | BB12: =IF($BA12=1,SUMIFS($Q$6:$Q$1005,$A$6:$A$1005,$A12,$AS$6:$AS$1005,1),"") | BC12: =IF(ISNUMBER($R12),1,0) -> 1 | BD12: =IF(ISNUMBER($U12),$U12*$V12,"") | BE12: =IF($AM12=0,"",IFERROR(MATCH($AF12&"|"&UPPER(TRIM($E12)),Lists!$A$6:$A$205,0),0)) -> 1 | BF12: =IF($AM12=0,"",IFERROR(MATCH($AF12,Settings!$B$14:$B$18,0),IFERROR(MATCH(Settings!$C$6,Settings!$B$14:$B$18,0),1))) -> 1 | BG12: =IF($AM12=0,"",IF(NOT(ISNUMBER($I12)),"No stop; ","")&IF(AND(ISNUMBER($H12),ISNUMBER($I12)),IF(OR(AND($F12<>"Short",$I12>=$H12),AND($F12="Short",$I12<=$H12)),"Stop on wrong side; ",""),"")&IF($F12="","No direction; ","")&IF(AND(ISNUMBER(Settings!$C$22),ISNUMBER($V12)),IF($V12>Settings!$C$22,"Risk over max $; ",""),"")&IF(AND(ISNUMBER(Settings!$C$23),ISNUMBER($V12),ISNUMBER($AP12),IFERROR(N(INDEX(Accounts!$E$7:$E$16,MATCH($C12,Accounts!$B$7:$B$16,0))),0)>0),IF($V12>Settings!$C$23*($AP12-N($Q12)),"Risk over max %; ",""),"")&IF(AND(ISNUMBER(Settings!$C$24),ISNUMBER($N12)),IF($N12>Settings!$C$24,"Leverage over max; ",""),"")&IF(AND(ISNUMBER(Settings!$C$27),ISNUMBER($T12)),IF($T12<Settings!$C$27,"R:R below min; ",""),"")&IF(ISNUMBER(Settings!$C$25),IF(COUNTIFS($A$6:$A12,$A12,$AM$6:$AM12,1)>Settings!$C$25,"Over max trades/day; ",""),"")&IF(ISNUMBER(Settings!$C$26),IF(SUMIFS($Q$5:$Q11,$A$5:$A11,$A12)<=-Settings!$C$26,"Traded after daily max loss; ",""),"")&IF(AND($AG12="",NOT(ISNUMBER($O12))),"Symbol not in Instruments; ","")&IF(AND($AH12="",NOT(ISNUMBER($O12))),"Forex cross: type Gross P&L; ","")) | BH12: =IF(ISNUMBER($Q12),1,0) -> 1 | BI12: =IF($Y12="",0,1) -> 0 | BJ12: =IF($AB12="",0,1) -> 1 | BK12: =IF(AND($BH12=1,$W12<>"OK"),1,0) -> 0 | BL12: =IF(N($AZ12)=0,0,IFERROR(INDEX($AT$6:$AT$1005,MATCH($AZ12,$AY$6:$AY$1005,0)),0)) -> 528.204 | BM12: =IF(ISNUMBER(SEARCH("daily max loss",$BG12)),1,0) -> 0
A13: 46289 | B13: 0.39930556 | C13: Prop Eval 50K | E13: SIL | F13: Long | G13: 1 | H13: 51.2 | I13: 51.05 | J13: 51.5 | K13: 51.5 | L13: Limit | M13: Target | Q13: =IF($AM13=0,"",IF(ISNUMBER($AK13),$AK13-N($AL13),"")) -> 299 | R13: =IF(OR($Q13="",NOT(ISNUMBER($V13))),"",$AK13/$V13) -> 2 | S13: =IF($Q13="","",IF(AND(ISNUMBER($R13),ABS(N($R13))<N(Settings!$C$8)),"Scratch",IF($Q13>0,"Win",IF($Q13<0,"Loss","Scratch")))) -> Win | T13: =IF(OR($AM13=0,NOT(ISNUMBER($H13)),NOT(ISNUMBER($I13)),NOT(ISNUMBER($J13))),"",IF($H13=$I13,"",ROUND(ABS($J13-$H13)/ABS($H13-$I13),6))) -> 2 | U13: =IF(OR($S13<>"Win",NOT(ISNUMBER($T13)),NOT(ISNUMBER($R13))),"",MAX(0,$T13-$R13)) -> 0 | V13: =IF(OR($AM13=0,NOT(ISNUMBER($H13)),NOT(ISNUMBER($I13)),NOT(ISNUMBER($G13))),"",IF(OR($AG13="",$AH13=""),"",IF(ROUND(ABS($H13-$I13)*ABS($G13)*$AG13*$AH13,6)=0,"",ROUND(ABS($H13-$I13)*ABS($G13)*$AG13*$AH13,6)))) -> 150 | W13: =IF($AM13=0,"",IF($BG13="","OK",LEFT($BG13,LEN($BG13)-2))) -> OK | X13: NY Open | Y13: Trend Pullback | Z13: Yes | AA13: Calm | AC13: Silver pulled back to VWAP in an uptrend | AD13: Patient entry, held to target. | AF13: =IF($AM13=0,"",IF($D13<>"",$D13,IF(IFERROR(INDEX(Accounts!$C$7:$C$16,MATCH($C13,Accounts!$B$7:$B$16,0))&"","")<>"",INDEX(Accounts!$C$7:$C$16,MATCH($C13,Accounts!$B$7:$B$16,0)),Settings!$C$6))) -> Futures | AG13: =IF($AM13=0,"",IF(AND($BE13>0,N(INDEX(Instruments!$D$6:$D$205,MAX(1,$BE13)))>0),INDEX(Instruments!$D$6:$D$205,MAX(1,$BE13)),IF(N(INDEX(Settings!$D$14:$D$18,$BF13))>0,INDEX(Settings!$D$14:$D$18,$BF13),""))) -> 1000 | AH13: =IF($AM13=0,"",IF($AF13<>"Forex",1,IF(MID(UPPER(SUBSTITUTE(TRIM($E13),"/","")),4,3)=UPPER(TRIM(Settings!$C$7)),1,IF(LEFT(UPPER(SUBSTITUTE(TRIM($E13),"/","")),3)=UPPER(TRIM(Settings!$C$7)),IF(AND(ISNUMBER($K13),N($K13)<>0),1/$K13,""),"")))) -> 1 | AI13: =IF($AM13=0,"",IF(OR(NOT(ISNUMBER($H13)),NOT(ISNUMBER($K13)),NOT(ISNUMBER($G13)),$AG13="",$AH13=""),"",ROUND(($K13-$H13)*IF($F13="Short",-1,1)*$G13*$AG13*$AH13,6))) -> 300 | AJ13: =IF($AM13=0,"",IF(INDEX(Settings!$E$14:$E$18,$BF13)="% of notional",IF(OR($AG13="",NOT(ISNUMBER($H13)),NOT(ISNUMBER($G13))),"",ROUND(ABS($H13*$G13*$AG13*N($AH13))*IF($L13="Limit",N(INDEX(Settings!$G$14:$G$18,$BF13)),N(INDEX(Settings!$H$14:$H$18,$BF13)))+IF(ISNUMBER($K13),ABS($K13*$G13*$AG13*N($AH13))*IF($M13="Target",N(INDEX(Settings!$G$14:$G$18,$BF13)),N(INDEX(Settings!$H$14:$H$18,$BF13))),0),6)),IF(NOT(ISNUMBER($G13)),"",ROUND(ABS($G13)*2*IF(AND($BE13>0,ISNUMBER(INDEX(Instruments!$G$6:$G$205,MAX(1,$BE13)))),INDEX(Instruments!$G$6:$G$205,MAX(1,$BE13)),N(INDEX(Settings!$F$14:$F$18,$BF13))),6)))) -> 1 | AK13: =IF($AM13=0,"",IF(ISNUMBER($O13),$O13,$AI13)) -> 300 | AL13: =IF($AM13=0,"",IF(ISNUMBER($P13),$P13,N($AJ13))) -> 1 | AM13: =IF(AND($A13<>"",$E13<>"",OR(AND(ISNUMBER($G13),ISNUMBER($H13),ISNUMBER($K13)),ISNUMBER($O13))),1,0) -> 1 | AN13: =IF($A13="","",$A13-WEEKDAY($A13,3)) -> 46286 | AO13: =IF($A13="","",WEEKDAY($A13,2)) -> 4 | AP13: =IF(OR($AM13=0,$C13=""),"",IFERROR(N(INDEX(Accounts!$E$7:$E$16,MATCH($C13,Accounts!$B$7:$B$16,0))),0)+SUMIFS($Q$6:$Q13,$C$6:$C13,$C13)) -> 50660.5 | AQ13: =IF(OR($AM13=0,$C13=""),"",SUMIFS($Q$6:$Q$1005,$C$6:$C$1005,$C13,$A$6:$A$1005,$A13)) -> 397 | AR13: =IF(OR($AM13=0,$C13=""),"",IFERROR(N(INDEX(Accounts!$E$7:$E$16,MATCH($C13,Accounts!$B$7:$B$16,0))),0)+SUMIFS($Q$6:$Q$1005,$C$6:$C$1005,$C13,$A$6:$A$1005,"<="&$A13)) -> 50758.5 | AS13: =IF(OR($AM13=0,$Q13=""),0,IF(AND($A13>=Lists!$W$6,$A13<=Lists!$W$7,OR(Dashboard!$D$6="All accounts",$C13=Dashboard!$D$6),OR(Dashboard!$D$7="All markets",$AF13=Dashboard!$D$7)),1,0)) -> 1 | AT13: =IF($AS13=1,N(AT12)+$Q13,N(AT12)) -> 719.204 | AU13: =MAX(N(AU12),$AT13) -> 719.204 | AV13: =$AT13-$AU13 -> 0 | AW13: =IF($AS13=1,IF($S13="Win",N(AW12)+1,IF($S13="Loss",0,N(AW12))),N(AW12)) -> 1 | AX13: =IF($AS13=1,IF($S13="Loss",N(AX12)+1,IF($S13="Win",0,N(AX12))),N(AX12)) -> 0 | AY13: =IF($AS13=1,COUNTIF($AS$6:$AS13,1),"") -> 8 | AZ13: =MIN(7,N(Lists!$W$8)) -> 7 | BA13: =IF($AS13=1,IF(COUNTIFS($A$6:$A13,$A13,$AS$6:$AS13,1)=1,1,0),0) -> 1 | BB13: =IF($BA13=1,SUMIFS($Q$6:$Q$1005,$A$6:$A$1005,$A13,$AS$6:$AS$1005,1),"") -> 347.761 | BC13: =IF(ISNUMBER($R13),1,0) -> 1 | BD13: =IF(ISNUMBER($U13),$U13*$V13,"") -> 0 | BE13: =IF($AM13=0,"",IFERROR(MATCH($AF13&"|"&UPPER(TRIM($E13)),Lists!$A$6:$A$205,0),0)) -> 16 | BF13: =IF($AM13=0,"",IFERROR(MATCH($AF13,Settings!$B$14:$B$18,0),IFERROR(MATCH(Settings!$C$6,Settings!$B$14:$B$18,0),1))) -> 1 | BG13: =IF($AM13=0,"",IF(NOT(ISNUMBER($I13)),"No stop; ","")&IF(AND(ISNUMBER($H13),ISNUMBER($I13)),IF(OR(AND($F13<>"Short",$I13>=$H13),AND($F13="Short",$I13<=$H13)),"Stop on wrong side; ",""),"")&IF($F13="","No direction; ","")&IF(AND(ISNUMBER(Settings!$C$22),ISNUMBER($V13)),IF($V13>Settings!$C$22,"Risk over max $; ",""),"")&IF(AND(ISNUMBER(Settings!$C$23),ISNUMBER($V13),ISNUMBER($AP13),IFERROR(N(INDEX(Accounts!$E$7:$E$16,MATCH($C13,Accounts!$B$7:$B$16,0))),0)>0),IF($V13>Settings!$C$23*($AP13-N($Q13)),"Risk over max %; ",""),"")&IF(AND(ISNUMBER(Settings!$C$24),ISNUMBER($N13)),IF($N13>Settings!$C$24,"Leverage over max; ",""),"")&IF(AND(ISNUMBER(Settings!$C$27),ISNUMBER($T13)),IF($T13<Settings!$C$27,"R:R below min; ",""),"")&IF(ISNUMBER(Settings!$C$25),IF(COUNTIFS($A$6:$A13,$A13,$AM$6:$AM13,1)>Settings!$C$25,"Over max trades/day; ",""),"")&IF(ISNUMBER(Settings!$C$26),IF(SUMIFS($Q$5:$Q12,$A$5:$A12,$A13)<=-Settings!$C$26,"Traded after daily max loss; ",""),"")&IF(AND($AG13="",NOT(ISNUMBER($O13))),"Symbol not in Instruments; ","")&IF(AND($AH13="",NOT(ISNUMBER($O13))),"Forex cross: type Gross P&L; ","")) | BH13: =IF(ISNUMBER($Q13),1,0) -> 1 | BI13: =IF($Y13="",0,1) -> 1 | BJ13: =IF($AB13="",0,1) -> 0 | BK13: =IF(AND($BH13=1,$W13<>"OK"),1,0) -> 0 | BL13: =IF(N($AZ13)=0,0,IFERROR(INDEX($AT$6:$AT$1005,MATCH($AZ13,$AY$6:$AY$1005,0)),0)) -> 420.204 | BM13: =IF(ISNUMBER(SEARCH("daily max loss",$BG13)),1,0) -> 0
A14: 46289 | B14: 0.42013889 | C14: Prop Eval 50K | E14: MNQ | F14: Long | G14: 2 | H14: 29880 | I14: 29850 | J14: 29940 | K14: 29905 | L14: Market | M14: Manual | Q14: =IF($AM14=0,"",IF(ISNUMBER($AK14),$AK14-N($AL14),"")) -> 98 | R14: =IF(OR($Q14="",NOT(ISNUMBER($V14))),"",$AK14/$V14) -> 0.83333333 | S14: =IF($Q14="","",IF(AND(ISNUMBER($R14),ABS(N($R14))<N(Settings!$C$8)),"Scratch",IF($Q14>0,"Win",IF($Q14<0,"Loss","Scratch")))) -> Win | T14: =IF(OR($AM14=0,NOT(ISNUMBER($H14)),NOT(ISNUMBER($I14)),NOT(ISNUMBER($J14))),"",IF($H14=$I14,"",ROUND(ABS($J14-$H14)/ABS($H14-$I14),6))) -> 2 | U14: =IF(OR($S14<>"Win",NOT(ISNUMBER($T14)),NOT(ISNUMBER($R14))),"",MAX(0,$T14-$R14)) -> 1.1666667 | V14: =IF(OR($AM14=0,NOT(ISNUMBER($H14)),NOT(ISNUMBER($I14)),NOT(ISNUMBER($G14))),"",IF(OR($AG14="",$AH14=""),"",IF(ROUND(ABS($H14-$I14)*ABS($G14)*$AG14*$AH14,6)=0,"",ROUND(ABS($H14-$I14)*ABS($G14)*$AG14*$AH14,6)))) -> 120 | W14: =IF($AM14=0,"",IF($BG14="","OK",LEFT($BG14,LEN($BG14)-2))) -> OK | X14: NY Open | Y14: Trend Pullback | Z14: No | AA14: Anxious | AB14: Took profit too early | AC14: Second pullback, trend intact | AD14: Cut it at +25 points. Fear, not a reason. | AF14: =IF($AM14=0,"",IF($D14<>"",$D14,IF(IFERROR(INDEX(Accounts!$C$7:$C$16,MATCH($C14,Accounts!$B$7:$B$16,0))&"","")<>"",INDEX(Accounts!$C$7:$C$16,MATCH($C14,Accounts!$B$7:$B$16,0)),Settings!$C$6))) -> Futures | AG14: =IF($AM14=0,"",IF(AND($BE14>0,N(INDEX(Instruments!$D$6:$D$205,MAX(1,$BE14)))>0),INDEX(Instruments!$D$6:$D$205,MAX(1,$BE14)),IF(N(INDEX(Settings!$D$14:$D$18,$BF14))>0,INDEX(Settings!$D$14:$D$18,$BF14),""))) -> 2 | AH14: =IF($AM14=0,"",IF($AF14<>"Forex",1,IF(MID(UPPER(SUBSTITUTE(TRIM($E14),"/","")),4,3)=UPPER(TRIM(Settings!$C$7)),1,IF(LEFT(UPPER(SUBSTITUTE(TRIM($E14),"/","")),3)=UPPER(TRIM(Settings!$C$7)),IF(AND(ISNUMBER($K14),N($K14)<>0),1/$K14,""),"")))) -> 1 | AI14: =IF($AM14=0,"",IF(OR(NOT(ISNUMBER($H14)),NOT(ISNUMBER($K14)),NOT(ISNUMBER($G14)),$AG14="",$AH14=""),"",ROUND(($K14-$H14)*IF($F14="Short",-1,1)*$G14*$AG14*$AH14,6))) -> 100 | AJ14: =IF($AM14=0,"",IF(INDEX(Settings!$E$14:$E$18,$BF14)="% of notional",IF(OR($AG14="",NOT(ISNUMBER($H14)),NOT(ISNUMBER($G14))),"",ROUND(ABS($H14*$G14*$AG14*N($AH14))*IF($L14="Limit",N(INDEX(Settings!$G$14:$G$18,$BF14)),N(INDEX(Settings!$H$14:$H$18,$BF14)))+IF(ISNUMBER($K14),ABS($K14*$G14*$AG14*N($AH14))*IF($M14="Target",N(INDEX(Settings!$G$14:$G$18,$BF14)),N(INDEX(Settings!$H$14:$H$18,$BF14))),0),6)),IF(NOT(ISNUMBER($G14)),"",ROUND(ABS($G14)*2*IF(AND($BE14>0,ISNUMBER(INDEX(Instruments!$G$6:$G$205,MAX(1,$BE14)))),INDEX(Instruments!$G$6:$G$205,MAX(1,$BE14)),N(INDEX(Settings!$F$14:$F$18,$BF14))),6)))) -> 2 | AK14: =IF($AM14=0,"",IF(ISNUMBER($O14),$O14,$AI14)) -> 100 | AL14: =IF($AM14=0,"",IF(ISNUMBER($P14),$P14,N($AJ14))) -> 2 | AM14: =IF(AND($A14<>"",$E14<>"",OR(AND(ISNUMBER($G14),ISNUMBER($H14),ISNUMBER($K14)),ISNUMBER($O14))),1,0) -> 1 | AN14: =IF($A14="","",$A14-WEEKDAY($A14,3)) -> 46286 | AO14: =IF($A14="","",WEEKDAY($A14,2)) -> 4 | AP14: =IF(OR($AM14=0,$C14=""),"",IFERROR(N(INDEX(Accounts!$E$7:$E$16,MATCH($C14,Accounts!$B$7:$B$16,0))),0)+SUMIFS($Q$6:$Q14,$C$6:$C14,$C14)) -> 50758.5 | AQ14: =IF(OR($AM14=0,$C14=""),"",SUMIFS($Q$6:$Q$1005,$C$6:$C$1005,$C14,$A$6:$A$1005,$A14)) -> 397 | AR14: =IF(OR($AM14=0,$C14=""),"",IFERROR(N(INDEX(Accounts!$E$7:$E$16,MATCH($C14,Accounts!$B$7:$B$16,0))),0)+SUMIFS($Q$6:$Q$1005,$C$6:$C$1005,$C14,$A$6:$A$1005,"<="&$A14)) -> 50758.5 | AS14: =IF(OR($AM14=0,$Q14=""),0,IF(AND($A14>=Lists!$W$6,$A14<=Lists!$W$7,OR(Dashboard!$D$6="All accounts",$C14=Dashboard!$D$6),OR(Dashboard!$D$7="All markets",$AF14=Dashboard!$D$7)),1,0)) -> 1 | AT14: =IF($AS14=1,N(AT13)+$Q14,N(AT13)) -> 817.204 | AU14: =MAX(N(AU13),$AT14) -> 817.204 | AV14: =$AT14-$AU14 -> 0 | AW14: =IF($AS14=1,IF($S14="Win",N(AW13)+1,IF($S14="Loss",0,N(AW13))),N(AW13)) -> 2 | AX14: =IF($AS14=1,IF($S14="Loss",N(AX13)+1,IF($S14="Win",0,N(AX13))),N(AX13)) -> 0 | AY14: =IF($AS14=1,COUNTIF($AS$6:$AS14,1),"") -> 9 | AZ14: =MIN(8,N(Lists!$W$8)) -> 8 | BA14: =IF($AS14=1,IF(COUNTIFS($A$6:$A14,$A14,$AS$6:$AS14,1)=1,1,0),0) -> 0 | BB14: =IF($BA14=1,SUMIFS($Q$6:$Q$1005,$A$6:$A$1005,$A14,$AS$6:$AS$1005,1),"") | BC14: =IF(ISNUMBER($R14),1,0) -> 1 | BD14: =IF(ISNUMBER($U14),$U14*$V14,"") -> 140 | BE14: =IF($AM14=0,"",IFERROR(MATCH($AF14&"|"&UPPER(TRIM($E14)),Lists!$A$6:$A$205,0),0)) -> 3 | BF14: =IF($AM14=0,"",IFERROR(MATCH($AF14,Settings!$B$14:$B$18,0),IFERROR(MATCH(Settings!$C$6,Settings!$B$14:$B$18,0),1))) -> 1 | BG14: =IF($AM14=0,"",IF(NOT(ISNUMBER($I14)),"No stop; ","")&IF(AND(ISNUMBER($H14),ISNUMBER($I14)),IF(OR(AND($F14<>"Short",$I14>=$H14),AND($F14="Short",$I14<=$H14)),"Stop on wrong side; ",""),"")&IF($F14="","No direction; ","")&IF(AND(ISNUMBER(Settings!$C$22),ISNUMBER($V14)),IF($V14>Settings!$C$22,"Risk over max $; ",""),"")&IF(AND(ISNUMBER(Settings!$C$23),ISNUMBER($V14),ISNUMBER($AP14),IFERROR(N(INDEX(Accounts!$E$7:$E$16,MATCH($C14,Accounts!$B$7:$B$16,0))),0)>0),IF($V14>Settings!$C$23*($AP14-N($Q14)),"Risk over max %; ",""),"")&IF(AND(ISNUMBER(Settings!$C$24),ISNUMBER($N14)),IF($N14>Settings!$C$24,"Leverage over max; ",""),"")&IF(AND(ISNUMBER(Settings!$C$27),ISNUMBER($T14)),IF($T14<Settings!$C$27,"R:R below min; ",""),"")&IF(ISNUMBER(Settings!$C$25),IF(COUNTIFS($A$6:$A14,$A14,$AM$6:$AM14,1)>Settings!$C$25,"Over max trades/day; ",""),"")&IF(ISNUMBER(Settings!$C$26),IF(SUMIFS($Q$5:$Q13,$A$5:$A13,$A14)<=-Settings!$C$26,"Traded after daily max loss; ",""),"")&IF(AND($AG14="",NOT(ISNUMBER($O14))),"Symbol not in Instruments; ","")&IF(AND($AH14="",NOT(ISNUMBER($O14))),"Forex cross: type Gross P&L; ","")) | BH14: =IF(ISNUMBER($Q14),1,0) -> 1 | BI14: =IF($Y14="",0,1) -> 1 | BJ14: =IF($AB14="",0,1) -> 1 | BK14: =IF(AND($BH14=1,$W14<>"OK"),1,0) -> 0 | BL14: =IF(N($AZ14)=0,0,IFERROR(INDEX($AT$6:$AT$1005,MATCH($AZ14,$AY$6:$AY$1005,0)),0)) -> 719.204 | BM14: =IF(ISNUMBER(SEARCH("daily max loss",$BG14)),1,0) -> 0
A15: 46289 | B15: 0.60416667 | C15: Crypto Main | E15: ETHUSDT | F15: Short | G15: 1.5 | H15: 2340 | I15: 2370 | J15: 2280 | K15: 2370 | L15: Market | M15: Stop loss | N15: 25 | Q15: =IF($AM15=0,"",IF(ISNUMBER($AK15),$AK15-N($AL15),"")) -> -49.239 | R15: =IF(OR($Q15="",NOT(ISNUMBER($V15))),"",$AK15/$V15) -> -1 | S15: =IF($Q15="","",IF(AND(ISNUMBER($R15),ABS(N($R15))<N(Settings!$C$8)),"Scratch",IF($Q15>0,"Win",IF($Q15<0,"Loss","Scratch")))) -> Loss | T15: =IF(OR($AM15=0,NOT(ISNUMBER($H15)),NOT(ISNUMBER($I15)),NOT(ISNUMBER($J15))),"",IF($H15=$I15,"",ROUND(ABS($J15-$H15)/ABS($H15-$I15),6))) -> 2 | U15: =IF(OR($S15<>"Win",NOT(ISNUMBER($T15)),NOT(ISNUMBER($R15))),"",MAX(0,$T15-$R15)) | V15: =IF(OR($AM15=0,NOT(ISNUMBER($H15)),NOT(ISNUMBER($I15)),NOT(ISNUMBER($G15))),"",IF(OR($AG15="",$AH15=""),"",IF(ROUND(ABS($H15-$I15)*ABS($G15)*$AG15*$AH15,6)=0,"",ROUND(ABS($H15-$I15)*ABS($G15)*$AG15*$AH15,6)))) -> 45 | W15: =IF($AM15=0,"",IF($BG15="","OK",LEFT($BG15,LEN($BG15)-2))) -> Leverage over max | X15: US | Y15: Failed Breakout Reversal | Z15: No | AA15: FOMO | AB15: Late entry (chased) | AC15: Chased the dump | AD15: 25x and late. Two rule breaks. | AF15: =IF($AM15=0,"",IF($D15<>"",$D15,IF(IFERROR(INDEX(Accounts!$C$7:$C$16,MATCH($C15,Accounts!$B$7:$B$16,0))&"","")<>"",INDEX(Accounts!$C$7:$C$16,MATCH($C15,Accounts!$B$7:$B$16,0)),Settings!$C$6))) -> Crypto | AG15: =IF($AM15=0,"",IF(AND($BE15>0,N(INDEX(Instruments!$D$6:$D$205,MAX(1,$BE15)))>0),INDEX(Instruments!$D$6:$D$205,MAX(1,$BE15)),IF(N(INDEX(Settings!$D$14:$D$18,$BF15))>0,INDEX(Settings!$D$14:$D$18,$BF15),""))) -> 1 | AH15: =IF($AM15=0,"",IF($AF15<>"Forex",1,IF(MID(UPPER(SUBSTITUTE(TRIM($E15),"/","")),4,3)=UPPER(TRIM(Settings!$C$7)),1,IF(LEFT(UPPER(SUBSTITUTE(TRIM($E15),"/","")),3)=UPPER(TRIM(Settings!$C$7)),IF(AND(ISNUMBER($K15),N($K15)<>0),1/$K15,""),"")))) -> 1 | AI15: =IF($AM15=0,"",IF(OR(NOT(ISNUMBER($H15)),NOT(ISNUMBER($K15)),NOT(ISNUMBER($G15)),$AG15="",$AH15=""),"",ROUND(($K15-$H15)*IF($F15="Short",-1,1)*$G15*$AG15*$AH15,6))) -> -45 | AJ15: =IF($AM15=0,"",IF(INDEX(Settings!$E$14:$E$18,$BF15)="% of notional",IF(OR($AG15="",NOT(ISNUMBER($H15)),NOT(ISNUMBER($G15))),"",ROUND(ABS($H15*$G15*$AG15*N($AH15))*IF($L15="Limit",N(INDEX(Settings!$G$14:$G$18,$BF15)),N(INDEX(Settings!$H$14:$H$18,$BF15)))+IF(ISNUMBER($K15),ABS($K15*$G15*$AG15*N($AH15))*IF($M15="Target",N(INDEX(Settings!$G$14:$G$18,$BF15)),N(INDEX(Settings!$H$14:$H$18,$BF15))),0),6)),IF(NOT(ISNUMBER($G15)),"",ROUND(ABS($G15)*2*IF(AND($BE15>0,ISNUMBER(INDEX(Instruments!$G$6:$G$205,MAX(1,$BE15)))),INDEX(Instruments!$G$6:$G$205,MAX(1,$BE15)),N(INDEX(Settings!$F$14:$F$18,$BF15))),6)))) -> 4.239 | AK15: =IF($AM15=0,"",IF(ISNUMBER($O15),$O15,$AI15)) -> -45 | AL15: =IF($AM15=0,"",IF(ISNUMBER($P15),$P15,N($AJ15))) -> 4.239 | AM15: =IF(AND($A15<>"",$E15<>"",OR(AND(ISNUMBER($G15),ISNUMBER($H15),ISNUMBER($K15)),ISNUMBER($O15))),1,0) -> 1 | AN15: =IF($A15="","",$A15-WEEKDAY($A15,3)) -> 46286 | AO15: =IF($A15="","",WEEKDAY($A15,2)) -> 4 | AP15: =IF(OR($AM15=0,$C15=""),"",IFERROR(N(INDEX(Accounts!$E$7:$E$16,MATCH($C15,Accounts!$B$7:$B$16,0))),0)+SUMIFS($Q$6:$Q15,$C$6:$C15,$C15)) -> 5009.465 | AQ15: =IF(OR($AM15=0,$C15=""),"",SUMIFS($Q$6:$Q$1005,$C$6:$C$1005,$C15,$A$6:$A$1005,$A15)) -> -49.239 | AR15: =IF(OR($AM15=0,$C15=""),"",IFERROR(N(INDEX(Accounts!$E$7:$E$16,MATCH($C15,Accounts!$B$7:$B$16,0))),0)+SUMIFS($Q$6:$Q$1005,$C$6:$C$1005,$C15,$A$6:$A$1005,"<="&$A15)) -> 5009.465 | AS15: =IF(OR($AM15=0,$Q15=""),0,IF(AND($A15>=Lists!$W$6,$A15<=Lists!$W$7,OR(Dashboard!$D$6="All accounts",$C15=Dashboard!$D$6),OR(Dashboard!$D$7="All markets",$AF15=Dashboard!$D$7)),1,0)) -> 1 | AT15: =IF($AS15=1,N(AT14)+$Q15,N(AT14)) -> 767.965 | AU15: =MAX(N(AU14),$AT15) -> 817.204 | AV15: =$AT15-$AU15 -> -49.239 | AW15: =IF($AS15=1,IF($S15="Win",N(AW14)+1,IF($S15="Loss",0,N(AW14))),N(AW14)) -> 0 | AX15: =IF($AS15=1,IF($S15="Loss",N(AX14)+1,IF($S15="Win",0,N(AX14))),N(AX14)) -> 1 | AY15: =IF($AS15=1,COUNTIF($AS$6:$AS15,1),"") -> 10 | AZ15: =MIN(9,N(Lists!$W$8)) -> 9 | BA15: =IF($AS15=1,IF(COUNTIFS($A$6:$A15,$A15,$AS$6:$AS15,1)=1,1,0),0) -> 0 | BB15: =IF($BA15=1,SUMIFS($Q$6:$Q$1005,$A$6:$A$1005,$A15,$AS$6:$AS$1005,1),"") | BC15: =IF(ISNUMBER($R15),1,0) -> 1 | BD15: =IF(ISNUMBER($U15),$U15*$V15,"") | BE15: =IF($AM15=0,"",IFERROR(MATCH($AF15&"|"&UPPER(TRIM($E15)),Lists!$A$6:$A$205,0),0)) -> 47 | BF15: =IF($AM15=0,"",IFERROR(MATCH($AF15,Settings!$B$14:$B$18,0),IFERROR(MATCH(Settings!$C$6,Settings!$B$14:$B$18,0),1))) -> 5 | BG15: =IF($AM15=0,"",IF(NOT(ISNUMBER($I15)),"No stop; ","")&IF(AND(ISNUMBER($H15),ISNUMBER($I15)),IF(OR(AND($F15<>"Short",$I15>=$H15),AND($F15="Short",$I15<=$H15)),"Stop on wrong side; ",""),"")&IF($F15="","No direction; ","")&IF(AND(ISNUMBER(Settings!$C$22),ISNUMBER($V15)),IF($V15>Settings!$C$22,"Risk over max $; ",""),"")&IF(AND(ISNUMBER(Settings!$C$23),ISNUMBER($V15),ISNUMBER($AP15),IFERROR(N(INDEX(Accounts!$E$7:$E$16,MATCH($C15,Accounts!$B$7:$B$16,0))),0)>0),IF($V15>Settings!$C$23*($AP15-N($Q15)),"Risk over max %; ",""),"")&IF(AND(ISNUMBER(Settings!$C$24),ISNUMBER($N15)),IF($N15>Settings!$C$24,"Leverage over max; ",""),"")&IF(AND(ISNUMBER(Settings!$C$27),ISNUMBER($T15)),IF($T15<Settings!$C$27,"R:R below min; ",""),"")&IF(ISNUMBER(Settings!$C$25),IF(COUNTIFS($A$6:$A15,$A15,$AM$6:$AM15,1)>Settings!$C$25,"Over max trades/day; ",""),"")&IF(ISNUMBER(Settings!$C$26),IF(SUMIFS($Q$5:$Q14,$A$5:$A14,$A15)<=-Settings!$C$26,"Traded after daily max loss; ",""),"")&IF(AND($AG15="",NOT(ISNUMBER($O15))),"Symbol not in Instruments; ","")&IF(AND($AH15="",NOT(ISNUMBER($O15))),"Forex cross: type Gross P&L; ","")) -> Leverage over max; | BH15: =IF(ISNUMBER($Q15),1,0) -> 1 | BI15: =IF($Y15="",0,1) -> 1 | BJ15: =IF($AB15="",0,1) -> 1 | BK15: =IF(AND($BH15=1,$W15<>"OK"),1,0) -> 1 | BL15: =IF(N($AZ15)=0,0,IFERROR(INDEX($AT$6:$AT$1005,MATCH($AZ15,$AY$6:$AY$1005,0)),0)) -> 817.204 | BM15: =IF(ISNUMBER(SEARCH("daily max loss",$BG15)),1,0) -> 0
A16: 46290 | B16: 0.40277778 | C16: Prop Eval 50K | E16: MGC | F16: Short | G16: 2 | H16: 4071 | I16: 4077 | J16: 4059 | K16: 4077 | L16: Limit | M16: Stop loss | Q16: =IF($AM16=0,"",IF(ISNUMBER($AK16),$AK16-N($AL16),"")) -> -122 | R16: =IF(OR($Q16="",NOT(ISNUMBER($V16))),"",$AK16/$V16) -> -1 | S16: =IF($Q16="","",IF(AND(ISNUMBER($R16),ABS(N($R16))<N(Settings!$C$8)),"Scratch",IF($Q16>0,"Win",IF($Q16<0,"Loss","Scratch")))) -> Loss | T16: =IF(OR($AM16=0,NOT(ISNUMBER($H16)),NOT(ISNUMBER($I16)),NOT(ISNUMBER($J16))),"",IF($H16=$I16,"",ROUND(ABS($J16-$H16)/ABS($H16-$I16),6))) -> 2 | U16: =IF(OR($S16<>"Win",NOT(ISNUMBER($T16)),NOT(ISNUMBER($R16))),"",MAX(0,$T16-$R16)) | V16: =IF(OR($AM16=0,NOT(ISNUMBER($H16)),NOT(ISNUMBER($I16)),NOT(ISNUMBER($G16))),"",IF(OR($AG16="",$AH16=""),"",IF(ROUND(ABS($H16-$I16)*ABS($G16)*$AG16*$AH16,6)=0,"",ROUND(ABS($H16-$I16)*ABS($G16)*$AG16*$AH16,6)))) -> 120 | W16: =IF($AM16=0,"",IF($BG16="","OK",LEFT($BG16,LEN($BG16)-2))) -> OK | X16: NY Open | Y16: Failed Breakout Reversal | Z16: Yes | AA16: Calm | AC16: Failed push above 4,070 | AD16: Valid setup that didn't work. That's fine. | AF16: =IF($AM16=0,"",IF($D16<>"",$D16,IF(IFERROR(INDEX(Accounts!$C$7:$C$16,MATCH($C16,Accounts!$B$7:$B$16,0))&"","")<>"",INDEX(Accounts!$C$7:$C$16,MATCH($C16,Accounts!$B$7:$B$16,0)),Settings!$C$6))) -> Futures | AG16: =IF($AM16=0,"",IF(AND($BE16>0,N(INDEX(Instruments!$D$6:$D$205,MAX(1,$BE16)))>0),INDEX(Instruments!$D$6:$D$205,MAX(1,$BE16)),IF(N(INDEX(Settings!$D$14:$D$18,$BF16))>0,INDEX(Settings!$D$14:$D$18,$BF16),""))) -> 10 | AH16: =IF($AM16=0,"",IF($AF16<>"Forex",1,IF(MID(UPPER(SUBSTITUTE(TRIM($E16),"/","")),4,3)=UPPER(TRIM(Settings!$C$7)),1,IF(LEFT(UPPER(SUBSTITUTE(TRIM($E16),"/","")),3)=UPPER(TRIM(Settings!$C$7)),IF(AND(ISNUMBER($K16),N($K16)<>0),1/$K16,""),"")))) -> 1 | AI16: =IF($AM16=0,"",IF(OR(NOT(ISNUMBER($H16)),NOT(ISNUMBER($K16)),NOT(ISNUMBER($G16)),$AG16="",$AH16=""),"",ROUND(($K16-$H16)*IF($F16="Short",-1,1)*$G16*$AG16*$AH16,6))) -> -120 | AJ16: =IF($AM16=0,"",IF(INDEX(Settings!$E$14:$E$18,$BF16)="% of notional",IF(OR($AG16="",NOT(ISNUMBER($H16)),NOT(ISNUMBER($G16))),"",ROUND(ABS($H16*$G16*$AG16*N($AH16))*IF($L16="Limit",N(INDEX(Settings!$G$14:$G$18,$BF16)),N(INDEX(Settings!$H$14:$H$18,$BF16)))+IF(ISNUMBER($K16),ABS($K16*$G16*$AG16*N($AH16))*IF($M16="Target",N(INDEX(Settings!$G$14:$G$18,$BF16)),N(INDEX(Settings!$H$14:$H$18,$BF16))),0),6)),IF(NOT(ISNUMBER($G16)),"",ROUND(ABS($G16)*2*IF(AND($BE16>0,ISNUMBER(INDEX(Instruments!$G$6:$G$205,MAX(1,$BE16)))),INDEX(Instruments!$G$6:$G$205,MAX(1,$BE16)),N(INDEX(Settings!$F$14:$F$18,$BF16))),6)))) -> 2 | AK16: =IF($AM16=0,"",IF(ISNUMBER($O16),$O16,$AI16)) -> -120 | AL16: =IF($AM16=0,"",IF(ISNUMBER($P16),$P16,N($AJ16))) -> 2 | AM16: =IF(AND($A16<>"",$E16<>"",OR(AND(ISNUMBER($G16),ISNUMBER($H16),ISNUMBER($K16)),ISNUMBER($O16))),1,0) -> 1 | AN16: =IF($A16="","",$A16-WEEKDAY($A16,3)) -> 46286 | AO16: =IF($A16="","",WEEKDAY($A16,2)) -> 5 | AP16: =IF(OR($AM16=0,$C16=""),"",IFERROR(N(INDEX(Accounts!$E$7:$E$16,MATCH($C16,Accounts!$B$7:$B$16,0))),0)+SUMIFS($Q$6:$Q16,$C$6:$C16,$C16)) -> 50636.5 | AQ16: =IF(OR($AM16=0,$C16=""),"",SUMIFS($Q$6:$Q$1005,$C$6:$C$1005,$C16,$A$6:$A$1005,$A16)) -> -395.5 | AR16: =IF(OR($AM16=0,$C16=""),"",IFERROR(N(INDEX(Accounts!$E$7:$E$16,MATCH($C16,Accounts!$B$7:$B$16,0))),0)+SUMIFS($Q$6:$Q$1005,$C$6:$C$1005,$C16,$A$6:$A$1005,"<="&$A16)) -> 50363 | AS16: =IF(OR($AM16=0,$Q16=""),0,IF(AND($A16>=Lists!$W$6,$A16<=Lists!$W$7,OR(Dashboard!$D$6="All accounts",$C16=Dashboard!$D$6),OR(Dashboard!$D$7="All markets",$AF16=Dashboard!$D$7)),1,0)) -> 1 | AT16: =IF($AS16=1,N(AT15)+$Q16,N(AT15)) -> 645.965 | AU16: =MAX(N(AU15),$AT16) -> 817.204 | AV16: =$AT16-$AU16 -> -171.239 | AW16: =IF($AS16=1,IF($S16="Win",N(AW15)+1,IF($S16="Loss",0,N(AW15))),N(AW15)) -> 0 | AX16: =IF($AS16=1,IF($S16="Loss",N(AX15)+1,IF($S16="Win",0,N(AX15))),N(AX15)) -> 2 | AY16: =IF($AS16=1,COUNTIF($AS$6:$AS16,1),"") -> 11 | AZ16: =MIN(10,N(Lists!$W$8)) -> 10 | BA16: =IF($AS16=1,IF(COUNTIFS($A$6:$A16,$A16,$AS$6:$AS16,1)=1,1,0),0) -> 1 | BB16: =IF($BA16=1,SUMIFS($Q$6:$Q$1005,$A$6:$A$1005,$A16,$AS$6:$AS$1005,1),"") -> -395.5 | BC16: =IF(ISNUMBER($R16),1,0) -> 1 | BD16: =IF(ISNUMBER($U16),$U16*$V16,"") | BE16: =IF($AM16=0,"",IFERROR(MATCH($AF16&"|"&UPPER(TRIM($E16)),Lists!$A$6:$A$205,0),0)) -> 14 | BF16: =IF($AM16=0,"",IFERROR(MATCH($AF16,Settings!$B$14:$B$18,0),IFERROR(MATCH(Settings!$C$6,Settings!$B$14:$B$18,0),1))) -> 1 | BG16: =IF($AM16=0,"",IF(NOT(ISNUMBER($I16)),"No stop; ","")&IF(AND(ISNUMBER($H16),ISNUMBER($I16)),IF(OR(AND($F16<>"Short",$I16>=$H16),AND($F16="Short",$I16<=$H16)),"Stop on wrong side; ",""),"")&IF($F16="","No direction; ","")&IF(AND(ISNUMBER(Settings!$C$22),ISNUMBER($V16)),IF($V16>Settings!$C$22,"Risk over max $; ",""),"")&IF(AND(ISNUMBER(Settings!$C$23),ISNUMBER($V16),ISNUMBER($AP16),IFERROR(N(INDEX(Accounts!$E$7:$E$16,MATCH($C16,Accounts!$B$7:$B$16,0))),0)>0),IF($V16>Settings!$C$23*($AP16-N($Q16)),"Risk over max %; ",""),"")&IF(AND(ISNUMBER(Settings!$C$24),ISNUMBER($N16)),IF($N16>Settings!$C$24,"Leverage over max; ",""),"")&IF(AND(ISNUMBER(Settings!$C$27),ISNUMBER($T16)),IF($T16<Settings!$C$27,"R:R below min; ",""),"")&IF(ISNUMBER(Settings!$C$25),IF(COUNTIFS($A$6:$A16,$A16,$AM$6:$AM16,1)>Settings!$C$25,"Over max trades/day; ",""),"")&IF(ISNUMBER(Settings!$C$26),IF(SUMIFS($Q$5:$Q15,$A$5:$A15,$A16)<=-Settings!$C$26,"Traded after daily max loss; ",""),"")&IF(AND($AG16="",NOT(ISNUMBER($O16))),"Symbol not in Instruments; ","")&IF(AND($AH16="",NOT(ISNUMBER($O16))),"Forex cross: type Gross P&L; ","")) | BH16: =IF(ISNUMBER($Q16),1,0) -> 1 | BI16: =IF($Y16="",0,1) -> 1 | BJ16: =IF($AB16="",0,1) -> 0 | BK16: =IF(AND($BH16=1,$W16<>"OK"),1,0) -> 0 | BL16: =IF(N($AZ16)=0,0,IFERROR(INDEX($AT$6:$AT$1005,MATCH($AZ16,$AY$6:$AY$1005,0)),0)) -> 767.965 | BM16: =IF(ISNUMBER(SEARCH("daily max loss",$BG16)),1,0) -> 0
A17: 46290 | B17: 0.43194444 | C17: Prop Eval 50K | E17: MGC | F17: Short | G17: 2 | H17: 4074 | I17: 4080 | J17: 4062 | K17: 4083 | L17: Market | M17: Stop loss | Q17: =IF($AM17=0,"",IF(ISNUMBER($AK17),$AK17-N($AL17),"")) -> -182 | R17: =IF(OR($Q17="",NOT(ISNUMBER($V17))),"",$AK17/$V17) -> -1.5 | S17: =IF($Q17="","",IF(AND(ISNUMBER($R17),ABS(N($R17))<N(Settings!$C$8)),"Scratch",IF($Q17>0,"Win",IF($Q17<0,"Loss","Scratch")))) -> Loss | T17: =IF(OR($AM17=0,NOT(ISNUMBER($H17)),NOT(ISNUMBER($I17)),NOT(ISNUMBER($J17))),"",IF($H17=$I17,"",ROUND(ABS($J17-$H17)/ABS($H17-$I17),6))) -> 2 | U17: =IF(OR($S17<>"Win",NOT(ISNUMBER($T17)),NOT(ISNUMBER($R17))),"",MAX(0,$T17-$R17)) | V17: =IF(OR($AM17=0,NOT(ISNUMBER($H17)),NOT(ISNUMBER($I17)),NOT(ISNUMBER($G17))),"",IF(OR($AG17="",$AH17=""),"",IF(ROUND(ABS($H17-$I17)*ABS($G17)*$AG17*$AH17,6)=0,"",ROUND(ABS($H17-$I17)*ABS($G17)*$AG17*$AH17,6)))) -> 120 | W17: =IF($AM17=0,"",IF($BG17="","OK",LEFT($BG17,LEN($BG17)-2))) -> OK | X17: NY Open | Y17: Failed Breakout Reversal | Z17: No | AA17: Revenge | AB17: Moved stop | AC17: Wanted the last loss back | AD17: Re-entered right away and moved my stop. -1.5R. | AF17: =IF($AM17=0,"",IF($D17<>"",$D17,IF(IFERROR(INDEX(Accounts!$C$7:$C$16,MATCH($C17,Accounts!$B$7:$B$16,0))&"","")<>"",INDEX(Accounts!$C$7:$C$16,MATCH($C17,Accounts!$B$7:$B$16,0)),Settings!$C$6))) -> Futures | AG17: =IF($AM17=0,"",IF(AND($BE17>0,N(INDEX(Instruments!$D$6:$D$205,MAX(1,$BE17)))>0),INDEX(Instruments!$D$6:$D$205,MAX(1,$BE17)),IF(N(INDEX(Settings!$D$14:$D$18,$BF17))>0,INDEX(Settings!$D$14:$D$18,$BF17),""))) -> 10 | AH17: =IF($AM17=0,"",IF($AF17<>"Forex",1,IF(MID(UPPER(SUBSTITUTE(TRIM($E17),"/","")),4,3)=UPPER(TRIM(Settings!$C$7)),1,IF(LEFT(UPPER(SUBSTITUTE(TRIM($E17),"/","")),3)=UPPER(TRIM(Settings!$C$7)),IF(AND(ISNUMBER($K17),N($K17)<>0),1/$K17,""),"")))) -> 1 | AI17: =IF($AM17=0,"",IF(OR(NOT(ISNUMBER($H17)),NOT(ISNUMBER($K17)),NOT(ISNUMBER($G17)),$AG17="",$AH17=""),"",ROUND(($K17-$H17)*IF($F17="Short",-1,1)*$G17*$AG17*$AH17,6))) -> -180 | AJ17: =IF($AM17=0,"",IF(INDEX(Settings!$E$14:$E$18,$BF17)="% of notional",IF(OR($AG17="",NOT(ISNUMBER($H17)),NOT(ISNUMBER($G17))),"",ROUND(ABS($H17*$G17*$AG17*N($AH17))*IF($L17="Limit",N(INDEX(Settings!$G$14:$G$18,$BF17)),N(INDEX(Settings!$H$14:$H$18,$BF17)))+IF(ISNUMBER($K17),ABS($K17*$G17*$AG17*N($AH17))*IF($M17="Target",N(INDEX(Settings!$G$14:$G$18,$BF17)),N(INDEX(Settings!$H$14:$H$18,$BF17))),0),6)),IF(NOT(ISNUMBER($G17)),"",ROUND(ABS($G17)*2*IF(AND($BE17>0,ISNUMBER(INDEX(Instruments!$G$6:$G$205,MAX(1,$BE17)))),INDEX(Instruments!$G$6:$G$205,MAX(1,$BE17)),N(INDEX(Settings!$F$14:$F$18,$BF17))),6)))) -> 2 | AK17: =IF($AM17=0,"",IF(ISNUMBER($O17),$O17,$AI17)) -> -180 | AL17: =IF($AM17=0,"",IF(ISNUMBER($P17),$P17,N($AJ17))) -> 2 | AM17: =IF(AND($A17<>"",$E17<>"",OR(AND(ISNUMBER($G17),ISNUMBER($H17),ISNUMBER($K17)),ISNUMBER($O17))),1,0) -> 1 | AN17: =IF($A17="","",$A17-WEEKDAY($A17,3)) -> 46286 | AO17: =IF($A17="","",WEEKDAY($A17,2)) -> 5 | AP17: =IF(OR($AM17=0,$C17=""),"",IFERROR(N(INDEX(Accounts!$E$7:$E$16,MATCH($C17,Accounts!$B$7:$B$16,0))),0)+SUMIFS($Q$6:$Q17,$C$6:$C17,$C17)) -> 50454.5 | AQ17: =IF(OR($AM17=0,$C17=""),"",SUMIFS($Q$6:$Q$1005,$C$6:$C$1005,$C17,$A$6:$A$1005,$A17)) -> -395.5 | AR17: =IF(OR($AM17=0,$C17=""),"",IFERROR(N(INDEX(Accounts!$E$7:$E$16,MATCH($C17,Accounts!$B$7:$B$16,0))),0)+SUMIFS($Q$6:$Q$1005,$C$6:$C$1005,$C17,$A$6:$A$1005,"<="&$A17)) -> 50363 | AS17: =IF(OR($AM17=0,$Q17=""),0,IF(AND($A17>=Lists!$W$6,$A17<=Lists!$W$7,OR(Dashboard!$D$6="All accounts",$C17=Dashboard!$D$6),OR(Dashboard!$D$7="All markets",$AF17=Dashboard!$D$7)),1,0)) -> 1 | AT17: =IF($AS17=1,N(AT16)+$Q17,N(AT16)) -> 463.965 | AU17: =MAX(N(AU16),$AT17) -> 817.204 | AV17: =$AT17-$AU17 -> -353.239 | AW17: =IF($AS17=1,IF($S17="Win",N(AW16)+1,IF($S17="Loss",0,N(AW16))),N(AW16)) -> 0 | AX17: =IF($AS17=1,IF($S17="Loss",N(AX16)+1,IF($S17="Win",0,N(AX16))),N(AX16)) -> 3 | AY17: =IF($AS17=1,COUNTIF($AS$6:$AS17,1),"") -> 12 | AZ17: =MIN(11,N(Lists!$W$8)) -> 11 | BA17: =IF($AS17=1,IF(COUNTIFS($A$6:$A17,$A17,$AS$6:$AS17,1)=1,1,0),0) -> 0 | BB17: =IF($BA17=1,SUMIFS($Q$6:$Q$1005,$A$6:$A$1005,$A17,$AS$6:$AS$1005,1),"") | BC17: =IF(ISNUMBER($R17),1,0) -> 1 | BD17: =IF(ISNUMBER($U17),$U17*$V17,"") | BE17: =IF($AM17=0,"",IFERROR(MATCH($AF17&"|"&UPPER(TRIM($E17)),Lists!$A$6:$A$205,0),0)) -> 14 | BF17: =IF($AM17=0,"",IFERROR(MATCH($AF17,Settings!$B$14:$B$18,0),IFERROR(MATCH(Settings!$C$6,Settings!$B$14:$B$18,0),1))) -> 1 | BG17: =IF($AM17=0,"",IF(NOT(ISNUMBER($I17)),"No stop; ","")&IF(AND(ISNUMBER($H17),ISNUMBER($I17)),IF(OR(AND($F17<>"Short",$I17>=$H17),AND($F17="Short",$I17<=$H17)),"Stop on wrong side; ",""),"")&IF($F17="","No direction; ","")&IF(AND(ISNUMBER(Settings!$C$22),ISNUMBER($V17)),IF($V17>Settings!$C$22,"Risk over max $; ",""),"")&IF(AND(ISNUMBER(Settings!$C$23),ISNUMBER($V17),ISNUMBER($AP17),IFERROR(N(INDEX(Accounts!$E$7:$E$16,MATCH($C17,Accounts!$B$7:$B$16,0))),0)>0),IF($V17>Settings!$C$23*($AP17-N($Q17)),"Risk over max %; ",""),"")&IF(AND(ISNUMBER(Settings!$C$24),ISNUMBER($N17)),IF($N17>Settings!$C$24,"Leverage over max; ",""),"")&IF(AND(ISNUMBER(Settings!$C$27),ISNUMBER($T17)),IF($T17<Settings!$C$27,"R:R below min; ",""),"")&IF(ISNUMBER(Settings!$C$25),IF(COUNTIFS($A$6:$A17,$A17,$AM$6:$AM17,1)>Settings!$C$25,"Over max trades/day; ",""),"")&IF(ISNUMBER(Settings!$C$26),IF(SUMIFS($Q$5:$Q16,$A$5:$A16,$A17)<=-Settings!$C$26,"Traded after daily max loss; ",""),"")&IF(AND($AG17="",NOT(ISNUMBER($O17))),"Symbol not in Instruments; ","")&IF(AND($AH17="",NOT(ISNUMBER($O17))),"Forex cross: type Gross P&L; ","")) | BH17: =IF(ISNUMBER($Q17),1,0) -> 1 | BI17: =IF($Y17="",0,1) -> 1 | BJ17: =IF($AB17="",0,1) -> 1 | BK17: =IF(AND($BH17=1,$W17<>"OK"),1,0) -> 0 | BL17: =IF(N($AZ17)=0,0,IFERROR(INDEX($AT$6:$AT$1005,MATCH($AZ17,$AY$6:$AY$1005,0)),0)) -> 645.965 | BM17: =IF(ISNUMBER(SEARCH("daily max loss",$BG17)),1,0) -> 0
A18: 46290 | B18: 0.44444444 | C18: Prop Eval 50K | E18: MES | F18: Short | G18: 3 | H18: 7701.25 | I18: 7708.75 | J18: 7686.25 | K18: 7708.75 | L18: Market | M18: Stop loss | Q18: =IF($AM18=0,"",IF(ISNUMBER($AK18),$AK18-N($AL18),"")) -> -115.5 | R18: =IF(OR($Q18="",NOT(ISNUMBER($V18))),"",$AK18/$V18) -> -1 | S18: =IF($Q18="","",IF(AND(ISNUMBER($R18),ABS(N($R18))<N(Settings!$C$8)),"Scratch",IF($Q18>0,"Win",IF($Q18<0,"Loss","Scratch")))) -> Loss | T18: =IF(OR($AM18=0,NOT(ISNUMBER($H18)),NOT(ISNUMBER($I18)),NOT(ISNUMBER($J18))),"",IF($H18=$I18,"",ROUND(ABS($J18-$H18)/ABS($H18-$I18),6))) -> 2 | U18: =IF(OR($S18<>"Win",NOT(ISNUMBER($T18)),NOT(ISNUMBER($R18))),"",MAX(0,$T18-$R18)) | V18: =IF(OR($AM18=0,NOT(ISNUMBER($H18)),NOT(ISNUMBER($I18)),NOT(ISNUMBER($G18))),"",IF(OR($AG18="",$AH18=""),"",IF(ROUND(ABS($H18-$I18)*ABS($G18)*$AG18*$AH18,6)=0,"",ROUND(ABS($H18-$I18)*ABS($G18)*$AG18*$AH18,6)))) -> 112.5 | W18: =IF($AM18=0,"",IF($BG18="","OK",LEFT($BG18,LEN($BG18)-2))) -> OK | X18: NY Open | Z18: No | AA18: Tilted | AB18: No setup (impulse) | AC18: Just clicked | AD18: Tilted. Should have stopped after the second loss. | AF18: =IF($AM18=0,"",IF($D18<>"",$D18,IF(IFERROR(INDEX(Accounts!$C$7:$C$16,MATCH($C18,Accounts!$B$7:$B$16,0))&"","")<>"",INDEX(Accounts!$C$7:$C$16,MATCH($C18,Accounts!$B$7:$B$16,0)),Settings!$C$6))) -> Futures | AG18: =IF($AM18=0,"",IF(AND($BE18>0,N(INDEX(Instruments!$D$6:$D$205,MAX(1,$BE18)))>0),INDEX(Instruments!$D$6:$D$205,MAX(1,$BE18)),IF(N(INDEX(Settings!$D$14:$D$18,$BF18))>0,INDEX(Settings!$D$14:$D$18,$BF18),""))) -> 5 | AH18: =IF($AM18=0,"",IF($AF18<>"Forex",1,IF(MID(UPPER(SUBSTITUTE(TRIM($E18),"/","")),4,3)=UPPER(TRIM(Settings!$C$7)),1,IF(LEFT(UPPER(SUBSTITUTE(TRIM($E18),"/","")),3)=UPPER(TRIM(Settings!$C$7)),IF(AND(ISNUMBER($K18),N($K18)<>0),1/$K18,""),"")))) -> 1 | AI18: =IF($AM18=0,"",IF(OR(NOT(ISNUMBER($H18)),NOT(ISNUMBER($K18)),NOT(ISNUMBER($G18)),$AG18="",$AH18=""),"",ROUND(($K18-$H18)*IF($F18="Short",-1,1)*$G18*$AG18*$AH18,6))) -> -112.5 | AJ18: =IF($AM18=0,"",IF(INDEX(Settings!$E$14:$E$18,$BF18)="% of notional",IF(OR($AG18="",NOT(ISNUMBER($H18)),NOT(ISNUMBER($G18))),"",ROUND(ABS($H18*$G18*$AG18*N($AH18))*IF($L18="Limit",N(INDEX(Settings!$G$14:$G$18,$BF18)),N(INDEX(Settings!$H$14:$H$18,$BF18)))+IF(ISNUMBER($K18),ABS($K18*$G18*$AG18*N($AH18))*IF($M18="Target",N(INDEX(Settings!$G$14:$G$18,$BF18)),N(INDEX(Settings!$H$14:$H$18,$BF18))),0),6)),IF(NOT(ISNUMBER($G18)),"",ROUND(ABS($G18)*2*IF(AND($BE18>0,ISNUMBER(INDEX(Instruments!$G$6:$G$205,MAX(1,$BE18)))),INDEX(Instruments!$G$6:$G$205,MAX(1,$BE18)),N(INDEX(Settings!$F$14:$F$18,$BF18))),6)))) -> 3 | AK18: =IF($AM18=0,"",IF(ISNUMBER($O18),$O18,$AI18)) -> -112.5 | AL18: =IF($AM18=0,"",IF(ISNUMBER($P18),$P18,N($AJ18))) -> 3 | AM18: =IF(AND($A18<>"",$E18<>"",OR(AND(ISNUMBER($G18),ISNUMBER($H18),ISNUMBER($K18)),ISNUMBER($O18))),1,0) -> 1 | AN18: =IF($A18="","",$A18-WEEKDAY($A18,3)) -> 46286 | AO18: =IF($A18="","",WEEKDAY($A18,2)) -> 5 | AP18: =IF(OR($AM18=0,$C18=""),"",IFERROR(N(INDEX(Accounts!$E$7:$E$16,MATCH($C18,Accounts!$B$7:$B$16,0))),0)+SUMIFS($Q$6:$Q18,$C$6:$C18,$C18)) -> 50339 | AQ18: =IF(OR($AM18=0,$C18=""),"",SUMIFS($Q$6:$Q$1005,$C$6:$C$1005,$C18,$A$6:$A$1005,$A18)) -> -395.5 | AR18: =IF(OR($AM18=0,$C18=""),"",IFERROR(N(INDEX(Accounts!$E$7:$E$16,MATCH($C18,Accounts!$B$7:$B$16,0))),0)+SUMIFS($Q$6:$Q$1005,$C$6:$C$1005,$C18,$A$6:$A$1005,"<="&$A18)) -> 50363 | AS18: =IF(OR($AM18=0,$Q18=""),0,IF(AND($A18>=Lists!$W$6,$A18<=Lists!$W$7,OR(Dashboard!$D$6="All accounts",$C18=Dashboard!$D$6),OR(Dashboard!$D$7="All markets",$AF18=Dashboard!$D$7)),1,0)) -> 1 | AT18: =IF($AS18=1,N(AT17)+$Q18,N(AT17)) -> 348.465 | AU18: =MAX(N(AU17),$AT18) -> 817.204 | AV18: =$AT18-$AU18 -> -468.739 | AW18: =IF($AS18=1,IF($S18="Win",N(AW17)+1,IF($S18="Loss",0,N(AW17))),N(AW17)) -> 0 | AX18: =IF($AS18=1,IF($S18="Loss",N(AX17)+1,IF($S18="Win",0,N(AX17))),N(AX17)) -> 4 | AY18: =IF($AS18=1,COUNTIF($AS$6:$AS18,1),"") -> 13 | AZ18: =MIN(12,N(Lists!$W$8)) -> 12 | BA18: =IF($AS18=1,IF(COUNTIFS($A$6:$A18,$A18,$AS$6:$AS18,1)=1,1,0),0) -> 0 | BB18: =IF($BA18=1,SUMIFS($Q$6:$Q$1005,$A$6:$A$1005,$A18,$AS$6:$AS$1005,1),"") | BC18: =IF(ISNUMBER($R18),1,0) -> 1 | BD18: =IF(ISNUMBER($U18),$U18*$V18,"") | BE18: =IF($AM18=0,"",IFERROR(MATCH($AF18&"|"&UPPER(TRIM($E18)),Lists!$A$6:$A$205,0),0)) -> 1 | BF18: =IF($AM18=0,"",IFERROR(MATCH($AF18,Settings!$B$14:$B$18,0),IFERROR(MATCH(Settings!$C$6,Settings!$B$14:$B$18,0),1))) -> 1 | BG18: =IF($AM18=0,"",IF(NOT(ISNUMBER($I18)),"No stop; ","")&IF(AND(ISNUMBER($H18),ISNUMBER($I18)),IF(OR(AND($F18<>"Short",$I18>=$H18),AND($F18="Short",$I18<=$H18)),"Stop on wrong side; ",""),"")&IF($F18="","No direction; ","")&IF(AND(ISNUMBER(Settings!$C$22),ISNUMBER($V18)),IF($V18>Settings!$C$22,"Risk over max $; ",""),"")&IF(AND(ISNUMBER(Settings!$C$23),ISNUMBER($V18),ISNUMBER($AP18),IFERROR(N(INDEX(Accounts!$E$7:$E$16,MATCH($C18,Accounts!$B$7:$B$16,0))),0)>0),IF($V18>Settings!$C$23*($AP18-N($Q18)),"Risk over max %; ",""),"")&IF(AND(ISNUMBER(Settings!$C$24),ISNUMBER($N18)),IF($N18>Settings!$C$24,"Leverage over max; ",""),"")&IF(AND(ISNUMBER(Settings!$C$27),ISNUMBER($T18)),IF($T18<Settings!$C$27,"R:R below min; ",""),"")&IF(ISNUMBER(Settings!$C$25),IF(COUNTIFS($A$6:$A18,$A18,$AM$6:$AM18,1)>Settings!$C$25,"Over max trades/day; ",""),"")&IF(ISNUMBER(Settings!$C$26),IF(SUMIFS($Q$5:$Q17,$A$5:$A17,$A18)<=-Settings!$C$26,"Traded after daily max loss; ",""),"")&IF(AND($AG18="",NOT(ISNUMBER($O18))),"Symbol not in Instruments; ","")&IF(AND($AH18="",NOT(ISNUMBER($O18))),"Forex cross: type Gross P&L; ","")) | BH18: =IF(ISNUMBER($Q18),1,0) -> 1 | BI18: =IF($Y18="",0,1) -> 0 | BJ18: =IF($AB18="",0,1) -> 1 | BK18: =IF(AND($BH18=1,$W18<>"OK"),1,0) -> 0 | BL18: =IF(N($AZ18)=0,0,IFERROR(INDEX($AT$6:$AT$1005,MATCH($AZ18,$AY$6:$AY$1005,0)),0)) -> 463.965 | BM18: =IF(ISNUMBER(SEARCH("daily max loss",$BG18)),1,0) -> 0
A19: 46290 | B19: 0.47916667 | C19: Prop Eval 50K | E19: MNQ | F19: Long | G19: 1 | H19: 29700 | I19: 29670 | J19: 29760 | K19: 29712.5 | L19: Market | M19: Manual | Q19: =IF($AM19=0,"",IF(ISNUMBER($AK19),$AK19-N($AL19),"")) -> 24 | R19: =IF(OR($Q19="",NOT(ISNUMBER($V19))),"",$AK19/$V19) -> 0.41666667 | S19: =IF($Q19="","",IF(AND(ISNUMBER($R19),ABS(N($R19))<N(Settings!$C$8)),"Scratch",IF($Q19>0,"Win",IF($Q19<0,"Loss","Scratch")))) -> Win | T19: =IF(OR($AM19=0,NOT(ISNUMBER($H19)),NOT(ISNUMBER($I19)),NOT(ISNUMBER($J19))),"",IF($H19=$I19,"",ROUND(ABS($J19-$H19)/ABS($H19-$I19),6))) -> 2 | U19: =IF(OR($S19<>"Win",NOT(ISNUMBER($T19)),NOT(ISNUMBER($R19))),"",MAX(0,$T19-$R19)) -> 1.5833333 | V19: =IF(OR($AM19=0,NOT(ISNUMBER($H19)),NOT(ISNUMBER($I19)),NOT(ISNUMBER($G19))),"",IF(OR($AG19="",$AH19=""),"",IF(ROUND(ABS($H19-$I19)*ABS($G19)*$AG19*$AH19,6)=0,"",ROUND(ABS($H19-$I19)*ABS($G19)*$AG19*$AH19,6)))) -> 60 | W19: =IF($AM19=0,"",IF($BG19="","OK",LEFT($BG19,LEN($BG19)-2))) -> Traded after daily max loss | X19: NY Midday | Z19: No | AA19: Tilted | AB19: Traded after max loss | AC19: Trying to make it back | AD19: Past my daily max loss. Never again. | AF19: =IF($AM19=0,"",IF($D19<>"",$D19,IF(IFERROR(INDEX(Accounts!$C$7:$C$16,MATCH($C19,Accounts!$B$7:$B$16,0))&"","")<>"",INDEX(Accounts!$C$7:$C$16,MATCH($C19,Accounts!$B$7:$B$16,0)),Settings!$C$6))) -> Futures | AG19: =IF($AM19=0,"",IF(AND($BE19>0,N(INDEX(Instruments!$D$6:$D$205,MAX(1,$BE19)))>0),INDEX(Instruments!$D$6:$D$205,MAX(1,$BE19)),IF(N(INDEX(Settings!$D$14:$D$18,$BF19))>0,INDEX(Settings!$D$14:$D$18,$BF19),""))) -> 2 | AH19: =IF($AM19=0,"",IF($AF19<>"Forex",1,IF(MID(UPPER(SUBSTITUTE(TRIM($E19),"/","")),4,3)=UPPER(TRIM(Settings!$C$7)),1,IF(LEFT(UPPER(SUBSTITUTE(TRIM($E19),"/","")),3)=UPPER(TRIM(Settings!$C$7)),IF(AND(ISNUMBER($K19),N($K19)<>0),1/$K19,""),"")))) -> 1 | AI19: =IF($AM19=0,"",IF(OR(NOT(ISNUMBER($H19)),NOT(ISNUMBER($K19)),NOT(ISNUMBER($G19)),$AG19="",$AH19=""),"",ROUND(($K19-$H19)*IF($F19="Short",-1,1)*$G19*$AG19*$AH19,6))) -> 25 | AJ19: =IF($AM19=0,"",IF(INDEX(Settings!$E$14:$E$18,$BF19)="% of notional",IF(OR($AG19="",NOT(ISNUMBER($H19)),NOT(ISNUMBER($G19))),"",ROUND(ABS($H19*$G19*$AG19*N($AH19))*IF($L19="Limit",N(INDEX(Settings!$G$14:$G$18,$BF19)),N(INDEX(Settings!$H$14:$H$18,$BF19)))+IF(ISNUMBER($K19),ABS($K19*$G19*$AG19*N($AH19))*IF($M19="Target",N(INDEX(Settings!$G$14:$G$18,$BF19)),N(INDEX(Settings!$H$14:$H$18,$BF19))),0),6)),IF(NOT(ISNUMBER($G19)),"",ROUND(ABS($G19)*2*IF(AND($BE19>0,ISNUMBER(INDEX(Instruments!$G$6:$G$205,MAX(1,$BE19)))),INDEX(Instruments!$G$6:$G$205,MAX(1,$BE19)),N(INDEX(Settings!$F$14:$F$18,$BF19))),6)))) -> 1 | AK19: =IF($AM19=0,"",IF(ISNUMBER($O19),$O19,$AI19)) -> 25 | AL19: =IF($AM19=0,"",IF(ISNUMBER($P19),$P19,N($AJ19))) -> 1 | AM19: =IF(AND($A19<>"",$E19<>"",OR(AND(ISNUMBER($G19),ISNUMBER($H19),ISNUMBER($K19)),ISNUMBER($O19))),1,0) -> 1 | AN19: =IF($A19="","",$A19-WEEKDAY($A19,3)) -> 46286 | AO19: =IF($A19="","",WEEKDAY($A19,2)) -> 5 | AP19: =IF(OR($AM19=0,$C19=""),"",IFERROR(N(INDEX(Accounts!$E$7:$E$16,MATCH($C19,Accounts!$B$7:$B$16,0))),0)+SUMIFS($Q$6:$Q19,$C$6:$C19,$C19)) -> 50363 | AQ19: =IF(OR($AM19=0,$C19=""),"",SUMIFS($Q$6:$Q$1005,$C$6:$C$1005,$C19,$A$6:$A$1005,$A19)) -> -395.5 | AR19: =IF(OR($AM19=0,$C19=""),"",IFERROR(N(INDEX(Accounts!$E$7:$E$16,MATCH($C19,Accounts!$B$7:$B$16,0))),0)+SUMIFS($Q$6:$Q$1005,$C$6:$C$1005,$C19,$A$6:$A$1005,"<="&$A19)) -> 50363 | AS19: =IF(OR($AM19=0,$Q19=""),0,IF(AND($A19>=Lists!$W$6,$A19<=Lists!$W$7,OR(Dashboard!$D$6="All accounts",$C19=Dashboard!$D$6),OR(Dashboard!$D$7="All markets",$AF19=Dashboard!$D$7)),1,0)) -> 1 | AT19: =IF($AS19=1,N(AT18)+$Q19,N(AT18)) -> 372.465 | AU19: =MAX(N(AU18),$AT19) -> 817.204 | AV19: =$AT19-$AU19 -> -444.739 | AW19: =IF($AS19=1,IF($S19="Win",N(AW18)+1,IF($S19="Loss",0,N(AW18))),N(AW18)) -> 1 | AX19: =IF($AS19=1,IF($S19="Loss",N(AX18)+1,IF($S19="Win",0,N(AX18))),N(AX18)) -> 0 | AY19: =IF($AS19=1,COUNTIF($AS$6:$AS19,1),"") -> 14 | AZ19: =MIN(13,N(Lists!$W$8)) -> 13 | BA19: =IF($AS19=1,IF(COUNTIFS($A$6:$A19,$A19,$AS$6:$AS19,1)=1,1,0),0) -> 0 | BB19: =IF($BA19=1,SUMIFS($Q$6:$Q$1005,$A$6:$A$1005,$A19,$AS$6:$AS$1005,1),"") | BC19: =IF(ISNUMBER($R19),1,0) -> 1 | BD19: =IF(ISNUMBER($U19),$U19*$V19,"") -> 95 | BE19: =IF($AM19=0,"",IFERROR(MATCH($AF19&"|"&UPPER(TRIM($E19)),Lists!$A$6:$A$205,0),0)) -> 3 | BF19: =IF($AM19=0,"",IFERROR(MATCH($AF19,Settings!$B$14:$B$18,0),IFERROR(MATCH(Settings!$C$6,Settings!$B$14:$B$18,0),1))) -> 1 | BG19: =IF($AM19=0,"",IF(NOT(ISNUMBER($I19)),"No stop; ","")&IF(AND(ISNUMBER($H19),ISNUMBER($I19)),IF(OR(AND($F19<>"Short",$I19>=$H19),AND($F19="Short",$I19<=$H19)),"Stop on wrong side; ",""),"")&IF($F19="","No direction; ","")&IF(AND(ISNUMBER(Settings!$C$22),ISNUMBER($V19)),IF($V19>Settings!$C$22,"Risk over max $; ",""),"")&IF(AND(ISNUMBER(Settings!$C$23),ISNUMBER($V19),ISNUMBER($AP19),IFERROR(N(INDEX(Accounts!$E$7:$E$16,MATCH($C19,Accounts!$B$7:$B$16,0))),0)>0),IF($V19>Settings!$C$23*($AP19-N($Q19)),"Risk over max %; ",""),"")&IF(AND(ISNUMBER(Settings!$C$24),ISNUMBER($N19)),IF($N19>Settings!$C$24,"Leverage over max; ",""),"")&IF(AND(ISNUMBER(Settings!$C$27),ISNUMBER($T19)),IF($T19<Settings!$C$27,"R:R below min; ",""),"")&IF(ISNUMBER(Settings!$C$25),IF(COUNTIFS($A$6:$A19,$A19,$AM$6:$AM19,1)>Settings!$C$25,"Over max trades/day; ",""),"")&IF(ISNUMBER(Settings!$C$26),IF(SUMIFS($Q$5:$Q18,$A$5:$A18,$A19)<=-Settings!$C$26,"Traded after daily max loss; ",""),"")&IF(AND($AG19="",NOT(ISNUMBER($O19))),"Symbol not in Instruments; ","")&IF(AND($AH19="",NOT(ISNUMBER($O19))),"Forex cross: type Gross P&L; ","")) -> Traded after daily max loss; | BH19: =IF(ISNUMBER($Q19),1,0) -> 1 | BI19: =IF($Y19="",0,1) -> 0 | BJ19: =IF($AB19="",0,1) -> 1 | BK19: =IF(AND($BH19=1,$W19<>"OK"),1,0) -> 1 | BL19: =IF(N($AZ19)=0,0,IFERROR(INDEX($AT$6:$AT$1005,MATCH($AZ19,$AY$6:$AY$1005,0)),0)) -> 348.465 | BM19: =IF(ISNUMBER(SEARCH("daily max loss",$BG19)),1,0) -> 1
A20: 46291 | B20: 0.45833333 | C20: Crypto Main | E20: SOLUSDT | F20: Long | G20: 24 | H20: 148.5 | I20: 146 | J20: 153.5 | K20: 152.8 | L20: Limit | M20: Manual | N20: 8 | Q20: =IF($AM20=0,"",IF(ISNUMBER($AK20),$AK20-N($AL20),"")) -> 100.28688 | R20: =IF(OR($Q20="",NOT(ISNUMBER($V20))),"",$AK20/$V20) -> 1.72 | S20: =IF($Q20="","",IF(AND(ISNUMBER($R20),ABS(N($R20))<N(Settings!$C$8)),"Scratch",IF($Q20>0,"Win",IF($Q20<0,"Loss","Scratch")))) -> Win | T20: =IF(OR($AM20=0,NOT(ISNUMBER($H20)),NOT(ISNUMBER($I20)),NOT(ISNUMBER($J20))),"",IF($H20=$I20,"",ROUND(ABS($J20-$H20)/ABS($H20-$I20),6))) -> 2 | U20: =IF(OR($S20<>"Win",NOT(ISNUMBER($T20)),NOT(ISNUMBER($R20))),"",MAX(0,$T20-$R20)) -> 0.28 | V20: =IF(OR($AM20=0,NOT(ISNUMBER($H20)),NOT(ISNUMBER($I20)),NOT(ISNUMBER($G20))),"",IF(OR($AG20="",$AH20=""),"",IF(ROUND(ABS($H20-$I20)*ABS($G20)*$AG20*$AH20,6)=0,"",ROUND(ABS($H20-$I20)*ABS($G20)*$AG20*$AH20,6)))) -> 60 | W20: =IF($AM20=0,"",IF($BG20="","OK",LEFT($BG20,LEN($BG20)-2))) -> Risk over max % | X20: Weekend | Y20: Trend Pullback | Z20: No | AA20: Greedy | AB20: Oversized | AC20: Weekend trend pullback | AD20: Risked 1.2% - over my 1% rule. | AF20: =IF($AM20=0,"",IF($D20<>"",$D20,IF(IFERROR(INDEX(Accounts!$C$7:$C$16,MATCH($C20,Accounts!$B$7:$B$16,0))&"","")<>"",INDEX(Accounts!$C$7:$C$16,MATCH($C20,Accounts!$B$7:$B$16,0)),Settings!$C$6))) -> Crypto | AG20: =IF($AM20=0,"",IF(AND($BE20>0,N(INDEX(Instruments!$D$6:$D$205,MAX(1,$BE20)))>0),INDEX(Instruments!$D$6:$D$205,MAX(1,$BE20)),IF(N(INDEX(Settings!$D$14:$D$18,$BF20))>0,INDEX(Settings!$D$14:$D$18,$BF20),""))) -> 1 | AH20: =IF($AM20=0,"",IF($AF20<>"Forex",1,IF(MID(UPPER(SUBSTITUTE(TRIM($E20),"/","")),4,3)=UPPER(TRIM(Settings!$C$7)),1,IF(LEFT(UPPER(SUBSTITUTE(TRIM($E20),"/","")),3)=UPPER(TRIM(Settings!$C$7)),IF(AND(ISNUMBER($K20),N($K20)<>0),1/$K20,""),"")))) -> 1 | AI20: =IF($AM20=0,"",IF(OR(NOT(ISNUMBER($H20)),NOT(ISNUMBER($K20)),NOT(ISNUMBER($G20)),$AG20="",$AH20=""),"",ROUND(($K20-$H20)*IF($F20="Short",-1,1)*$G20*$AG20*$AH20,6))) -> 103.2 | AJ20: =IF($AM20=0,"",IF(INDEX(Settings!$E$14:$E$18,$BF20)="% of notional",IF(OR($AG20="",NOT(ISNUMBER($H20)),NOT(ISNUMBER($G20))),"",ROUND(ABS($H20*$G20*$AG20*N($AH20))*IF($L20="Limit",N(INDEX(Settings!$G$14:$G$18,$BF20)),N(INDEX(Settings!$H$14:$H$18,$BF20)))+IF(ISNUMBER($K20),ABS($K20*$G20*$AG20*N($AH20))*IF($M20="Target",N(INDEX(Settings!$G$14:$G$18,$BF20)),N(INDEX(Settings!$H$14:$H$18,$BF20))),0),6)),IF(NOT(ISNUMBER($G20)),"",ROUND(ABS($G20)*2*IF(AND($BE20>0,ISNUMBER(INDEX(Instruments!$G$6:$G$205,MAX(1,$BE20)))),INDEX(Instruments!$G$6:$G$205,MAX(1,$BE20)),N(INDEX(Settings!$F$14:$F$18,$BF20))),6)))) -> 2.91312 | AK20: =IF($AM20=0,"",IF(ISNUMBER($O20),$O20,$AI20)) -> 103.2 | AL20: =IF($AM20=0,"",IF(ISNUMBER($P20),$P20,N($AJ20))) -> 2.91312 | AM20: =IF(AND($A20<>"",$E20<>"",OR(AND(ISNUMBER($G20),ISNUMBER($H20),ISNUMBER($K20)),ISNUMBER($O20))),1,0) -> 1 | AN20: =IF($A20="","",$A20-WEEKDAY($A20,3)) -> 46286 | AO20: =IF($A20="","",WEEKDAY($A20,2)) -> 6 | AP20: =IF(OR($AM20=0,$C20=""),"",IFERROR(N(INDEX(Accounts!$E$7:$E$16,MATCH($C20,Accounts!$B$7:$B$16,0))),0)+SUMIFS($Q$6:$Q20,$C$6:$C20,$C20)) -> 5109.7519 | AQ20: =IF(OR($AM20=0,$C20=""),"",SUMIFS($Q$6:$Q$1005,$C$6:$C$1005,$C20,$A$6:$A$1005,$A20)) -> 100.28688 | AR20: =IF(OR($AM20=0,$C20=""),"",IFERROR(N(INDEX(Accounts!$E$7:$E$16,MATCH($C20,Accounts!$B$7:$B$16,0))),0)+SUMIFS($Q$6:$Q$1005,$C$6:$C$1005,$C20,$A$6:$A$1005,"<="&$A20)) -> 5109.7519 | AS20: =IF(OR($AM20=0,$Q20=""),0,IF(AND($A20>=Lists!$W$6,$A20<=Lists!$W$7,OR(Dashboard!$D$6="All accounts",$C20=Dashboard!$D$6),OR(Dashboard!$D$7="All markets",$AF20=Dashboard!$D$7)),1,0)) -> 1 | AT20: =IF($AS20=1,N(AT19)+$Q20,N(AT19)) -> 472.75188 | AU20: =MAX(N(AU19),$AT20) -> 817.204 | AV20: =$AT20-$AU20 -> -344.45212 | AW20: =IF($AS20=1,IF($S20="Win",N(AW19)+1,IF($S20="Loss",0,N(AW19))),N(AW19)) -> 2 | AX20: =IF($AS20=1,IF($S20="Loss",N(AX19)+1,IF($S20="Win",0,N(AX19))),N(AX19)) -> 0 | AY20: =IF($AS20=1,COUNTIF($AS$6:$AS20,1),"") -> 15 | AZ20: =MIN(14,N(Lists!$W$8)) -> 14 | BA20: =IF($AS20=1,IF(COUNTIFS($A$6:$A20,$A20,$AS$6:$AS20,1)=1,1,0),0) -> 1 | BB20: =IF($BA20=1,SUMIFS($Q$6:$Q$1005,$A$6:$A$1005,$A20,$AS$6:$AS$1005,1),"") -> 100.28688 | BC20: =IF(ISNUMBER($R20),1,0) -> 1 | BD20: =IF(ISNUMBER($U20),$U20*$V20,"") -> 16.8 | BE20: =IF($AM20=0,"",IFERROR(MATCH($AF20&"|"&UPPER(TRIM($E20)),Lists!$A$6:$A$205,0),0)) -> 48 | BF20: =IF($AM20=0,"",IFERROR(MATCH($AF20,Settings!$B$14:$B$18,0),IFERROR(MATCH(Settings!$C$6,Settings!$B$14:$B$18,0),1))) -> 5 | BG20: =IF($AM20=0,"",IF(NOT(ISNUMBER($I20)),"No stop; ","")&IF(AND(ISNUMBER($H20),ISNUMBER($I20)),IF(OR(AND($F20<>"Short",$I20>=$H20),AND($F20="Short",$I20<=$H20)),"Stop on wrong side; ",""),"")&IF($F20="","No direction; ","")&IF(AND(ISNUMBER(Settings!$C$22),ISNUMBER($V20)),IF($V20>Settings!$C$22,"Risk over max $; ",""),"")&IF(AND(ISNUMBER(Settings!$C$23),ISNUMBER($V20),ISNUMBER($AP20),IFERROR(N(INDEX(Accounts!$E$7:$E$16,MATCH($C20,Accounts!$B$7:$B$16,0))),0)>0),IF($V20>Settings!$C$23*($AP20-N($Q20)),"Risk over max %; ",""),"")&IF(AND(ISNUMBER(Settings!$C$24),ISNUMBER($N20)),IF($N20>Settings!$C$24,"Leverage over max; ",""),"")&IF(AND(ISNUMBER(Settings!$C$27),ISNUMBER($T20)),IF($T20<Settings!$C$27,"R:R below min; ",""),"")&IF(ISNUMBER(Settings!$C$25),IF(COUNTIFS($A$6:$A20,$A20,$AM$6:$AM20,1)>Settings!$C$25,"Over max trades/day; ",""),"")&IF(ISNUMBER(Settings!$C$26),IF(SUMIFS($Q$5:$Q19,$A$5:$A19,$A20)<=-Settings!$C$26,"Traded after daily max loss; ",""),"")&IF(AND($AG20="",NOT(ISNUMBER($O20))),"Symbol not in Instruments; ","")&IF(AND($AH20="",NOT(ISNUMBER($O20))),"Forex cross: type Gross P&L; ","")) -> Risk over max %; | BH20: =IF(ISNUMBER($Q20),1,0) -> 1 | BI20: =IF($Y20="",0,1) -> 1 | BJ20: =IF($AB20="",0,1) -> 1 | BK20: =IF(AND($BH20=1,$W20<>"OK"),1,0) -> 1 | BL20: =IF(N($AZ20)=0,0,IFERROR(INDEX($AT$6:$AT$1005,MATCH($AZ20,$AY$6:$AY$1005,0)),0)) -> 372.465 | BM20: =IF(ISNUMBER(SEARCH("daily max loss",$BG20)),1,0) -> 0
A21: 46293 | B21: 0.40138889 | C21: Prop Eval 50K | E21: MNQ | F21: Long | G21: 2 | H21: 29560 | I21: 29530 | J21: 29620 | K21: 29620 | L21: Limit | M21: Target | Q21: =IF($AM21=0,"",IF(ISNUMBER($AK21),$AK21-N($AL21),"")) -> 238 | R21: =IF(OR($Q21="",NOT(ISNUMBER($V21))),"",$AK21/$V21) -> 2 | S21: =IF($Q21="","",IF(AND(ISNUMBER($R21),ABS(N($R21))<N(Settings!$C$8)),"Scratch",IF($Q21>0,"Win",IF($Q21<0,"Loss","Scratch")))) -> Win | T21: =IF(OR($AM21=0,NOT(ISNUMBER($H21)),NOT(ISNUMBER($I21)),NOT(ISNUMBER($J21))),"",IF($H21=$I21,"",ROUND(ABS($J21-$H21)/ABS($H21-$I21),6))) -> 2 | U21: =IF(OR($S21<>"Win",NOT(ISNUMBER($T21)),NOT(ISNUMBER($R21))),"",MAX(0,$T21-$R21)) -> 0 | V21: =IF(OR($AM21=0,NOT(ISNUMBER($H21)),NOT(ISNUMBER($I21)),NOT(ISNUMBER($G21))),"",IF(OR($AG21="",$AH21=""),"",IF(ROUND(ABS($H21-$I21)*ABS($G21)*$AG21*$AH21,6)=0,"",ROUND(ABS($H21-$I21)*ABS($G21)*$AG21*$AH21,6)))) -> 120 | W21: =IF($AM21=0,"",IF($BG21="","OK",LEFT($BG21,LEN($BG21)-2))) -> OK | X21: NY Open | Y21: Breakout & Retest | Z21: Yes | AA21: Calm | AC21: Opening range breakout, clean retest | AD21: A-grade. | AF21: =IF($AM21=0,"",IF($D21<>"",$D21,IF(IFERROR(INDEX(Accounts!$C$7:$C$16,MATCH($C21,Accounts!$B$7:$B$16,0))&"","")<>"",INDEX(Accounts!$C$7:$C$16,MATCH($C21,Accounts!$B$7:$B$16,0)),Settings!$C$6))) -> Futures | AG21: =IF($AM21=0,"",IF(AND($BE21>0,N(INDEX(Instruments!$D$6:$D$205,MAX(1,$BE21)))>0),INDEX(Instruments!$D$6:$D$205,MAX(1,$BE21)),IF(N(INDEX(Settings!$D$14:$D$18,$BF21))>0,INDEX(Settings!$D$14:$D$18,$BF21),""))) -> 2 | AH21: =IF($AM21=0,"",IF($AF21<>"Forex",1,IF(MID(UPPER(SUBSTITUTE(TRIM($E21),"/","")),4,3)=UPPER(TRIM(Settings!$C$7)),1,IF(LEFT(UPPER(SUBSTITUTE(TRIM($E21),"/","")),3)=UPPER(TRIM(Settings!$C$7)),IF(AND(ISNUMBER($K21),N($K21)<>0),1/$K21,""),"")))) -> 1 | AI21: =IF($AM21=0,"",IF(OR(NOT(ISNUMBER($H21)),NOT(ISNUMBER($K21)),NOT(ISNUMBER($G21)),$AG21="",$AH21=""),"",ROUND(($K21-$H21)*IF($F21="Short",-1,1)*$G21*$AG21*$AH21,6))) -> 240 | AJ21: =IF($AM21=0,"",IF(INDEX(Settings!$E$14:$E$18,$BF21)="% of notional",IF(OR($AG21="",NOT(ISNUMBER($H21)),NOT(ISNUMBER($G21))),"",ROUND(ABS($H21*$G21*$AG21*N($AH21))*IF($L21="Limit",N(INDEX(Settings!$G$14:$G$18,$BF21)),N(INDEX(Settings!$H$14:$H$18,$BF21)))+IF(ISNUMBER($K21),ABS($K21*$G21*$AG21*N($AH21))*IF($M21="Target",N(INDEX(Settings!$G$14:$G$18,$BF21)),N(INDEX(Settings!$H$14:$H$18,$BF21))),0),6)),IF(NOT(ISNUMBER($G21)),"",ROUND(ABS($G21)*2*IF(AND($BE21>0,ISNUMBER(INDEX(Instruments!$G$6:$G$205,MAX(1,$BE21)))),INDEX(Instruments!$G$6:$G$205,MAX(1,$BE21)),N(INDEX(Settings!$F$14:$F$18,$BF21))),6)))) -> 2 | AK21: =IF($AM21=0,"",IF(ISNUMBER($O21),$O21,$AI21)) -> 240 | AL21: =IF($AM21=0,"",IF(ISNUMBER($P21),$P21,N($AJ21))) -> 2 | AM21: =IF(AND($A21<>"",$E21<>"",OR(AND(ISNUMBER($G21),ISNUMBER($H21),ISNUMBER($K21)),ISNUMBER($O21))),1,0) -> 1 | AN21: =IF($A21="","",$A21-WEEKDAY($A21,3)) -> 46293 | AO21: =IF($A21="","",WEEKDAY($A21,2)) -> 1 | AP21: =IF(OR($AM21=0,$C21=""),"",IFERROR(N(INDEX(Accounts!$E$7:$E$16,MATCH($C21,Accounts!$B$7:$B$16,0))),0)+SUMIFS($Q$6:$Q21,$C$6:$C21,$C21)) -> 50601 | AQ21: =IF(OR($AM21=0,$C21=""),"",SUMIFS($Q$6:$Q$1005,$C$6:$C$1005,$C21,$A$6:$A$1005,$A21)) -> 296 | AR21: =IF(OR($AM21=0,$C21=""),"",IFERROR(N(INDEX(Accounts!$E$7:$E$16,MATCH($C21,Accounts!$B$7:$B$16,0))),0)+SUMIFS($Q$6:$Q$1005,$C$6:$C$1005,$C21,$A$6:$A$1005,"<="&$A21)) -> 50659 | AS21: =IF(OR($AM21=0,$Q21=""),0,IF(AND($A21>=Lists!$W$6,$A21<=Lists!$W$7,OR(Dashboard!$D$6="All accounts",$C21=Dashboard!$D$6),OR(Dashboard!$D$7="All markets",$AF21=Dashboard!$D$7)),1,0)) -> 1 | AT21: =IF($AS21=1,N(AT20)+$Q21,N(AT20)) -> 710.75188 | AU21: =MAX(N(AU20),$AT21) -> 817.204 | AV21: =$AT21-$AU21 -> -106.45212 | AW21: =IF($AS21=1,IF($S21="Win",N(AW20)+1,IF($S21="Loss",0,N(AW20))),N(AW20)) -> 3 | AX21: =IF($AS21=1,IF($S21="Loss",N(AX20)+1,IF($S21="Win",0,N(AX20))),N(AX20)) -> 0 | AY21: =IF($AS21=1,COUNTIF($AS$6:$AS21,1),"") -> 16 | AZ21: =MIN(15,N(Lists!$W$8)) -> 15 | BA21: =IF($AS21=1,IF(COUNTIFS($A$6:$A21,$A21,$AS$6:$AS21,1)=1,1,0),0) -> 1 | BB21: =IF($BA21=1,SUMIFS($Q$6:$Q$1005,$A$6:$A$1005,$A21,$AS$6:$AS$1005,1),"") -> 296 | BC21: =IF(ISNUMBER($R21),1,0) -> 1 | BD21: =IF(ISNUMBER($U21),$U21*$V21,"") -> 0 | BE21: =IF($AM21=0,"",IFERROR(MATCH($AF21&"|"&UPPER(TRIM($E21)),Lists!$A$6:$A$205,0),0)) -> 3 | BF21: =IF($AM21=0,"",IFERROR(MATCH($AF21,Settings!$B$14:$B$18,0),IFERROR(MATCH(Settings!$C$6,Settings!$B$14:$B$18,0),1))) -> 1 | BG21: =IF($AM21=0,"",IF(NOT(ISNUMBER($I21)),"No stop; ","")&IF(AND(ISNUMBER($H21),ISNUMBER($I21)),IF(OR(AND($F21<>"Short",$I21>=$H21),AND($F21="Short",$I21<=$H21)),"Stop on wrong side; ",""),"")&IF($F21="","No direction; ","")&IF(AND(ISNUMBER(Settings!$C$22),ISNUMBER($V21)),IF($V21>Settings!$C$22,"Risk over max $; ",""),"")&IF(AND(ISNUMBER(Settings!$C$23),ISNUMBER($V21),ISNUMBER($AP21),IFERROR(N(INDEX(Accounts!$E$7:$E$16,MATCH($C21,Accounts!$B$7:$B$16,0))),0)>0),IF($V21>Settings!$C$23*($AP21-N($Q21)),"Risk over max %; ",""),"")&IF(AND(ISNUMBER(Settings!$C$24),ISNUMBER($N21)),IF($N21>Settings!$C$24,"Leverage over max; ",""),"")&IF(AND(ISNUMBER(Settings!$C$27),ISNUMBER($T21)),IF($T21<Settings!$C$27,"R:R below min; ",""),"")&IF(ISNUMBER(Settings!$C$25),IF(COUNTIFS($A$6:$A21,$A21,$AM$6:$AM21,1)>Settings!$C$25,"Over max trades/day; ",""),"")&IF(ISNUMBER(Settings!$C$26),IF(SUMIFS($Q$5:$Q20,$A$5:$A20,$A21)<=-Settings!$C$26,"Traded after daily max loss; ",""),"")&IF(AND($AG21="",NOT(ISNUMBER($O21))),"Symbol not in Instruments; ","")&IF(AND($AH21="",NOT(ISNUMBER($O21))),"Forex cross: type Gross P&L; ","")) | BH21: =IF(ISNUMBER($Q21),1,0) -> 1 | BI21: =IF($Y21="",0,1) -> 1 | BJ21: =IF($AB21="",0,1) -> 0 | BK21: =IF(AND($BH21=1,$W21<>"OK"),1,0) -> 0 | BL21: =IF(N($AZ21)=0,0,IFERROR(INDEX($AT$6:$AT$1005,MATCH($AZ21,$AY$6:$AY$1005,0)),0)) -> 472.75188 | BM21: =IF(ISNUMBER(SEARCH("daily max loss",$BG21)),1,0) -> 0
A22: 46293 | B22: 0.45138889 | C22: Prop Eval 50K | E22: MCL | F22: Long | G22: 2 | H22: 68.4 | I22: 68.1 | J22: 68.7 | K22: 68.7 | L22: Limit | M22: Target | Q22: =IF($AM22=0,"",IF(ISNUMBER($AK22),$AK22-N($AL22),"")) -> 58 | R22: =IF(OR($Q22="",NOT(ISNUMBER($V22))),"",$AK22/$V22) -> 1 | S22: =IF($Q22="","",IF(AND(ISNUMBER($R22),ABS(N($R22))<N(Settings!$C$8)),"Scratch",IF($Q22>0,"Win",IF($Q22<0,"Loss","Scratch")))) -> Win | T22: =IF(OR($AM22=0,NOT(ISNUMBER($H22)),NOT(ISNUMBER($I22)),NOT(ISNUMBER($J22))),"",IF($H22=$I22,"",ROUND(ABS($J22-$H22)/ABS($H22-$I22),6))) -> 1 | U22: =IF(OR($S22<>"Win",NOT(ISNUMBER($T22)),NOT(ISNUMBER($R22))),"",MAX(0,$T22-$R22)) -> 0 | V22: =IF(OR($AM22=0,NOT(ISNUMBER($H22)),NOT(ISNUMBER($I22)),NOT(ISNUMBER($G22))),"",IF(OR($AG22="",$AH22=""),"",IF(ROUND(ABS($H22-$I22)*ABS($G22)*$AG22*$AH22,6)=0,"",ROUND(ABS($H22-$I22)*ABS($G22)*$AG22*$AH22,6)))) -> 60 | W22: =IF($AM22=0,"",IF($BG22="","OK",LEFT($BG22,LEN($BG22)-2))) -> R:R below min | X22: NY Open | Y22: Trend Pullback | Z22: Yes | AA22: Confident | AC22: Crude pullback to the 20 EMA | AD22: Target was only 1R - below my 1.5R minimum. | AF22: =IF($AM22=0,"",IF($D22<>"",$D22,IF(IFERROR(INDEX(Accounts!$C$7:$C$16,MATCH($C22,Accounts!$B$7:$B$16,0))&"","")<>"",INDEX(Accounts!$C$7:$C$16,MATCH($C22,Accounts!$B$7:$B$16,0)),Settings!$C$6))) -> Futures | AG22: =IF($AM22=0,"",IF(AND($BE22>0,N(INDEX(Instruments!$D$6:$D$205,MAX(1,$BE22)))>0),INDEX(Instruments!$D$6:$D$205,MAX(1,$BE22)),IF(N(INDEX(Settings!$D$14:$D$18,$BF22))>0,INDEX(Settings!$D$14:$D$18,$BF22),""))) -> 100 | AH22: =IF($AM22=0,"",IF($AF22<>"Forex",1,IF(MID(UPPER(SUBSTITUTE(TRIM($E22),"/","")),4,3)=UPPER(TRIM(Settings!$C$7)),1,IF(LEFT(UPPER(SUBSTITUTE(TRIM($E22),"/","")),3)=UPPER(TRIM(Settings!$C$7)),IF(AND(ISNUMBER($K22),N($K22)<>0),1/$K22,""),"")))) -> 1 | AI22: =IF($AM22=0,"",IF(OR(NOT(ISNUMBER($H22)),NOT(ISNUMBER($K22)),NOT(ISNUMBER($G22)),$AG22="",$AH22=""),"",ROUND(($K22-$H22)*IF($F22="Short",-1,1)*$G22*$AG22*$AH22,6))) -> 60 | AJ22: =IF($AM22=0,"",IF(INDEX(Settings!$E$14:$E$18,$BF22)="% of notional",IF(OR($AG22="",NOT(ISNUMBER($H22)),NOT(ISNUMBER($G22))),"",ROUND(ABS($H22*$G22*$AG22*N($AH22))*IF($L22="Limit",N(INDEX(Settings!$G$14:$G$18,$BF22)),N(INDEX(Settings!$H$14:$H$18,$BF22)))+IF(ISNUMBER($K22),ABS($K22*$G22*$AG22*N($AH22))*IF($M22="Target",N(INDEX(Settings!$G$14:$G$18,$BF22)),N(INDEX(Settings!$H$14:$H$18,$BF22))),0),6)),IF(NOT(ISNUMBER($G22)),"",ROUND(ABS($G22)*2*IF(AND($BE22>0,ISNUMBER(INDEX(Instruments!$G$6:$G$205,MAX(1,$BE22)))),INDEX(Instruments!$G$6:$G$205,MAX(1,$BE22)),N(INDEX(Settings!$F$14:$F$18,$BF22))),6)))) -> 2 | AK22: =IF($AM22=0,"",IF(ISNUMBER($O22),$O22,$AI22)) -> 60 | AL22: =IF($AM22=0,"",IF(ISNUMBER($P22),$P22,N($AJ22))) -> 2 | AM22: =IF(AND($A22<>"",$E22<>"",OR(AND(ISNUMBER($G22),ISNUMBER($H22),ISNUMBER($K22)),ISNUMBER($O22))),1,0) -> 1 | AN22: =IF($A22="","",$A22-WEEKDAY($A22,3)) -> 46293 | AO22: =IF($A22="","",WEEKDAY($A22,2)) -> 1 | AP22: =IF(OR($AM22=0,$C22=""),"",IFERROR(N(INDEX(Accounts!$E$7:$E$16,MATCH($C22,Accounts!$B$7:$B$16,0))),0)+SUMIFS($Q$6:$Q22,$C$6:$C22,$C22)) -> 50659 | AQ22: =IF(OR($AM22=0,$C22=""),"",SUMIFS($Q$6:$Q$1005,$C$6:$C$1005,$C22,$A$6:$A$1005,$A22)) -> 296 | AR22: =IF(OR($AM22=0,$C22=""),"",IFERROR(N(INDEX(Accounts!$E$7:$E$16,MATCH($C22,Accounts!$B$7:$B$16,0))),0)+SUMIFS($Q$6:$Q$1005,$C$6:$C$1005,$C22,$A$6:$A$1005,"<="&$A22)) -> 50659 | AS22: =IF(OR($AM22=0,$Q22=""),0,IF(AND($A22>=Lists!$W$6,$A22<=Lists!$W$7,OR(Dashboard!$D$6="All accounts",$C22=Dashboard!$D$6),OR(Dashboard!$D$7="All markets",$AF22=Dashboard!$D$7)),1,0)) -> 1 | AT22: =IF($AS22=1,N(AT21)+$Q22,N(AT21)) -> 768.75188 | AU22: =MAX(N(AU21),$AT22) -> 817.204 | AV22: =$AT22-$AU22 -> -48.45212 | AW22: =IF($AS22=1,IF($S22="Win",N(AW21)+1,IF($S22="Loss",0,N(AW21))),N(AW21)) -> 4 | AX22: =IF($AS22=1,IF($S22="Loss",N(AX21)+1,IF($S22="Win",0,N(AX21))),N(AX21)) -> 0 | AY22: =IF($AS22=1,COUNTIF($AS$6:$AS22,1),"") -> 17 | AZ22: =MIN(16,N(Lists!$W$8)) -> 16 | BA22: =IF($AS22=1,IF(COUNTIFS($A$6:$A22,$A22,$AS$6:$AS22,1)=1,1,0),0) -> 0 | BB22: =IF($BA22=1,SUMIFS($Q$6:$Q$1005,$A$6:$A$1005,$A22,$AS$6:$AS$1005,1),"") | BC22: =IF(ISNUMBER($R22),1,0) -> 1 | BD22: =IF(ISNUMBER($U22),$U22*$V22,"") -> 0 | BE22: =IF($AM22=0,"",IFERROR(MATCH($AF22&"|"&UPPER(TRIM($E22)),Lists!$A$6:$A$205,0),0)) -> 9 | BF22: =IF($AM22=0,"",IFERROR(MATCH($AF22,Settings!$B$14:$B$18,0),IFERROR(MATCH(Settings!$C$6,Settings!$B$14:$B$18,0),1))) -> 1 | BG22: =IF($AM22=0,"",IF(NOT(ISNUMBER($I22)),"No stop; ","")&IF(AND(ISNUMBER($H22),ISNUMBER($I22)),IF(OR(AND($F22<>"Short",$I22>=$H22),AND($F22="Short",$I22<=$H22)),"Stop on wrong side; ",""),"")&IF($F22="","No direction; ","")&IF(AND(ISNUMBER(Settings!$C$22),ISNUMBER($V22)),IF($V22>Settings!$C$22,"Risk over max $; ",""),"")&IF(AND(ISNUMBER(Settings!$C$23),ISNUMBER($V22),ISNUMBER($AP22),IFERROR(N(INDEX(Accounts!$E$7:$E$16,MATCH($C22,Accounts!$B$7:$B$16,0))),0)>0),IF($V22>Settings!$C$23*($AP22-N($Q22)),"Risk over max %; ",""),"")&IF(AND(ISNUMBER(Settings!$C$24),ISNUMBER($N22)),IF($N22>Settings!$C$24,"Leverage over max; ",""),"")&IF(AND(ISNUMBER(Settings!$C$27),ISNUMBER($T22)),IF($T22<Settings!$C$27,"R:R below min; ",""),"")&IF(ISNUMBER(Settings!$C$25),IF(COUNTIFS($A$6:$A22,$A22,$AM$6:$AM22,1)>Settings!$C$25,"Over max trades/day; ",""),"")&IF(ISNUMBER(Settings!$C$26),IF(SUMIFS($Q$5:$Q21,$A$5:$A21,$A22)<=-Settings!$C$26,"Traded after daily max loss; ",""),"")&IF(AND($AG22="",NOT(ISNUMBER($O22))),"Symbol not in Instruments; ","")&IF(AND($AH22="",NOT(ISNUMBER($O22))),"Forex cross: type Gross P&L; ","")) -> R:R below min; | BH22: =IF(ISNUMBER($Q22),1,0) -> 1 | BI22: =IF($Y22="",0,1) -> 1 | BJ22: =IF($AB22="",0,1) -> 0 | BK22: =IF(AND($BH22=1,$W22<>"OK"),1,0) -> 1 | BL22: =IF(N($AZ22)=0,0,IFERROR(INDEX($AT$6:$AT$1005,MATCH($AZ22,$AY$6:$AY$1005,0)),0)) -> 710.75188 | BM22: =IF(ISNUMBER(SEARCH("daily max loss",$BG22)),1,0) -> 0
A23: 46294 | B23: 0.40625 | C23: Prop Eval 50K | E23: MES | F23: Short | G23: 2 | H23: 7648.75 | I23: 7656.25 | J23: 7633.75 | K23: 7633.75 | L23: Limit | M23: Target | Q23: =IF($AM23=0,"",IF(ISNUMBER($AK23),$AK23-N($AL23),"")) -> 148 | R23: =IF(OR($Q23="",NOT(ISNUMBER($V23))),"",$AK23/$V23) -> 2 | S23: =IF($Q23="","",IF(AND(ISNUMBER($R23),ABS(N($R23))<N(Settings!$C$8)),"Scratch",IF($Q23>0,"Win",IF($Q23<0,"Loss","Scratch")))) -> Win | T23: =IF(OR($AM23=0,NOT(ISNUMBER($H23)),NOT(ISNUMBER($I23)),NOT(ISNUMBER($J23))),"",IF($H23=$I23,"",ROUND(ABS($J23-$H23)/ABS($H23-$I23),6))) -> 2 | U23: =IF(OR($S23<>"Win",NOT(ISNUMBER($T23)),NOT(ISNUMBER($R23))),"",MAX(0,$T23-$R23)) -> 0 | V23: =IF(OR($AM23=0,NOT(ISNUMBER($H23)),NOT(ISNUMBER($I23)),NOT(ISNUMBER($G23))),"",IF(OR($AG23="",$AH23=""),"",IF(ROUND(ABS($H23-$I23)*ABS($G23)*$AG23*$AH23,6)=0,"",ROUND(ABS($H23-$I23)*ABS($G23)*$AG23*$AH23,6)))) -> 75 | W23: =IF($AM23=0,"",IF($BG23="","OK",LEFT($BG23,LEN($BG23)-2))) -> OK | X23: NY Open | Y23: Range Fade | Z23: Yes | AA23: Calm | AC23: Rejection at range high | AD23: Clean. | AF23: =IF($AM23=0,"",IF($D23<>"",$D23,IF(IFERROR(INDEX(Accounts!$C$7:$C$16,MATCH($C23,Accounts!$B$7:$B$16,0))&"","")<>"",INDEX(Accounts!$C$7:$C$16,MATCH($C23,Accounts!$B$7:$B$16,0)),Settings!$C$6))) -> Futures | AG23: =IF($AM23=0,"",IF(AND($BE23>0,N(INDEX(Instruments!$D$6:$D$205,MAX(1,$BE23)))>0),INDEX(Instruments!$D$6:$D$205,MAX(1,$BE23)),IF(N(INDEX(Settings!$D$14:$D$18,$BF23))>0,INDEX(Settings!$D$14:$D$18,$BF23),""))) -> 5 | AH23: =IF($AM23=0,"",IF($AF23<>"Forex",1,IF(MID(UPPER(SUBSTITUTE(TRIM($E23),"/","")),4,3)=UPPER(TRIM(Settings!$C$7)),1,IF(LEFT(UPPER(SUBSTITUTE(TRIM($E23),"/","")),3)=UPPER(TRIM(Settings!$C$7)),IF(AND(ISNUMBER($K23),N($K23)<>0),1/$K23,""),"")))) -> 1 | AI23: =IF($AM23=0,"",IF(OR(NOT(ISNUMBER($H23)),NOT(ISNUMBER($K23)),NOT(ISNUMBER($G23)),$AG23="",$AH23=""),"",ROUND(($K23-$H23)*IF($F23="Short",-1,1)*$G23*$AG23*$AH23,6))) -> 150 | AJ23: =IF($AM23=0,"",IF(INDEX(Settings!$E$14:$E$18,$BF23)="% of notional",IF(OR($AG23="",NOT(ISNUMBER($H23)),NOT(ISNUMBER($G23))),"",ROUND(ABS($H23*$G23*$AG23*N($AH23))*IF($L23="Limit",N(INDEX(Settings!$G$14:$G$18,$BF23)),N(INDEX(Settings!$H$14:$H$18,$BF23)))+IF(ISNUMBER($K23),ABS($K23*$G23*$AG23*N($AH23))*IF($M23="Target",N(INDEX(Settings!$G$14:$G$18,$BF23)),N(INDEX(Settings!$H$14:$H$18,$BF23))),0),6)),IF(NOT(ISNUMBER($G23)),"",ROUND(ABS($G23)*2*IF(AND($BE23>0,ISNUMBER(INDEX(Instruments!$G$6:$G$205,MAX(1,$BE23)))),INDEX(Instruments!$G$6:$G$205,MAX(1,$BE23)),N(INDEX(Settings!$F$14:$F$18,$BF23))),6)))) -> 2 | AK23: =IF($AM23=0,"",IF(ISNUMBER($O23),$O23,$AI23)) -> 150 | AL23: =IF($AM23=0,"",IF(ISNUMBER($P23),$P23,N($AJ23))) -> 2 | AM23: =IF(AND($A23<>"",$E23<>"",OR(AND(ISNUMBER($G23),ISNUMBER($H23),ISNUMBER($K23)),ISNUMBER($O23))),1,0) -> 1 | AN23: =IF($A23="","",$A23-WEEKDAY($A23,3)) -> 46293 | AO23: =IF($A23="","",WEEKDAY($A23,2)) -> 2 | AP23: =IF(OR($AM23=0,$C23=""),"",IFERROR(N(INDEX(Accounts!$E$7:$E$16,MATCH($C23,Accounts!$B$7:$B$16,0))),0)+SUMIFS($Q$6:$Q23,$C$6:$C23,$C23)) -> 50807 | AQ23: =IF(OR($AM23=0,$C23=""),"",SUMIFS($Q$6:$Q$1005,$C$6:$C$1005,$C23,$A$6:$A$1005,$A23)) -> -3 | AR23: =IF(OR($AM23=0,$C23=""),"",IFERROR(N(INDEX(Accounts!$E$7:$E$16,MATCH($C23,Accounts!$B$7:$B$16,0))),0)+SUMIFS($Q$6:$Q$1005,$C$6:$C$1005,$C23,$A$6:$A$1005,"<="&$A23)) -> 50656 | AS23: =IF(OR($AM23=0,$Q23=""),0,IF(AND($A23>=Lists!$W$6,$A23<=Lists!$W$7,OR(Dashboard!$D$6="All accounts",$C23=Dashboard!$D$6),OR(Dashboard!$D$7="All markets",$AF23=Dashboard!$D$7)),1,0)) -> 1 | AT23: =IF($AS23=1,N(AT22)+$Q23,N(AT22)) -> 916.75188 | AU23: =MAX(N(AU22),$AT23) -> 916.75188 | AV23: =$AT23-$AU23 -> 0 | AW23: =IF($AS23=1,IF($S23="Win",N(AW22)+1,IF($S23="Loss",0,N(AW22))),N(AW22)) -> 5 | AX23: =IF($AS23=1,IF($S23="Loss",N(AX22)+1,IF($S23="Win",0,N(AX22))),N(AX22)) -> 0 | AY23: =IF($AS23=1,COUNTIF($AS$6:$AS23,1),"") -> 18 | AZ23: =MIN(17,N(Lists!$W$8)) -> 17 | BA23: =IF($AS23=1,IF(COUNTIFS($A$6:$A23,$A23,$AS$6:$AS23,1)=1,1,0),0) -> 1 | BB23: =IF($BA23=1,SUMIFS($Q$6:$Q$1005,$A$6:$A$1005,$A23,$AS$6:$AS$1005,1),"") -> -58.1 | BC23: =IF(ISNUMBER($R23),1,0) -> 1 | BD23: =IF(ISNUMBER($U23),$U23*$V23,"") -> 0 | BE23: =IF($AM23=0,"",IFERROR(MATCH($AF23&"|"&UPPER(TRIM($E23)),Lists!$A$6:$A$205,0),0)) -> 1 | BF23: =IF($AM23=0,"",IFERROR(MATCH($AF23,Settings!$B$14:$B$18,0),IFERROR(MATCH(Settings!$C$6,Settings!$B$14:$B$18,0),1))) -> 1 | BG23: =IF($AM23=0,"",IF(NOT(ISNUMBER($I23)),"No stop; ","")&IF(AND(ISNUMBER($H23),ISNUMBER($I23)),IF(OR(AND($F23<>"Short",$I23>=$H23),AND($F23="Short",$I23<=$H23)),"Stop on wrong side; ",""),"")&IF($F23="","No direction; ","")&IF(AND(ISNUMBER(Settings!$C$22),ISNUMBER($V23)),IF($V23>Settings!$C$22,"Risk over max $; ",""),"")&IF(AND(ISNUMBER(Settings!$C$23),ISNUMBER($V23),ISNUMBER($AP23),IFERROR(N(INDEX(Accounts!$E$7:$E$16,MATCH($C23,Accounts!$B$7:$B$16,0))),0)>0),IF($V23>Settings!$C$23*($AP23-N($Q23)),"Risk over max %; ",""),"")&IF(AND(ISNUMBER(Settings!$C$24),ISNUMBER($N23)),IF($N23>Settings!$C$24,"Leverage over max; ",""),"")&IF(AND(ISNUMBER(Settings!$C$27),ISNUMBER($T23)),IF($T23<Settings!$C$27,"R:R below min; ",""),"")&IF(ISNUMBER(Settings!$C$25),IF(COUNTIFS($A$6:$A23,$A23,$AM$6:$AM23,1)>Settings!$C$25,"Over max trades/day; ",""),"")&IF(ISNUMBER(Settings!$C$26),IF(SUMIFS($Q$5:$Q22,$A$5:$A22,$A23)<=-Settings!$C$26,"Traded after daily max loss; ",""),"")&IF(AND($AG23="",NOT(ISNUMBER($O23))),"Symbol not in Instruments; ","")&IF(AND($AH23="",NOT(ISNUMBER($O23))),"Forex cross: type Gross P&L; ","")) | BH23: =IF(ISNUMBER($Q23),1,0) -> 1 | BI23: =IF($Y23="",0,1) -> 1 | BJ23: =IF($AB23="",0,1) -> 0 | BK23: =IF(AND($BH23=1,$W23<>"OK"),1,0) -> 0 | BL23: =IF(N($AZ23)=0,0,IFERROR(INDEX($AT$6:$AT$1005,MATCH($AZ23,$AY$6:$AY$1005,0)),0)) -> 768.75188 | BM23: =IF(ISNUMBER(SEARCH("daily max loss",$BG23)),1,0) -> 0
A24: 46294 | B24: 0.59027778 | C24: Prop Eval 50K | E24: SIL | F24: Short | G24: 1 | H24: 50.85 | I24: 51 | J24: 50.55 | K24: 51 | L24: Limit | M24: Stop loss | Q24: =IF($AM24=0,"",IF(ISNUMBER($AK24),$AK24-N($AL24),"")) -> -151 | R24: =IF(OR($Q24="",NOT(ISNUMBER($V24))),"",$AK24/$V24) -> -1 | S24: =IF($Q24="","",IF(AND(ISNUMBER($R24),ABS(N($R24))<N(Settings!$C$8)),"Scratch",IF($Q24>0,"Win",IF($Q24<0,"Loss","Scratch")))) -> Loss | T24: =IF(OR($AM24=0,NOT(ISNUMBER($H24)),NOT(ISNUMBER($I24)),NOT(ISNUMBER($J24))),"",IF($H24=$I24,"",ROUND(ABS($J24-$H24)/ABS($H24-$I24),6))) -> 2 | U24: =IF(OR($S24<>"Win",NOT(ISNUMBER($T24)),NOT(ISNUMBER($R24))),"",MAX(0,$T24-$R24)) | V24: =IF(OR($AM24=0,NOT(ISNUMBER($H24)),NOT(ISNUMBER($I24)),NOT(ISNUMBER($G24))),"",IF(OR($AG24="",$AH24=""),"",IF(ROUND(ABS($H24-$I24)*ABS($G24)*$AG24*$AH24,6)=0,"",ROUND(ABS($H24-$I24)*ABS($G24)*$AG24*$AH24,6)))) -> 150 | W24: =IF($AM24=0,"",IF($BG24="","OK",LEFT($BG24,LEN($BG24)-2))) -> OK | X24: NY Afternoon | Y24: Failed Breakout Reversal | Z24: Yes | AA24: Calm | AC24: Failed breakout above 51 | AD24: Good trade, bad outcome. | AF24: =IF($AM24=0,"",IF($D24<>"",$D24,IF(IFERROR(INDEX(Accounts!$C$7:$C$16,MATCH($C24,Accounts!$B$7:$B$16,0))&"","")<>"",INDEX(Accounts!$C$7:$C$16,MATCH($C24,Accounts!$B$7:$B$16,0)),Settings!$C$6))) -> Futures | AG24: =IF($AM24=0,"",IF(AND($BE24>0,N(INDEX(Instruments!$D$6:$D$205,MAX(1,$BE24)))>0),INDEX(Instruments!$D$6:$D$205,MAX(1,$BE24)),IF(N(INDEX(Settings!$D$14:$D$18,$BF24))>0,INDEX(Settings!$D$14:$D$18,$BF24),""))) -> 1000 | AH24: =IF($AM24=0,"",IF($AF24<>"Forex",1,IF(MID(UPPER(SUBSTITUTE(TRIM($E24),"/","")),4,3)=UPPER(TRIM(Settings!$C$7)),1,IF(LEFT(UPPER(SUBSTITUTE(TRIM($E24),"/","")),3)=UPPER(TRIM(Settings!$C$7)),IF(AND(ISNUMBER($K24),N($K24)<>0),1/$K24,""),"")))) -> 1 | AI24: =IF($AM24=0,"",IF(OR(NOT(ISNUMBER($H24)),NOT(ISNUMBER($K24)),NOT(ISNUMBER($G24)),$AG24="",$AH24=""),"",ROUND(($K24-$H24)*IF($F24="Short",-1,1)*$G24*$AG24*$AH24,6))) -> -150 | AJ24: =IF($AM24=0,"",IF(INDEX(Settings!$E$14:$E$18,$BF24)="% of notional",IF(OR($AG24="",NOT(ISNUMBER($H24)),NOT(ISNUMBER($G24))),"",ROUND(ABS($H24*$G24*$AG24*N($AH24))*IF($L24="Limit",N(INDEX(Settings!$G$14:$G$18,$BF24)),N(INDEX(Settings!$H$14:$H$18,$BF24)))+IF(ISNUMBER($K24),ABS($K24*$G24*$AG24*N($AH24))*IF($M24="Target",N(INDEX(Settings!$G$14:$G$18,$BF24)),N(INDEX(Settings!$H$14:$H$18,$BF24))),0),6)),IF(NOT(ISNUMBER($G24)),"",ROUND(ABS($G24)*2*IF(AND($BE24>0,ISNUMBER(INDEX(Instruments!$G$6:$G$205,MAX(1,$BE24)))),INDEX(Instruments!$G$6:$G$205,MAX(1,$BE24)),N(INDEX(Settings!$F$14:$F$18,$BF24))),6)))) -> 1 | AK24: =IF($AM24=0,"",IF(ISNUMBER($O24),$O24,$AI24)) -> -150 | AL24: =IF($AM24=0,"",IF(ISNUMBER($P24),$P24,N($AJ24))) -> 1 | AM24: =IF(AND($A24<>"",$E24<>"",OR(AND(ISNUMBER($G24),ISNUMBER($H24),ISNUMBER($K24)),ISNUMBER($O24))),1,0) -> 1 | AN24: =IF($A24="","",$A24-WEEKDAY($A24,3)) -> 46293 | AO24: =IF($A24="","",WEEKDAY($A24,2)) -> 2 | AP24: =IF(OR($AM24=0,$C24=""),"",IFERROR(N(INDEX(Accounts!$E$7:$E$16,MATCH($C24,Accounts!$B$7:$B$16,0))),0)+SUMIFS($Q$6:$Q24,$C$6:$C24,$C24)) -> 50656 | AQ24: =IF(OR($AM24=0,$C24=""),"",SUMIFS($Q$6:$Q$1005,$C$6:$C$1005,$C24,$A$6:$A$1005,$A24)) -> -3 | AR24: =IF(OR($AM24=0,$C24=""),"",IFERROR(N(INDEX(Accounts!$E$7:$E$16,MATCH($C24,Accounts!$B$7:$B$16,0))),0)+SUMIFS($Q$6:$Q$1005,$C$6:$C$1005,$C24,$A$6:$A$1005,"<="&$A24)) -> 50656 | AS24: =IF(OR($AM24=0,$Q24=""),0,IF(AND($A24>=Lists!$W$6,$A24<=Lists!$W$7,OR(Dashboard!$D$6="All accounts",$C24=Dashboard!$D$6),OR(Dashboard!$D$7="All markets",$AF24=Dashboard!$D$7)),1,0)) -> 1 | AT24: =IF($AS24=1,N(AT23)+$Q24,N(AT23)) -> 765.75188 | AU24: =MAX(N(AU23),$AT24) -> 916.75188 | AV24: =$AT24-$AU24 -> -151 | AW24: =IF($AS24=1,IF($S24="Win",N(AW23)+1,IF($S24="Loss",0,N(AW23))),N(AW23)) -> 0 | AX24: =IF($AS24=1,IF($S24="Loss",N(AX23)+1,IF($S24="Win",0,N(AX23))),N(AX23)) -> 1 | AY24: =IF($AS24=1,COUNTIF($AS$6:$AS24,1),"") -> 19 | AZ24: =MIN(18,N(Lists!$W$8)) -> 18 | BA24: =IF($AS24=1,IF(COUNTIFS($A$6:$A24,$A24,$AS$6:$AS24,1)=1,1,0),0) -> 0 | BB24: =IF($BA24=1,SUMIFS($Q$6:$Q$1005,$A$6:$A$1005,$A24,$AS$6:$AS$1005,1),"") | BC24: =IF(ISNUMBER($R24),1,0) -> 1 | BD24: =IF(ISNUMBER($U24),$U24*$V24,"") | BE24: =IF($AM24=0,"",IFERROR(MATCH($AF24&"|"&UPPER(TRIM($E24)),Lists!$A$6:$A$205,0),0)) -> 16 | BF24: =IF($AM24=0,"",IFERROR(MATCH($AF24,Settings!$B$14:$B$18,0),IFERROR(MATCH(Settings!$C$6,Settings!$B$14:$B$18,0),1))) -> 1 | BG24: =IF($AM24=0,"",IF(NOT(ISNUMBER($I24)),"No stop; ","")&IF(AND(ISNUMBER($H24),ISNUMBER($I24)),IF(OR(AND($F24<>"Short",$I24>=$H24),AND($F24="Short",$I24<=$H24)),"Stop on wrong side; ",""),"")&IF($F24="","No direction; ","")&IF(AND(ISNUMBER(Settings!$C$22),ISNUMBER($V24)),IF($V24>Settings!$C$22,"Risk over max $; ",""),"")&IF(AND(ISNUMBER(Settings!$C$23),ISNUMBER($V24),ISNUMBER($AP24),IFERROR(N(INDEX(Accounts!$E$7:$E$16,MATCH($C24,Accounts!$B$7:$B$16,0))),0)>0),IF($V24>Settings!$C$23*($AP24-N($Q24)),"Risk over max %; ",""),"")&IF(AND(ISNUMBER(Settings!$C$24),ISNUMBER($N24)),IF($N24>Settings!$C$24,"Leverage over max; ",""),"")&IF(AND(ISNUMBER(Settings!$C$27),ISNUMBER($T24)),IF($T24<Settings!$C$27,"R:R below min; ",""),"")&IF(ISNUMBER(Settings!$C$25),IF(COUNTIFS($A$6:$A24,$A24,$AM$6:$AM24,1)>Settings!$C$25,"Over max trades/day; ",""),"")&IF(ISNUMBER(Settings!$C$26),IF(SUMIFS($Q$5:$Q23,$A$5:$A23,$A24)<=-Settings!$C$26,"Traded after daily max loss; ",""),"")&IF(AND($AG24="",NOT(ISNUMBER($O24))),"Symbol not in Instruments; ","")&IF(AND($AH24="",NOT(ISNUMBER($O24))),"Forex cross: type Gross P&L; ","")) | BH24: =IF(ISNUMBER($Q24),1,0) -> 1 | BI24: =IF($Y24="",0,1) -> 1 | BJ24: =IF($AB24="",0,1) -> 0 | BK24: =IF(AND($BH24=1,$W24<>"OK"),1,0) -> 0 | BL24: =IF(N($AZ24)=0,0,IFERROR(INDEX($AT$6:$AT$1005,MATCH($AZ24,$AY$6:$AY$1005,0)),0)) -> 916.75188 | BM24: =IF(ISNUMBER(SEARCH("daily max loss",$BG24)),1,0) -> 0
A25: 46294 | B25: 0.86458333 | C25: Crypto Main | E25: BTCUSDT | F25: Short | G25: 0.08 | H25: 65100 | I25: 65700 | J25: 63900 | K25: 65700 | L25: Market | M25: Stop loss | N25: 15 | P25: 7.1 | Q25: =IF($AM25=0,"",IF(ISNUMBER($AK25),$AK25-N($AL25),"")) -> -55.1 | R25: =IF(OR($Q25="",NOT(ISNUMBER($V25))),"",$AK25/$V25) -> -1 | S25: =IF($Q25="","",IF(AND(ISNUMBER($R25),ABS(N($R25))<N(Settings!$C$8)),"Scratch",IF($Q25>0,"Win",IF($Q25<0,"Loss","Scratch")))) -> Loss | T25: =IF(OR($AM25=0,NOT(ISNUMBER($H25)),NOT(ISNUMBER($I25)),NOT(ISNUMBER($J25))),"",IF($H25=$I25,"",ROUND(ABS($J25-$H25)/ABS($H25-$I25),6))) -> 2 | U25: =IF(OR($S25<>"Win",NOT(ISNUMBER($T25)),NOT(ISNUMBER($R25))),"",MAX(0,$T25-$R25)) | V25: =IF(OR($AM25=0,NOT(ISNUMBER($H25)),NOT(ISNUMBER($I25)),NOT(ISNUMBER($G25))),"",IF(OR($AG25="",$AH25=""),"",IF(ROUND(ABS($H25-$I25)*ABS($G25)*$AG25*$AH25,6)=0,"",ROUND(ABS($H25-$I25)*ABS($G25)*$AG25*$AH25,6)))) -> 48 | W25: =IF($AM25=0,"",IF($BG25="","OK",LEFT($BG25,LEN($BG25)-2))) -> OK | X25: US | Y25: Range Fade | Z25: Yes | AA25: Calm | AC25: Range high fade | AD25: Valid. Lost. Fees entered from exchange (incl. funding). | AF25: =IF($AM25=0,"",IF($D25<>"",$D25,IF(IFERROR(INDEX(Accounts!$C$7:$C$16,MATCH($C25,Accounts!$B$7:$B$16,0))&"","")<>"",INDEX(Accounts!$C$7:$C$16,MATCH($C25,Accounts!$B$7:$B$16,0)),Settings!$C$6))) -> Crypto | AG25: =IF($AM25=0,"",IF(AND($BE25>0,N(INDEX(Instruments!$D$6:$D$205,MAX(1,$BE25)))>0),INDEX(Instruments!$D$6:$D$205,MAX(1,$BE25)),IF(N(INDEX(Settings!$D$14:$D$18,$BF25))>0,INDEX(Settings!$D$14:$D$18,$BF25),""))) -> 1 | AH25: =IF($AM25=0,"",IF($AF25<>"Forex",1,IF(MID(UPPER(SUBSTITUTE(TRIM($E25),"/","")),4,3)=UPPER(TRIM(Settings!$C$7)),1,IF(LEFT(UPPER(SUBSTITUTE(TRIM($E25),"/","")),3)=UPPER(TRIM(Settings!$C$7)),IF(AND(ISNUMBER($K25),N($K25)<>0),1/$K25,""),"")))) -> 1 | AI25: =IF($AM25=0,"",IF(OR(NOT(ISNUMBER($H25)),NOT(ISNUMBER($K25)),NOT(ISNUMBER($G25)),$AG25="",$AH25=""),"",ROUND(($K25-$H25)*IF($F25="Short",-1,1)*$G25*$AG25*$AH25,6))) -> -48 | AJ25: =IF($AM25=0,"",IF(INDEX(Settings!$E$14:$E$18,$BF25)="% of notional",IF(OR($AG25="",NOT(ISNUMBER($H25)),NOT(ISNUMBER($G25))),"",ROUND(ABS($H25*$G25*$AG25*N($AH25))*IF($L25="Limit",N(INDEX(Settings!$G$14:$G$18,$BF25)),N(INDEX(Settings!$H$14:$H$18,$BF25)))+IF(ISNUMBER($K25),ABS($K25*$G25*$AG25*N($AH25))*IF($M25="Target",N(INDEX(Settings!$G$14:$G$18,$BF25)),N(INDEX(Settings!$H$14:$H$18,$BF25))),0),6)),IF(NOT(ISNUMBER($G25)),"",ROUND(ABS($G25)*2*IF(AND($BE25>0,ISNUMBER(INDEX(Instruments!$G$6:$G$205,MAX(1,$BE25)))),INDEX(Instruments!$G$6:$G$205,MAX(1,$BE25)),N(INDEX(Settings!$F$14:$F$18,$BF25))),6)))) -> 6.2784 | AK25: =IF($AM25=0,"",IF(ISNUMBER($O25),$O25,$AI25)) -> -48 | AL25: =IF($AM25=0,"",IF(ISNUMBER($P25),$P25,N($AJ25))) -> 7.1 | AM25: =IF(AND($A25<>"",$E25<>"",OR(AND(ISNUMBER($G25),ISNUMBER($H25),ISNUMBER($K25)),ISNUMBER($O25))),1,0) -> 1 | AN25: =IF($A25="","",$A25-WEEKDAY($A25,3)) -> 46293 | AO25: =IF($A25="","",WEEKDAY($A25,2)) -> 2 | AP25: =IF(OR($AM25=0,$C25=""),"",IFERROR(N(INDEX(Accounts!$E$7:$E$16,MATCH($C25,Accounts!$B$7:$B$16,0))),0)+SUMIFS($Q$6:$Q25,$C$6:$C25,$C25)) -> 5054.6519 | AQ25: =IF(OR($AM25=0,$C25=""),"",SUMIFS($Q$6:$Q$1005,$C$6:$C$1005,$C25,$A$6:$A$1005,$A25)) -> -55.1 | AR25: =IF(OR($AM25=0,$C25=""),"",IFERROR(N(INDEX(Accounts!$E$7:$E$16,MATCH($C25,Accounts!$B$7:$B$16,0))),0)+SUMIFS($Q$6:$Q$1005,$C$6:$C$1005,$C25,$A$6:$A$1005,"<="&$A25)) -> 5054.6519 | AS25: =IF(OR($AM25=0,$Q25=""),0,IF(AND($A25>=Lists!$W$6,$A25<=Lists!$W$7,OR(Dashboard!$D$6="All accounts",$C25=Dashboard!$D$6),OR(Dashboard!$D$7="All markets",$AF25=Dashboard!$D$7)),1,0)) -> 1 | AT25: =IF($AS25=1,N(AT24)+$Q25,N(AT24)) -> 710.65188 | AU25: =MAX(N(AU24),$AT25) -> 916.75188 | AV25: =$AT25-$AU25 -> -206.1 | AW25: =IF($AS25=1,IF($S25="Win",N(AW24)+1,IF($S25="Loss",0,N(AW24))),N(AW24)) -> 0 | AX25: =IF($AS25=1,IF($S25="Loss",N(AX24)+1,IF($S25="Win",0,N(AX24))),N(AX24)) -> 2 | AY25: =IF($AS25=1,COUNTIF($AS$6:$AS25,1),"") -> 20 | AZ25: =MIN(19,N(Lists!$W$8)) -> 19 | BA25: =IF($AS25=1,IF(COUNTIFS($A$6:$A25,$A25,$AS$6:$AS25,1)=1,1,0),0) -> 0 | BB25: =IF($BA25=1,SUMIFS($Q$6:$Q$1005,$A$6:$A$1005,$A25,$AS$6:$AS$1005,1),"") | BC25: =IF(ISNUMBER($R25),1,0) -> 1 | BD25: =IF(ISNUMBER($U25),$U25*$V25,"") | BE25: =IF($AM25=0,"",IFERROR(MATCH($AF25&"|"&UPPER(TRIM($E25)),Lists!$A$6:$A$205,0),0)) -> 46 | BF25: =IF($AM25=0,"",IFERROR(MATCH($AF25,Settings!$B$14:$B$18,0),IFERROR(MATCH(Settings!$C$6,Settings!$B$14:$B$18,0),1))) -> 5 | BG25: =IF($AM25=0,"",IF(NOT(ISNUMBER($I25)),"No stop; ","")&IF(AND(ISNUMBER($H25),ISNUMBER($I25)),IF(OR(AND($F25<>"Short",$I25>=$H25),AND($F25="Short",$I25<=$H25)),"Stop on wrong side; ",""),"")&IF($F25="","No direction; ","")&IF(AND(ISNUMBER(Settings!$C$22),ISNUMBER($V25)),IF($V25>Settings!$C$22,"Risk over max $; ",""),"")&IF(AND(ISNUMBER(Settings!$C$23),ISNUMBER($V25),ISNUMBER($AP25),IFERROR(N(INDEX(Accounts!$E$7:$E$16,MATCH($C25,Accounts!$B$7:$B$16,0))),0)>0),IF($V25>Settings!$C$23*($AP25-N($Q25)),"Risk over max %; ",""),"")&IF(AND(ISNUMBER(Settings!$C$24),ISNUMBER($N25)),IF($N25>Settings!$C$24,"Leverage over max; ",""),"")&IF(AND(ISNUMBER(Settings!$C$27),ISNUMBER($T25)),IF($T25<Settings!$C$27,"R:R below min; ",""),"")&IF(ISNUMBER(Settings!$C$25),IF(COUNTIFS($A$6:$A25,$A25,$AM$6:$AM25,1)>Settings!$C$25,"Over max trades/day; ",""),"")&IF(ISNUMBER(Settings!$C$26),IF(SUMIFS($Q$5:$Q24,$A$5:$A24,$A25)<=-Settings!$C$26,"Traded after daily max loss; ",""),"")&IF(AND($AG25="",NOT(ISNUMBER($O25))),"Symbol not in Instruments; ","")&IF(AND($AH25="",NOT(ISNUMBER($O25))),"Forex cross: type Gross P&L; ","")) | BH25: =IF(ISNUMBER($Q25),1,0) -> 1 | BI25: =IF($Y25="",0,1) -> 1 | BJ25: =IF($AB25="",0,1) -> 0 | BK25: =IF(AND($BH25=1,$W25<>"OK"),1,0) -> 0 | BL25: =IF(N($AZ25)=0,0,IFERROR(INDEX($AT$6:$AT$1005,MATCH($AZ25,$AY$6:$AY$1005,0)),0)) -> 765.75188 | BM25: =IF(ISNUMBER(SEARCH("daily max loss",$BG25)),1,0) -> 0
A26: 46295 | B26: 0.39791667 | C26: Prop Eval 50K | E26: MNQ | F26: Long | G26: 1 | H26: 29610 | I26: 29580 | J26: 29670 | K26: 29612 | L26: Market | M26: Breakeven | Q26: =IF($AM26=0,"",IF(ISNUMBER($AK26),$AK26-N($AL26),"")) -> 3 | R26: =IF(OR($Q26="",NOT(ISNUMBER($V26))),"",$AK26/$V26) -> 0.066666667 | S26: =IF($Q26="","",IF(AND(ISNUMBER($R26),ABS(N($R26))<N(Settings!$C$8)),"Scratch",IF($Q26>0,"Win",IF($Q26<0,"Loss","Scratch")))) -> Scratch | T26: =IF(OR($AM26=0,NOT(ISNUMBER($H26)),NOT(ISNUMBER($I26)),NOT(ISNUMBER($J26))),"",IF($H26=$I26,"",ROUND(ABS($J26-$H26)/ABS($H26-$I26),6))) -> 2 | U26: =IF(OR($S26<>"Win",NOT(ISNUMBER($T26)),NOT(ISNUMBER($R26))),"",MAX(0,$T26-$R26)) | V26: =IF(OR($AM26=0,NOT(ISNUMBER($H26)),NOT(ISNUMBER($I26)),NOT(ISNUMBER($G26))),"",IF(OR($AG26="",$AH26=""),"",IF(ROUND(ABS($H26-$I26)*ABS($G26)*$AG26*$AH26,6)=0,"",ROUND(ABS($H26-$I26)*ABS($G26)*$AG26*$AH26,6)))) -> 60 | W26: =IF($AM26=0,"",IF($BG26="","OK",LEFT($BG26,LEN($BG26)-2))) -> OK | X26: NY Open | Y26: Breakout & Retest | Z26: Yes | AA26: Hesitant | AC26: Breakout looked weak | AD26: Moved to breakeven per plan. Scratch. | AF26: =IF($AM26=0,"",IF($D26<>"",$D26,IF(IFERROR(INDEX(Accounts!$C$7:$C$16,MATCH($C26,Accounts!$B$7:$B$16,0))&"","")<>"",INDEX(Accounts!$C$7:$C$16,MATCH($C26,Accounts!$B$7:$B$16,0)),Settings!$C$6))) -> Futures | AG26: =IF($AM26=0,"",IF(AND($BE26>0,N(INDEX(Instruments!$D$6:$D$205,MAX(1,$BE26)))>0),INDEX(Instruments!$D$6:$D$205,MAX(1,$BE26)),IF(N(INDEX(Settings!$D$14:$D$18,$BF26))>0,INDEX(Settings!$D$14:$D$18,$BF26),""))) -> 2 | AH26: =IF($AM26=0,"",IF($AF26<>"Forex",1,IF(MID(UPPER(SUBSTITUTE(TRIM($E26),"/","")),4,3)=UPPER(TRIM(Settings!$C$7)),1,IF(LEFT(UPPER(SUBSTITUTE(TRIM($E26),"/","")),3)=UPPER(TRIM(Settings!$C$7)),IF(AND(ISNUMBER($K26),N($K26)<>0),1/$K26,""),"")))) -> 1 | AI26: =IF($AM26=0,"",IF(OR(NOT(ISNUMBER($H26)),NOT(ISNUMBER($K26)),NOT(ISNUMBER($G26)),$AG26="",$AH26=""),"",ROUND(($K26-$H26)*IF($F26="Short",-1,1)*$G26*$AG26*$AH26,6))) -> 4 | AJ26: =IF($AM26=0,"",IF(INDEX(Settings!$E$14:$E$18,$BF26)="% of notional",IF(OR($AG26="",NOT(ISNUMBER($H26)),NOT(ISNUMBER($G26))),"",ROUND(ABS($H26*$G26*$AG26*N($AH26))*IF($L26="Limit",N(INDEX(Settings!$G$14:$G$18,$BF26)),N(INDEX(Settings!$H$14:$H$18,$BF26)))+IF(ISNUMBER($K26),ABS($K26*$G26*$AG26*N($AH26))*IF($M26="Target",N(INDEX(Settings!$G$14:$G$18,$BF26)),N(INDEX(Settings!$H$14:$H$18,$BF26))),0),6)),IF(NOT(ISNUMBER($G26)),"",ROUND(ABS($G26)*2*IF(AND($BE26>0,ISNUMBER(INDEX(Instruments!$G$6:$G$205,MAX(1,$BE26)))),INDEX(Instruments!$G$6:$G$205,MAX(1,$BE26)),N(INDEX(Settings!$F$14:$F$18,$BF26))),6)))) -> 1 | AK26: =IF($AM26=0,"",IF(ISNUMBER($O26),$O26,$AI26)) -> 4 | AL26: =IF($AM26=0,"",IF(ISNUMBER($P26),$P26,N($AJ26))) -> 1 | AM26: =IF(AND($A26<>"",$E26<>"",OR(AND(ISNUMBER($G26),ISNUMBER($H26),ISNUMBER($K26)),ISNUMBER($O26))),1,0) -> 1 | AN26: =IF($A26="","",$A26-WEEKDAY($A26,3)) -> 46293 | AO26: =IF($A26="","",WEEKDAY($A26,2)) -> 3 | AP26: =IF(OR($AM26=0,$C26=""),"",IFERROR(N(INDEX(Accounts!$E$7:$E$16,MATCH($C26,Accounts!$B$7:$B$16,0))),0)+SUMIFS($Q$6:$Q26,$C$6:$C26,$C26)) -> 50659 | AQ26: =IF(OR($AM26=0,$C26=""),"",SUMIFS($Q$6:$Q$1005,$C$6:$C$1005,$C26,$A$6:$A$1005,$A26)) -> 122 | AR26: =IF(OR($AM26=0,$C26=""),"",IFERROR(N(INDEX(Accounts!$E$7:$E$16,MATCH($C26,Accounts!$B$7:$B$16,0))),0)+SUMIFS($Q$6:$Q$1005,$C$6:$C$1005,$C26,$A$6:$A$1005,"<="&$A26)) -> 50778 | AS26: =IF(OR($AM26=0,$Q26=""),0,IF(AND($A26>=Lists!$W$6,$A26<=Lists!$W$7,OR(Dashboard!$D$6="All accounts",$C26=Dashboard!$D$6),OR(Dashboard!$D$7="All markets",$AF26=Dashboard!$D$7)),1,0)) -> 1 | AT26: =IF($AS26=1,N(AT25)+$Q26,N(AT25)) -> 713.65188 | AU26: =MAX(N(AU25),$AT26) -> 916.75188 | AV26: =$AT26-$AU26 -> -203.1 | AW26: =IF($AS26=1,IF($S26="Win",N(AW25)+1,IF($S26="Loss",0,N(AW25))),N(AW25)) -> 0 | AX26: =IF($AS26=1,IF($S26="Loss",N(AX25)+1,IF($S26="Win",0,N(AX25))),N(AX25)) -> 2 | AY26: =IF($AS26=1,COUNTIF($AS$6:$AS26,1),"") -> 21 | AZ26: =MIN(20,N(Lists!$W$8)) -> 20 | BA26: =IF($AS26=1,IF(COUNTIFS($A$6:$A26,$A26,$AS$6:$AS26,1)=1,1,0),0) -> 1 | BB26: =IF($BA26=1,SUMIFS($Q$6:$Q$1005,$A$6:$A$1005,$A26,$AS$6:$AS$1005,1),"") -> 122 | BC26: =IF(ISNUMBER($R26),1,0) -> 1 | BD26: =IF(ISNUMBER($U26),$U26*$V26,"") | BE26: =IF($AM26=0,"",IFERROR(MATCH($AF26&"|"&UPPER(TRIM($E26)),Lists!$A$6:$A$205,0),0)) -> 3 | BF26: =IF($AM26=0,"",IFERROR(MATCH($AF26,Settings!$B$14:$B$18,0),IFERROR(MATCH(Settings!$C$6,Settings!$B$14:$B$18,0),1))) -> 1 | BG26: =IF($AM26=0,"",IF(NOT(ISNUMBER($I26)),"No stop; ","")&IF(AND(ISNUMBER($H26),ISNUMBER($I26)),IF(OR(AND($F26<>"Short",$I26>=$H26),AND($F26="Short",$I26<=$H26)),"Stop on wrong side; ",""),"")&IF($F26="","No direction; ","")&IF(AND(ISNUMBER(Settings!$C$22),ISNUMBER($V26)),IF($V26>Settings!$C$22,"Risk over max $; ",""),"")&IF(AND(ISNUMBER(Settings!$C$23),ISNUMBER($V26),ISNUMBER($AP26),IFERROR(N(INDEX(Accounts!$E$7:$E$16,MATCH($C26,Accounts!$B$7:$B$16,0))),0)>0),IF($V26>Settings!$C$23*($AP26-N($Q26)),"Risk over max %; ",""),"")&IF(AND(ISNUMBER(Settings!$C$24),ISNUMBER($N26)),IF($N26>Settings!$C$24,"Leverage over max; ",""),"")&IF(AND(ISNUMBER(Settings!$C$27),ISNUMBER($T26)),IF($T26<Settings!$C$27,"R:R below min; ",""),"")&IF(ISNUMBER(Settings!$C$25),IF(COUNTIFS($A$6:$A26,$A26,$AM$6:$AM26,1)>Settings!$C$25,"Over max trades/day; ",""),"")&IF(ISNUMBER(Settings!$C$26),IF(SUMIFS($Q$5:$Q25,$A$5:$A25,$A26)<=-Settings!$C$26,"Traded after daily max loss; ",""),"")&IF(AND($AG26="",NOT(ISNUMBER($O26))),"Symbol not in Instruments; ","")&IF(AND($AH26="",NOT(ISNUMBER($O26))),"Forex cross: type Gross P&L; ","")) | BH26: =IF(ISNUMBER($Q26),1,0) -> 1 | BI26: =IF($Y26="",0,1) -> 1 | BJ26: =IF($AB26="",0,1) -> 0 | BK26: =IF(AND($BH26=1,$W26<>"OK"),1,0) -> 0 | BL26: =IF(N($AZ26)=0,0,IFERROR(INDEX($AT$6:$AT$1005,MATCH($AZ26,$AY$6:$AY$1005,0)),0)) -> 710.65188 | BM26: =IF(ISNUMBER(SEARCH("daily max loss",$BG26)),1,0) -> 0
A27: 46295 | B27: 0.43055556 | C27: Prop Eval 50K | E27: MGC | F27: Long | G27: 1 | H27: 4045 | I27: 4039 | J27: 4057 | K27: 4057 | L27: Limit | M27: Target | Q27: =IF($AM27=0,"",IF(ISNUMBER($AK27),$AK27-N($AL27),"")) -> 119 | R27: =IF(OR($Q27="",NOT(ISNUMBER($V27))),"",$AK27/$V27) -> 2 | S27: =IF($Q27="","",IF(AND(ISNUMBER($R27),ABS(N($R27))<N(Settings!$C$8)),"Scratch",IF($Q27>0,"Win",IF($Q27<0,"Loss","Scratch")))) -> Win | T27: =IF(OR($AM27=0,NOT(ISNUMBER($H27)),NOT(ISNUMBER($I27)),NOT(ISNUMBER($J27))),"",IF($H27=$I27,"",ROUND(ABS($J27-$H27)/ABS($H27-$I27),6))) -> 2 | U27: =IF(OR($S27<>"Win",NOT(ISNUMBER($T27)),NOT(ISNUMBER($R27))),"",MAX(0,$T27-$R27)) -> 0 | V27: =IF(OR($AM27=0,NOT(ISNUMBER($H27)),NOT(ISNUMBER($I27)),NOT(ISNUMBER($G27))),"",IF(OR($AG27="",$AH27=""),"",IF(ROUND(ABS($H27-$I27)*ABS($G27)*$AG27*$AH27,6)=0,"",ROUND(ABS($H27-$I27)*ABS($G27)*$AG27*$AH27,6)))) -> 60 | W27: =IF($AM27=0,"",IF($BG27="","OK",LEFT($BG27,LEN($BG27)-2))) -> OK | X27: NY Open | Y27: Trend Pullback | Z27: Yes | AA27: Calm | AC27: Gold pullback held the 20 EMA | AD27: Clean. | AF27: =IF($AM27=0,"",IF($D27<>"",$D27,IF(IFERROR(INDEX(Accounts!$C$7:$C$16,MATCH($C27,Accounts!$B$7:$B$16,0))&"","")<>"",INDEX(Accounts!$C$7:$C$16,MATCH($C27,Accounts!$B$7:$B$16,0)),Settings!$C$6))) -> Futures | AG27: =IF($AM27=0,"",IF(AND($BE27>0,N(INDEX(Instruments!$D$6:$D$205,MAX(1,$BE27)))>0),INDEX(Instruments!$D$6:$D$205,MAX(1,$BE27)),IF(N(INDEX(Settings!$D$14:$D$18,$BF27))>0,INDEX(Settings!$D$14:$D$18,$BF27),""))) -> 10 | AH27: =IF($AM27=0,"",IF($AF27<>"Forex",1,IF(MID(UPPER(SUBSTITUTE(TRIM($E27),"/","")),4,3)=UPPER(TRIM(Settings!$C$7)),1,IF(LEFT(UPPER(SUBSTITUTE(TRIM($E27),"/","")),3)=UPPER(TRIM(Settings!$C$7)),IF(AND(ISNUMBER($K27),N($K27)<>0),1/$K27,""),"")))) -> 1 | AI27: =IF($AM27=0,"",IF(OR(NOT(ISNUMBER($H27)),NOT(ISNUMBER($K27)),NOT(ISNUMBER($G27)),$AG27="",$AH27=""),"",ROUND(($K27-$H27)*IF($F27="Short",-1,1)*$G27*$AG27*$AH27,6))) -> 120 | AJ27: =IF($AM27=0,"",IF(INDEX(Settings!$E$14:$E$18,$BF27)="% of notional",IF(OR($AG27="",NOT(ISNUMBER($H27)),NOT(ISNUMBER($G27))),"",ROUND(ABS($H27*$G27*$AG27*N($AH27))*IF($L27="Limit",N(INDEX(Settings!$G$14:$G$18,$BF27)),N(INDEX(Settings!$H$14:$H$18,$BF27)))+IF(ISNUMBER($K27),ABS($K27*$G27*$AG27*N($AH27))*IF($M27="Target",N(INDEX(Settings!$G$14:$G$18,$BF27)),N(INDEX(Settings!$H$14:$H$18,$BF27))),0),6)),IF(NOT(ISNUMBER($G27)),"",ROUND(ABS($G27)*2*IF(AND($BE27>0,ISNUMBER(INDEX(Instruments!$G$6:$G$205,MAX(1,$BE27)))),INDEX(Instruments!$G$6:$G$205,MAX(1,$BE27)),N(INDEX(Settings!$F$14:$F$18,$BF27))),6)))) -> 1 | AK27: =IF($AM27=0,"",IF(ISNUMBER($O27),$O27,$AI27)) -> 120 | AL27: =IF($AM27=0,"",IF(ISNUMBER($P27),$P27,N($AJ27))) -> 1 | AM27: =IF(AND($A27<>"",$E27<>"",OR(AND(ISNUMBER($G27),ISNUMBER($H27),ISNUMBER($K27)),ISNUMBER($O27))),1,0) -> 1 | AN27: =IF($A27="","",$A27-WEEKDAY($A27,3)) -> 46293 | AO27: =IF($A27="","",WEEKDAY($A27,2)) -> 3 | AP27: =IF(OR($AM27=0,$C27=""),"",IFERROR(N(INDEX(Accounts!$E$7:$E$16,MATCH($C27,Accounts!$B$7:$B$16,0))),0)+SUMIFS($Q$6:$Q27,$C$6:$C27,$C27)) -> 50778 | AQ27: =IF(OR($AM27=0,$C27=""),"",SUMIFS($Q$6:$Q$1005,$C$6:$C$1005,$C27,$A$6:$A$1005,$A27)) -> 122 | AR27: =IF(OR($AM27=0,$C27=""),"",IFERROR(N(INDEX(Accounts!$E$7:$E$16,MATCH($C27,Accounts!$B$7:$B$16,0))),0)+SUMIFS($Q$6:$Q$1005,$C$6:$C$1005,$C27,$A$6:$A$1005,"<="&$A27)) -> 50778 | AS27: =IF(OR($AM27=0,$Q27=""),0,IF(AND($A27>=Lists!$W$6,$A27<=Lists!$W$7,OR(Dashboard!$D$6="All accounts",$C27=Dashboard!$D$6),OR(Dashboard!$D$7="All markets",$AF27=Dashboard!$D$7)),1,0)) -> 1 | AT27: =IF($AS27=1,N(AT26)+$Q27,N(AT26)) -> 832.65188 | AU27: =MAX(N(AU26),$AT27) -> 916.75188 | AV27: =$AT27-$AU27 -> -84.1 | AW27: =IF($AS27=1,IF($S27="Win",N(AW26)+1,IF($S27="Loss",0,N(AW26))),N(AW26)) -> 1 | AX27: =IF($AS27=1,IF($S27="Loss",N(AX26)+1,IF($S27="Win",0,N(AX26))),N(AX26)) -> 0 | AY27: =IF($AS27=1,COUNTIF($AS$6:$AS27,1),"") -> 22 | AZ27: =MIN(21,N(Lists!$W$8)) -> 21 | BA27: =IF($AS27=1,IF(COUNTIFS($A$6:$A27,$A27,$AS$6:$AS27,1)=1,1,0),0) -> 0 | BB27: =IF($BA27=1,SUMIFS($Q$6:$Q$1005,$A$6:$A$1005,$A27,$AS$6:$AS$1005,1),"") | BC27: =IF(ISNUMBER($R27),1,0) -> 1 | BD27: =IF(ISNUMBER($U27),$U27*$V27,"") -> 0 | BE27: =IF($AM27=0,"",IFERROR(MATCH($AF27&"|"&UPPER(TRIM($E27)),Lists!$A$6:$A$205,0),0)) -> 14 | BF27: =IF($AM27=0,"",IFERROR(MATCH($AF27,Settings!$B$14:$B$18,0),IFERROR(MATCH(Settings!$C$6,Settings!$B$14:$B$18,0),1))) -> 1 | BG27: =IF($AM27=0,"",IF(NOT(ISNUMBER($I27)),"No stop; ","")&IF(AND(ISNUMBER($H27),ISNUMBER($I27)),IF(OR(AND($F27<>"Short",$I27>=$H27),AND($F27="Short",$I27<=$H27)),"Stop on wrong side; ",""),"")&IF($F27="","No direction; ","")&IF(AND(ISNUMBER(Settings!$C$22),ISNUMBER($V27)),IF($V27>Settings!$C$22,"Risk over max $; ",""),"")&IF(AND(ISNUMBER(Settings!$C$23),ISNUMBER($V27),ISNUMBER($AP27),IFERROR(N(INDEX(Accounts!$E$7:$E$16,MATCH($C27,Accounts!$B$7:$B$16,0))),0)>0),IF($V27>Settings!$C$23*($AP27-N($Q27)),"Risk over max %; ",""),"")&IF(AND(ISNUMBER(Settings!$C$24),ISNUMBER($N27)),IF($N27>Settings!$C$24,"Leverage over max; ",""),"")&IF(AND(ISNUMBER(Settings!$C$27),ISNUMBER($T27)),IF($T27<Settings!$C$27,"R:R below min; ",""),"")&IF(ISNUMBER(Settings!$C$25),IF(COUNTIFS($A$6:$A27,$A27,$AM$6:$AM27,1)>Settings!$C$25,"Over max trades/day; ",""),"")&IF(ISNUMBER(Settings!$C$26),IF(SUMIFS($Q$5:$Q26,$A$5:$A26,$A27)<=-Settings!$C$26,"Traded after daily max loss; ",""),"")&IF(AND($AG27="",NOT(ISNUMBER($O27))),"Symbol not in Instruments; ","")&IF(AND($AH27="",NOT(ISNUMBER($O27))),"Forex cross: type Gross P&L; ","")) | BH27: =IF(ISNUMBER($Q27),1,0) -> 1 | BI27: =IF($Y27="",0,1) -> 1 | BJ27: =IF($AB27="",0,1) -> 0 | BK27: =IF(AND($BH27=1,$W27<>"OK"),1,0) -> 0 | BL27: =IF(N($AZ27)=0,0,IFERROR(INDEX($AT$6:$AT$1005,MATCH($AZ27,$AY$6:$AY$1005,0)),0)) -> 713.65188 | BM27: =IF(ISNUMBER(SEARCH("daily max loss",$BG27)),1,0) -> 0
A28: 46296 | B28: 0.40972222 | C28: Prop Eval 50K | E28: MES | F28: Long | G28: 6 | H28: 7670 | I28: 7660 | J28: 7690 | K28: 7660 | L28: Market | M28: Stop loss | Q28: =IF($AM28=0,"",IF(ISNUMBER($AK28),$AK28-N($AL28),"")) -> -306 | R28: =IF(OR($Q28="",NOT(ISNUMBER($V28))),"",$AK28/$V28) -> -1 | S28: =IF($Q28="","",IF(AND(ISNUMBER($R28),ABS(N($R28))<N(Settings!$C$8)),"Scratch",IF($Q28>0,"Win",IF($Q28<0,"Loss","Scratch")))) -> Loss | T28: =IF(OR($AM28=0,NOT(ISNUMBER($H28)),NOT(ISNUMBER($I28)),NOT(ISNUMBER($J28))),"",IF($H28=$I28,"",ROUND(ABS($J28-$H28)/ABS($H28-$I28),6))) -> 2 | U28: =IF(OR($S28<>"Win",NOT(ISNUMBER($T28)),NOT(ISNUMBER($R28))),"",MAX(0,$T28-$R28)) | V28: =IF(OR($AM28=0,NOT(ISNUMBER($H28)),NOT(ISNUMBER($I28)),NOT(ISNUMBER($G28))),"",IF(OR($AG28="",$AH28=""),"",IF(ROUND(ABS($H28-$I28)*ABS($G28)*$AG28*$AH28,6)=0,"",ROUND(ABS($H28-$I28)*ABS($G28)*$AG28*$AH28,6)))) -> 300 | W28: =IF($AM28=0,"",IF($BG28="","OK",LEFT($BG28,LEN($BG28)-2))) -> Risk over max $ | X28: NY Open | Y28: Breakout & Retest | Z28: No | AA28: FOMO | AB28: Oversized | AC28: Breakout, felt sure about it | AD28: Sized up after two green days. Broke my max risk. | AF28: =IF($AM28=0,"",IF($D28<>"",$D28,IF(IFERROR(INDEX(Accounts!$C$7:$C$16,MATCH($C28,Accounts!$B$7:$B$16,0))&"","")<>"",INDEX(Accounts!$C$7:$C$16,MATCH($C28,Accounts!$B$7:$B$16,0)),Settings!$C$6))) -> Futures | AG28: =IF($AM28=0,"",IF(AND($BE28>0,N(INDEX(Instruments!$D$6:$D$205,MAX(1,$BE28)))>0),INDEX(Instruments!$D$6:$D$205,MAX(1,$BE28)),IF(N(INDEX(Settings!$D$14:$D$18,$BF28))>0,INDEX(Settings!$D$14:$D$18,$BF28),""))) -> 5 | AH28: =IF($AM28=0,"",IF($AF28<>"Forex",1,IF(MID(UPPER(SUBSTITUTE(TRIM($E28),"/","")),4,3)=UPPER(TRIM(Settings!$C$7)),1,IF(LEFT(UPPER(SUBSTITUTE(TRIM($E28),"/","")),3)=UPPER(TRIM(Settings!$C$7)),IF(AND(ISNUMBER($K28),N($K28)<>0),1/$K28,""),"")))) -> 1 | AI28: =IF($AM28=0,"",IF(OR(NOT(ISNUMBER($H28)),NOT(ISNUMBER($K28)),NOT(ISNUMBER($G28)),$AG28="",$AH28=""),"",ROUND(($K28-$H28)*IF($F28="Short",-1,1)*$G28*$AG28*$AH28,6))) -> -300 | AJ28: =IF($AM28=0,"",IF(INDEX(Settings!$E$14:$E$18,$BF28)="% of notional",IF(OR($AG28="",NOT(ISNUMBER($H28)),NOT(ISNUMBER($G28))),"",ROUND(ABS($H28*$G28*$AG28*N($AH28))*IF($L28="Limit",N(INDEX(Settings!$G$14:$G$18,$BF28)),N(INDEX(Settings!$H$14:$H$18,$BF28)))+IF(ISNUMBER($K28),ABS($K28*$G28*$AG28*N($AH28))*IF($M28="Target",N(INDEX(Settings!$G$14:$G$18,$BF28)),N(INDEX(Settings!$H$14:$H$18,$BF28))),0),6)),IF(NOT(ISNUMBER($G28)),"",ROUND(ABS($G28)*2*IF(AND($BE28>0,ISNUMBER(INDEX(Instruments!$G$6:$G$205,MAX(1,$BE28)))),INDEX(Instruments!$G$6:$G$205,MAX(1,$BE28)),N(INDEX(Settings!$F$14:$F$18,$BF28))),6)))) -> 6 | AK28: =IF($AM28=0,"",IF(ISNUMBER($O28),$O28,$AI28)) -> -300 | AL28: =IF($AM28=0,"",IF(ISNUMBER($P28),$P28,N($AJ28))) -> 6 | AM28: =IF(AND($A28<>"",$E28<>"",OR(AND(ISNUMBER($G28),ISNUMBER($H28),ISNUMBER($K28)),ISNUMBER($O28))),1,0) -> 1 | AN28: =IF($A28="","",$A28-WEEKDAY($A28,3)) -> 46293 | AO28: =IF($A28="","",WEEKDAY($A28,2)) -> 4 | AP28: =IF(OR($AM28=0,$C28=""),"",IFERROR(N(INDEX(Accounts!$E$7:$E$16,MATCH($C28,Accounts!$B$7:$B$16,0))),0)+SUMIFS($Q$6:$Q28,$C$6:$C28,$C28)) -> 50472 | AQ28: =IF(OR($AM28=0,$C28=""),"",SUMIFS($Q$6:$Q$1005,$C$6:$C$1005,$C28,$A$6:$A$1005,$A28)) -> -306 | AR28: =IF(OR($AM28=0,$C28=""),"",IFERROR(N(INDEX(Accounts!$E$7:$E$16,MATCH($C28,Accounts!$B$7:$B$16,0))),0)+SUMIFS($Q$6:$Q$1005,$C$6:$C$1005,$C28,$A$6:$A$1005,"<="&$A28)) -> 50472 | AS28: =IF(OR($AM28=0,$Q28=""),0,IF(AND($A28>=Lists!$W$6,$A28<=Lists!$W$7,OR(Dashboard!$D$6="All accounts",$C28=Dashboard!$D$6),OR(Dashboard!$D$7="All markets",$AF28=Dashboard!$D$7)),1,0)) -> 1 | AT28: =IF($AS28=1,N(AT27)+$Q28,N(AT27)) -> 526.65188 | AU28: =MAX(N(AU27),$AT28) -> 916.75188 | AV28: =$AT28-$AU28 -> -390.1 | AW28: =IF($AS28=1,IF($S28="Win",N(AW27)+1,IF($S28="Loss",0,N(AW27))),N(AW27)) -> 0 | AX28: =IF($AS28=1,IF($S28="Loss",N(AX27)+1,IF($S28="Win",0,N(AX27))),N(AX27)) -> 1 | AY28: =IF($AS28=1,COUNTIF($AS$6:$AS28,1),"") -> 23 | AZ28: =MIN(22,N(Lists!$W$8)) -> 22 | BA28: =IF($AS28=1,IF(COUNTIFS($A$6:$A28,$A28,$AS$6:$AS28,1)=1,1,0),0) -> 1 | BB28: =IF($BA28=1,SUMIFS($Q$6:$Q$1005,$A$6:$A$1005,$A28,$AS$6:$AS$1005,1),"") -> -207.856 | BC28: =IF(ISNUMBER($R28),1,0) -> 1 | BD28: =IF(ISNUMBER($U28),$U28*$V28,"") | BE28: =IF($AM28=0,"",IFERROR(MATCH($AF28&"|"&UPPER(TRIM($E28)),Lists!$A$6:$A$205,0),0)) -> 1 | BF28: =IF($AM28=0,"",IFERROR(MATCH($AF28,Settings!$B$14:$B$18,0),IFERROR(MATCH(Settings!$C$6,Settings!$B$14:$B$18,0),1))) -> 1 | BG28: =IF($AM28=0,"",IF(NOT(ISNUMBER($I28)),"No stop; ","")&IF(AND(ISNUMBER($H28),ISNUMBER($I28)),IF(OR(AND($F28<>"Short",$I28>=$H28),AND($F28="Short",$I28<=$H28)),"Stop on wrong side; ",""),"")&IF($F28="","No direction; ","")&IF(AND(ISNUMBER(Settings!$C$22),ISNUMBER($V28)),IF($V28>Settings!$C$22,"Risk over max $; ",""),"")&IF(AND(ISNUMBER(Settings!$C$23),ISNUMBER($V28),ISNUMBER($AP28),IFERROR(N(INDEX(Accounts!$E$7:$E$16,MATCH($C28,Accounts!$B$7:$B$16,0))),0)>0),IF($V28>Settings!$C$23*($AP28-N($Q28)),"Risk over max %; ",""),"")&IF(AND(ISNUMBER(Settings!$C$24),ISNUMBER($N28)),IF($N28>Settings!$C$24,"Leverage over max; ",""),"")&IF(AND(ISNUMBER(Settings!$C$27),ISNUMBER($T28)),IF($T28<Settings!$C$27,"R:R below min; ",""),"")&IF(ISNUMBER(Settings!$C$25),IF(COUNTIFS($A$6:$A28,$A28,$AM$6:$AM28,1)>Settings!$C$25,"Over max trades/day; ",""),"")&IF(ISNUMBER(Settings!$C$26),IF(SUMIFS($Q$5:$Q27,$A$5:$A27,$A28)<=-Settings!$C$26,"Traded after daily max loss; ",""),"")&IF(AND($AG28="",NOT(ISNUMBER($O28))),"Symbol not in Instruments; ","")&IF(AND($AH28="",NOT(ISNUMBER($O28))),"Forex cross: type Gross P&L; ","")) -> Risk over max $; | BH28: =IF(ISNUMBER($Q28),1,0) -> 1 | BI28: =IF($Y28="",0,1) -> 1 | BJ28: =IF($AB28="",0,1) -> 1 | BK28: =IF(AND($BH28=1,$W28<>"OK"),1,0) -> 1 | BL28: =IF(N($AZ28)=0,0,IFERROR(INDEX($AT$6:$AT$1005,MATCH($AZ28,$AY$6:$AY$1005,0)),0)) -> 832.65188 | BM28: =IF(ISNUMBER(SEARCH("daily max loss",$BG28)),1,0) -> 0
A29: 46296 | B29: 0.92361111 | C29: Crypto Main | E29: ETHUSDT | F29: Long | G29: 2 | H29: 2295 | I29: 2270 | J29: 2345 | K29: 2345 | L29: Limit | M29: Target | N29: 10 | Q29: =IF($AM29=0,"",IF(ISNUMBER($AK29),$AK29-N($AL29),"")) -> 98.144 | R29: =IF(OR($Q29="",NOT(ISNUMBER($V29))),"",$AK29/$V29) -> 2 | S29: =IF($Q29="","",IF(AND(ISNUMBER($R29),ABS(N($R29))<N(Settings!$C$8)),"Scratch",IF($Q29>0,"Win",IF($Q29<0,"Loss","Scratch")))) -> Win | T29: =IF(OR($AM29=0,NOT(ISNUMBER($H29)),NOT(ISNUMBER($I29)),NOT(ISNUMBER($J29))),"",IF($H29=$I29,"",ROUND(ABS($J29-$H29)/ABS($H29-$I29),6))) -> 2 | U29: =IF(OR($S29<>"Win",NOT(ISNUMBER($T29)),NOT(ISNUMBER($R29))),"",MAX(0,$T29-$R29)) -> 0 | V29: =IF(OR($AM29=0,NOT(ISNUMBER($H29)),NOT(ISNUMBER($I29)),NOT(ISNUMBER($G29))),"",IF(OR($AG29="",$AH29=""),"",IF(ROUND(ABS($H29-$I29)*ABS($G29)*$AG29*$AH29,6)=0,"",ROUND(ABS($H29-$I29)*ABS($G29)*$AG29*$AH29,6)))) -> 50 | W29: =IF($AM29=0,"",IF($BG29="","OK",LEFT($BG29,LEN($BG29)-2))) -> OK | X29: US | Y29: Breakout & Retest | Z29: Yes | AA29: Confident | AC29: Retest of 2,290 held | AD29: Clean. | AF29: =IF($AM29=0,"",IF($D29<>"",$D29,IF(IFERROR(INDEX(Accounts!$C$7:$C$16,MATCH($C29,Accounts!$B$7:$B$16,0))&"","")<>"",INDEX(Accounts!$C$7:$C$16,MATCH($C29,Accounts!$B$7:$B$16,0)),Settings!$C$6))) -> Crypto | AG29: =IF($AM29=0,"",IF(AND($BE29>0,N(INDEX(Instruments!$D$6:$D$205,MAX(1,$BE29)))>0),INDEX(Instruments!$D$6:$D$205,MAX(1,$BE29)),IF(N(INDEX(Settings!$D$14:$D$18,$BF29))>0,INDEX(Settings!$D$14:$D$18,$BF29),""))) -> 1 | AH29: =IF($AM29=0,"",IF($AF29<>"Forex",1,IF(MID(UPPER(SUBSTITUTE(TRIM($E29),"/","")),4,3)=UPPER(TRIM(Settings!$C$7)),1,IF(LEFT(UPPER(SUBSTITUTE(TRIM($E29),"/","")),3)=UPPER(TRIM(Settings!$C$7)),IF(AND(ISNUMBER($K29),N($K29)<>0),1/$K29,""),"")))) -> 1 | AI29: =IF($AM29=0,"",IF(OR(NOT(ISNUMBER($H29)),NOT(ISNUMBER($K29)),NOT(ISNUMBER($G29)),$AG29="",$AH29=""),"",ROUND(($K29-$H29)*IF($F29="Short",-1,1)*$G29*$AG29*$AH29,6))) -> 100 | AJ29: =IF($AM29=0,"",IF(INDEX(Settings!$E$14:$E$18,$BF29)="% of notional",IF(OR($AG29="",NOT(ISNUMBER($H29)),NOT(ISNUMBER($G29))),"",ROUND(ABS($H29*$G29*$AG29*N($AH29))*IF($L29="Limit",N(INDEX(Settings!$G$14:$G$18,$BF29)),N(INDEX(Settings!$H$14:$H$18,$BF29)))+IF(ISNUMBER($K29),ABS($K29*$G29*$AG29*N($AH29))*IF($M29="Target",N(INDEX(Settings!$G$14:$G$18,$BF29)),N(INDEX(Settings!$H$14:$H$18,$BF29))),0),6)),IF(NOT(ISNUMBER($G29)),"",ROUND(ABS($G29)*2*IF(AND($BE29>0,ISNUMBER(INDEX(Instruments!$G$6:$G$205,MAX(1,$BE29)))),INDEX(Instruments!$G$6:$G$205,MAX(1,$BE29)),N(INDEX(Settings!$F$14:$F$18,$BF29))),6)))) -> 1.856 | AK29: =IF($AM29=0,"",IF(ISNUMBER($O29),$O29,$AI29)) -> 100 | AL29: =IF($AM29=0,"",IF(ISNUMBER($P29),$P29,N($AJ29))) -> 1.856 | AM29: =IF(AND($A29<>"",$E29<>"",OR(AND(ISNUMBER($G29),ISNUMBER($H29),ISNUMBER($K29)),ISNUMBER($O29))),1,0) -> 1 | AN29: =IF($A29="","",$A29-WEEKDAY($A29,3)) -> 46293 | AO29: =IF($A29="","",WEEKDAY($A29,2)) -> 4 | AP29: =IF(OR($AM29=0,$C29=""),"",IFERROR(N(INDEX(Accounts!$E$7:$E$16,MATCH($C29,Accounts!$B$7:$B$16,0))),0)+SUMIFS($Q$6:$Q29,$C$6:$C29,$C29)) -> 5152.7959 | AQ29: =IF(OR($AM29=0,$C29=""),"",SUMIFS($Q$6:$Q$1005,$C$6:$C$1005,$C29,$A$6:$A$1005,$A29)) -> 98.144 | AR29: =IF(OR($AM29=0,$C29=""),"",IFERROR(N(INDEX(Accounts!$E$7:$E$16,MATCH($C29,Accounts!$B$7:$B$16,0))),0)+SUMIFS($Q$6:$Q$1005,$C$6:$C$1005,$C29,$A$6:$A$1005,"<="&$A29)) -> 5152.7959 | AS29: =IF(OR($AM29=0,$Q29=""),0,IF(AND($A29>=Lists!$W$6,$A29<=Lists!$W$7,OR(Dashboard!$D$6="All accounts",$C29=Dashboard!$D$6),OR(Dashboard!$D$7="All markets",$AF29=Dashboard!$D$7)),1,0)) -> 1 | AT29: =IF($AS29=1,N(AT28)+$Q29,N(AT28)) -> 624.79588 | AU29: =MAX(N(AU28),$AT29) -> 916.75188 | AV29: =$AT29-$AU29 -> -291.956 | AW29: =IF($AS29=1,IF($S29="Win",N(AW28)+1,IF($S29="Loss",0,N(AW28))),N(AW28)) -> 1 | AX29: =IF($AS29=1,IF($S29="Loss",N(AX28)+1,IF($S29="Win",0,N(AX28))),N(AX28)) -> 0 | AY29: =IF($AS29=1,COUNTIF($AS$6:$AS29,1),"") -> 24 | AZ29: =MIN(23,N(Lists!$W$8)) -> 23 | BA29: =IF($AS29=1,IF(COUNTIFS($A$6:$A29,$A29,$AS$6:$AS29,1)=1,1,0),0) -> 0 | BB29: =IF($BA29=1,SUMIFS($Q$6:$Q$1005,$A$6:$A$1005,$A29,$AS$6:$AS$1005,1),"") | BC29: =IF(ISNUMBER($R29),1,0) -> 1 | BD29: =IF(ISNUMBER($U29),$U29*$V29,"") -> 0 | BE29: =IF($AM29=0,"",IFERROR(MATCH($AF29&"|"&UPPER(TRIM($E29)),Lists!$A$6:$A$205,0),0)) -> 47 | BF29: =IF($AM29=0,"",IFERROR(MATCH($AF29,Settings!$B$14:$B$18,0),IFERROR(MATCH(Settings!$C$6,Settings!$B$14:$B$18,0),1))) -> 5 | BG29: =IF($AM29=0,"",IF(NOT(ISNUMBER($I29)),"No stop; ","")&IF(AND(ISNUMBER($H29),ISNUMBER($I29)),IF(OR(AND($F29<>"Short",$I29>=$H29),AND($F29="Short",$I29<=$H29)),"Stop on wrong side; ",""),"")&IF($F29="","No direction; ","")&IF(AND(ISNUMBER(Settings!$C$22),ISNUMBER($V29)),IF($V29>Settings!$C$22,"Risk over max $; ",""),"")&IF(AND(ISNUMBER(Settings!$C$23),ISNUMBER($V29),ISNUMBER($AP29),IFERROR(N(INDEX(Accounts!$E$7:$E$16,MATCH($C29,Accounts!$B$7:$B$16,0))),0)>0),IF($V29>Settings!$C$23*($AP29-N($Q29)),"Risk over max %; ",""),"")&IF(AND(ISNUMBER(Settings!$C$24),ISNUMBER($N29)),IF($N29>Settings!$C$24,"Leverage over max; ",""),"")&IF(AND(ISNUMBER(Settings!$C$27),ISNUMBER($T29)),IF($T29<Settings!$C$27,"R:R below min; ",""),"")&IF(ISNUMBER(Settings!$C$25),IF(COUNTIFS($A$6:$A29,$A29,$AM$6:$AM29,1)>Settings!$C$25,"Over max trades/day; ",""),"")&IF(ISNUMBER(Settings!$C$26),IF(SUMIFS($Q$5:$Q28,$A$5:$A28,$A29)<=-Settings!$C$26,"Traded after daily max loss; ",""),"")&IF(AND($AG29="",NOT(ISNUMBER($O29))),"Symbol not in Instruments; ","")&IF(AND($AH29="",NOT(ISNUMBER($O29))),"Forex cross: type Gross P&L; ","")) | BH29: =IF(ISNUMBER($Q29),1,0) -> 1 | BI29: =IF($Y29="",0,1) -> 1 | BJ29: =IF($AB29="",0,1) -> 0 | BK29: =IF(AND($BH29=1,$W29<>"OK"),1,0) -> 0 | BL29: =IF(N($AZ29)=0,0,IFERROR(INDEX($AT$6:$AT$1005,MATCH($AZ29,$AY$6:$AY$1005,0)),0)) -> 526.65188 | BM29: =IF(ISNUMBER(SEARCH("daily max loss",$BG29)),1,0) -> 0
A30: 46297 | B30: 0.40347222 | C30: Prop Eval 50K | E30: MNQ | F30: Short | G30: 2 | H30: 29900 | I30: 29930 | J30: 29840 | K30: 29842.5 | L30: Limit | M30: Manual | Q30: =IF($AM30=0,"",IF(ISNUMBER($AK30),$AK30-N($AL30),"")) -> 228 | R30: =IF(OR($Q30="",NOT(ISNUMBER($V30))),"",$AK30/$V30) -> 1.9166667 | S30: =IF($Q30="","",IF(AND(ISNUMBER($R30),ABS(N($R30))<N(Settings!$C$8)),"Scratch",IF($Q30>0,"Win",IF($Q30<0,"Loss","Scratch")))) -> Win | T30: =IF(OR($AM30=0,NOT(ISNUMBER($H30)),NOT(ISNUMBER($I30)),NOT(ISNUMBER($J30))),"",IF($H30=$I30,"",ROUND(ABS($J30-$H30)/ABS($H30-$I30),6))) -> 2 | U30: =IF(OR($S30<>"Win",NOT(ISNUMBER($T30)),NOT(ISNUMBER($R30))),"",MAX(0,$T30-$R30)) -> 0.083333333 | V30: =IF(OR($AM30=0,NOT(ISNUMBER($H30)),NOT(ISNUMBER($I30)),NOT(ISNUMBER($G30))),"",IF(OR($AG30="",$AH30=""),"",IF(ROUND(ABS($H30-$I30)*ABS($G30)*$AG30*$AH30,6)=0,"",ROUND(ABS($H30-$I30)*ABS($G30)*$AG30*$AH30,6)))) -> 120 | W30: =IF($AM30=0,"",IF($BG30="","OK",LEFT($BG30,LEN($BG30)-2))) -> OK | X30: NY Open | Y30: Range Fade | Z30: Yes | AA30: Calm | AC30: Range high rejection | AD30: Closed just before target. | AF30: =IF($AM30=0,"",IF($D30<>"",$D30,IF(IFERROR(INDEX(Accounts!$C$7:$C$16,MATCH($C30,Accounts!$B$7:$B$16,0))&"","")<>"",INDEX(Accounts!$C$7:$C$16,MATCH($C30,Accounts!$B$7:$B$16,0)),Settings!$C$6))) -> Futures | AG30: =IF($AM30=0,"",IF(AND($BE30>0,N(INDEX(Instruments!$D$6:$D$205,MAX(1,$BE30)))>0),INDEX(Instruments!$D$6:$D$205,MAX(1,$BE30)),IF(N(INDEX(Settings!$D$14:$D$18,$BF30))>0,INDEX(Settings!$D$14:$D$18,$BF30),""))) -> 2 | AH30: =IF($AM30=0,"",IF($AF30<>"Forex",1,IF(MID(UPPER(SUBSTITUTE(TRIM($E30),"/","")),4,3)=UPPER(TRIM(Settings!$C$7)),1,IF(LEFT(UPPER(SUBSTITUTE(TRIM($E30),"/","")),3)=UPPER(TRIM(Settings!$C$7)),IF(AND(ISNUMBER($K30),N($K30)<>0),1/$K30,""),"")))) -> 1 | AI30: =IF($AM30=0,"",IF(OR(NOT(ISNUMBER($H30)),NOT(ISNUMBER($K30)),NOT(ISNUMBER($G30)),$AG30="",$AH30=""),"",ROUND(($K30-$H30)*IF($F30="Short",-1,1)*$G30*$AG30*$AH30,6))) -> 230 | AJ30: =IF($AM30=0,"",IF(INDEX(Settings!$E$14:$E$18,$BF30)="% of notional",IF(OR($AG30="",NOT(ISNUMBER($H30)),NOT(ISNUMBER($G30))),"",ROUND(ABS($H30*$G30*$AG30*N($AH30))*IF($L30="Limit",N(INDEX(Settings!$G$14:$G$18,$BF30)),N(INDEX(Settings!$H$14:$H$18,$BF30)))+IF(ISNUMBER($K30),ABS($K30*$G30*$AG30*N($AH30))*IF($M30="Target",N(INDEX(Settings!$G$14:$G$18,$BF30)),N(INDEX(Settings!$H$14:$H$18,$BF30))),0),6)),IF(NOT(ISNUMBER($G30)),"",ROUND(ABS($G30)*2*IF(AND($BE30>0,ISNUMBER(INDEX(Instruments!$G$6:$G$205,MAX(1,$BE30)))),INDEX(Instruments!$G$6:$G$205,MAX(1,$BE30)),N(INDEX(Settings!$F$14:$F$18,$BF30))),6)))) -> 2 | AK30: =IF($AM30=0,"",IF(ISNUMBER($O30),$O30,$AI30)) -> 230 | AL30: =IF($AM30=0,"",IF(ISNUMBER($P30),$P30,N($AJ30))) -> 2 | AM30: =IF(AND($A30<>"",$E30<>"",OR(AND(ISNUMBER($G30),ISNUMBER($H30),ISNUMBER($K30)),ISNUMBER($O30))),1,0) -> 1 | AN30: =IF($A30="","",$A30-WEEKDAY($A30,3)) -> 46293 | AO30: =IF($A30="","",WEEKDAY($A30,2)) -> 5 | AP30: =IF(OR($AM30=0,$C30=""),"",IFERROR(N(INDEX(Accounts!$E$7:$E$16,MATCH($C30,Accounts!$B$7:$B$16,0))),0)+SUMIFS($Q$6:$Q30,$C$6:$C30,$C30)) -> 50700 | AQ30: =IF(OR($AM30=0,$C30=""),"",SUMIFS($Q$6:$Q$1005,$C$6:$C$1005,$C30,$A$6:$A$1005,$A30)) -> 228 | AR30: =IF(OR($AM30=0,$C30=""),"",IFERROR(N(INDEX(Accounts!$E$7:$E$16,MATCH($C30,Accounts!$B$7:$B$16,0))),0)+SUMIFS($Q$6:$Q$1005,$C$6:$C$1005,$C30,$A$6:$A$1005,"<="&$A30)) -> 50700 | AS30: =IF(OR($AM30=0,$Q30=""),0,IF(AND($A30>=Lists!$W$6,$A30<=Lists!$W$7,OR(Dashboard!$D$6="All accounts",$C30=Dashboard!$D$6),OR(Dashboard!$D$7="All markets",$AF30=Dashboard!$D$7)),1,0)) -> 1 | AT30: =IF($AS30=1,N(AT29)+$Q30,N(AT29)) -> 852.79588 | AU30: =MAX(N(AU29),$AT30) -> 916.75188 | AV30: =$AT30-$AU30 -> -63.956 | AW30: =IF($AS30=1,IF($S30="Win",N(AW29)+1,IF($S30="Loss",0,N(AW29))),N(AW29)) -> 2 | AX30: =IF($AS30=1,IF($S30="Loss",N(AX29)+1,IF($S30="Win",0,N(AX29))),N(AX29)) -> 0 | AY30: =IF($AS30=1,COUNTIF($AS$6:$AS30,1),"") -> 25 | AZ30: =MIN(24,N(Lists!$W$8)) -> 24 | BA30: =IF($AS30=1,IF(COUNTIFS($A$6:$A30,$A30,$AS$6:$AS30,1)=1,1,0),0) -> 1 | BB30: =IF($BA30=1,SUMIFS($Q$6:$Q$1005,$A$6:$A$1005,$A30,$AS$6:$AS$1005,1),"") -> 228 | BC30: =IF(ISNUMBER($R30),1,0) -> 1 | BD30: =IF(ISNUMBER($U30),$U30*$V30,"") -> 10 | BE30: =IF($AM30=0,"",IFERROR(MATCH($AF30&"|"&UPPER(TRIM($E30)),Lists!$A$6:$A$205,0),0)) -> 3 | BF30: =IF($AM30=0,"",IFERROR(MATCH($AF30,Settings!$B$14:$B$18,0),IFERROR(MATCH(Settings!$C$6,Settings!$B$14:$B$18,0),1))) -> 1 | BG30: =IF($AM30=0,"",IF(NOT(ISNUMBER($I30)),"No stop; ","")&IF(AND(ISNUMBER($H30),ISNUMBER($I30)),IF(OR(AND($F30<>"Short",$I30>=$H30),AND($F30="Short",$I30<=$H30)),"Stop on wrong side; ",""),"")&IF($F30="","No direction; ","")&IF(AND(ISNUMBER(Settings!$C$22),ISNUMBER($V30)),IF($V30>Settings!$C$22,"Risk over max $; ",""),"")&IF(AND(ISNUMBER(Settings!$C$23),ISNUMBER($V30),ISNUMBER($AP30),IFERROR(N(INDEX(Accounts!$E$7:$E$16,MATCH($C30,Accounts!$B$7:$B$16,0))),0)>0),IF($V30>Settings!$C$23*($AP30-N($Q30)),"Risk over max %; ",""),"")&IF(AND(ISNUMBER(Settings!$C$24),ISNUMBER($N30)),IF($N30>Settings!$C$24,"Leverage over max; ",""),"")&IF(AND(ISNUMBER(Settings!$C$27),ISNUMBER($T30)),IF($T30<Settings!$C$27,"R:R below min; ",""),"")&IF(ISNUMBER(Settings!$C$25),IF(COUNTIFS($A$6:$A30,$A30,$AM$6:$AM30,1)>Settings!$C$25,"Over max trades/day; ",""),"")&IF(ISNUMBER(Settings!$C$26),IF(SUMIFS($Q$5:$Q29,$A$5:$A29,$A30)<=-Settings!$C$26,"Traded after daily max loss; ",""),"")&IF(AND($AG30="",NOT(ISNUMBER($O30))),"Symbol not in Instruments; ","")&IF(AND($AH30="",NOT(ISNUMBER($O30))),"Forex cross: type Gross P&L; ","")) | BH30: =IF(ISNUMBER($Q30),1,0) -> 1 | BI30: =IF($Y30="",0,1) -> 1 | BJ30: =IF($AB30="",0,1) -> 0 | BK30: =IF(AND($BH30=1,$W30<>"OK"),1,0) -> 0 | BL30: =IF(N($AZ30)=0,0,IFERROR(INDEX($AT$6:$AT$1005,MATCH($AZ30,$AY$6:$AY$1005,0)),0)) -> 624.79588 | BM30: =IF(ISNUMBER(SEARCH("daily max loss",$BG30)),1,0) -> 0
A31: 46300 | B31: 0.40069444 | C31: Prop Eval 50K | E31: MNQ | F31: Long | G31: 2 | H31: 29750 | I31: 29720 | J31: 29810 | K31: 29810 | L31: Limit | M31: Target | Q31: =IF($AM31=0,"",IF(ISNUMBER($AK31),$AK31-N($AL31),"")) -> 238 | R31: =IF(OR($Q31="",NOT(ISNUMBER($V31))),"",$AK31/$V31) -> 2 | S31: =IF($Q31="","",IF(AND(ISNUMBER($R31),ABS(N($R31))<N(Settings!$C$8)),"Scratch",IF($Q31>0,"Win",IF($Q31<0,"Loss","Scratch")))) -> Win | T31: =IF(OR($AM31=0,NOT(ISNUMBER($H31)),NOT(ISNUMBER($I31)),NOT(ISNUMBER($J31))),"",IF($H31=$I31,"",ROUND(ABS($J31-$H31)/ABS($H31-$I31),6))) -> 2 | U31: =IF(OR($S31<>"Win",NOT(ISNUMBER($T31)),NOT(ISNUMBER($R31))),"",MAX(0,$T31-$R31)) -> 0 | V31: =IF(OR($AM31=0,NOT(ISNUMBER($H31)),NOT(ISNUMBER($I31)),NOT(ISNUMBER($G31))),"",IF(OR($AG31="",$AH31=""),"",IF(ROUND(ABS($H31-$I31)*ABS($G31)*$AG31*$AH31,6)=0,"",ROUND(ABS($H31-$I31)*ABS($G31)*$AG31*$AH31,6)))) -> 120 | W31: =IF($AM31=0,"",IF($BG31="","OK",LEFT($BG31,LEN($BG31)-2))) -> OK | X31: NY Open | Y31: Breakout & Retest | Z31: Yes | AA31: Calm | AC31: Breakout and retest of Friday's high | AD31: Clean. | AF31: =IF($AM31=0,"",IF($D31<>"",$D31,IF(IFERROR(INDEX(Accounts!$C$7:$C$16,MATCH($C31,Accounts!$B$7:$B$16,0))&"","")<>"",INDEX(Accounts!$C$7:$C$16,MATCH($C31,Accounts!$B$7:$B$16,0)),Settings!$C$6))) -> Futures | AG31: =IF($AM31=0,"",IF(AND($BE31>0,N(INDEX(Instruments!$D$6:$D$205,MAX(1,$BE31)))>0),INDEX(Instruments!$D$6:$D$205,MAX(1,$BE31)),IF(N(INDEX(Settings!$D$14:$D$18,$BF31))>0,INDEX(Settings!$D$14:$D$18,$BF31),""))) -> 2 | AH31: =IF($AM31=0,"",IF($AF31<>"Forex",1,IF(MID(UPPER(SUBSTITUTE(TRIM($E31),"/","")),4,3)=UPPER(TRIM(Settings!$C$7)),1,IF(LEFT(UPPER(SUBSTITUTE(TRIM($E31),"/","")),3)=UPPER(TRIM(Settings!$C$7)),IF(AND(ISNUMBER($K31),N($K31)<>0),1/$K31,""),"")))) -> 1 | AI31: =IF($AM31=0,"",IF(OR(NOT(ISNUMBER($H31)),NOT(ISNUMBER($K31)),NOT(ISNUMBER($G31)),$AG31="",$AH31=""),"",ROUND(($K31-$H31)*IF($F31="Short",-1,1)*$G31*$AG31*$AH31,6))) -> 240 | AJ31: =IF($AM31=0,"",IF(INDEX(Settings!$E$14:$E$18,$BF31)="% of notional",IF(OR($AG31="",NOT(ISNUMBER($H31)),NOT(ISNUMBER($G31))),"",ROUND(ABS($H31*$G31*$AG31*N($AH31))*IF($L31="Limit",N(INDEX(Settings!$G$14:$G$18,$BF31)),N(INDEX(Settings!$H$14:$H$18,$BF31)))+IF(ISNUMBER($K31),ABS($K31*$G31*$AG31*N($AH31))*IF($M31="Target",N(INDEX(Settings!$G$14:$G$18,$BF31)),N(INDEX(Settings!$H$14:$H$18,$BF31))),0),6)),IF(NOT(ISNUMBER($G31)),"",ROUND(ABS($G31)*2*IF(AND($BE31>0,ISNUMBER(INDEX(Instruments!$G$6:$G$205,MAX(1,$BE31)))),INDEX(Instruments!$G$6:$G$205,MAX(1,$BE31)),N(INDEX(Settings!$F$14:$F$18,$BF31))),6)))) -> 2 | AK31: =IF($AM31=0,"",IF(ISNUMBER($O31),$O31,$AI31)) -> 240 | AL31: =IF($AM31=0,"",IF(ISNUMBER($P31),$P31,N($AJ31))) -> 2 | AM31: =IF(AND($A31<>"",$E31<>"",OR(AND(ISNUMBER($G31),ISNUMBER($H31),ISNUMBER($K31)),ISNUMBER($O31))),1,0) -> 1 | AN31: =IF($A31="","",$A31-WEEKDAY($A31,3)) -> 46300 | AO31: =IF($A31="","",WEEKDAY($A31,2)) -> 1 | AP31: =IF(OR($AM31=0,$C31=""),"",IFERROR(N(INDEX(Accounts!$E$7:$E$16,MATCH($C31,Accounts!$B$7:$B$16,0))),0)+SUMIFS($Q$6:$Q31,$C$6:$C31,$C31)) -> 50938 | AQ31: =IF(OR($AM31=0,$C31=""),"",SUMIFS($Q$6:$Q$1005,$C$6:$C$1005,$C31,$A$6:$A$1005,$A31)) -> 238 | AR31: =IF(OR($AM31=0,$C31=""),"",IFERROR(N(INDEX(Accounts!$E$7:$E$16,MATCH($C31,Accounts!$B$7:$B$16,0))),0)+SUMIFS($Q$6:$Q$1005,$C$6:$C$1005,$C31,$A$6:$A$1005,"<="&$A31)) -> 50938 | AS31: =IF(OR($AM31=0,$Q31=""),0,IF(AND($A31>=Lists!$W$6,$A31<=Lists!$W$7,OR(Dashboard!$D$6="All accounts",$C31=Dashboard!$D$6),OR(Dashboard!$D$7="All markets",$AF31=Dashboard!$D$7)),1,0)) -> 1 | AT31: =IF($AS31=1,N(AT30)+$Q31,N(AT30)) -> 1090.7959 | AU31: =MAX(N(AU30),$AT31) -> 1090.7959 | AV31: =$AT31-$AU31 -> 0 | AW31: =IF($AS31=1,IF($S31="Win",N(AW30)+1,IF($S31="Loss",0,N(AW30))),N(AW30)) -> 3 | AX31: =IF($AS31=1,IF($S31="Loss",N(AX30)+1,IF($S31="Win",0,N(AX30))),N(AX30)) -> 0 | AY31: =IF($AS31=1,COUNTIF($AS$6:$AS31,1),"") -> 26 | AZ31: =MIN(25,N(Lists!$W$8)) -> 25 | BA31: =IF($AS31=1,IF(COUNTIFS($A$6:$A31,$A31,$AS$6:$AS31,1)=1,1,0),0) -> 1 | BB31: =IF($BA31=1,SUMIFS($Q$6:$Q$1005,$A$6:$A$1005,$A31,$AS$6:$AS$1005,1),"") -> 285.311 | BC31: =IF(ISNUMBER($R31),1,0) -> 1 | BD31: =IF(ISNUMBER($U31),$U31*$V31,"") -> 0 | BE31: =IF($AM31=0,"",IFERROR(MATCH($AF31&"|"&UPPER(TRIM($E31)),Lists!$A$6:$A$205,0),0)) -> 3 | BF31: =IF($AM31=0,"",IFERROR(MATCH($AF31,Settings!$B$14:$B$18,0),IFERROR(MATCH(Settings!$C$6,Settings!$B$14:$B$18,0),1))) -> 1 | BG31: =IF($AM31=0,"",IF(NOT(ISNUMBER($I31)),"No stop; ","")&IF(AND(ISNUMBER($H31),ISNUMBER($I31)),IF(OR(AND($F31<>"Short",$I31>=$H31),AND($F31="Short",$I31<=$H31)),"Stop on wrong side; ",""),"")&IF($F31="","No direction; ","")&IF(AND(ISNUMBER(Settings!$C$22),ISNUMBER($V31)),IF($V31>Settings!$C$22,"Risk over max $; ",""),"")&IF(AND(ISNUMBER(Settings!$C$23),ISNUMBER($V31),ISNUMBER($AP31),IFERROR(N(INDEX(Accounts!$E$7:$E$16,MATCH($C31,Accounts!$B$7:$B$16,0))),0)>0),IF($V31>Settings!$C$23*($AP31-N($Q31)),"Risk over max %; ",""),"")&IF(AND(ISNUMBER(Settings!$C$24),ISNUMBER($N31)),IF($N31>Settings!$C$24,"Leverage over max; ",""),"")&IF(AND(ISNUMBER(Settings!$C$27),ISNUMBER($T31)),IF($T31<Settings!$C$27,"R:R below min; ",""),"")&IF(ISNUMBER(Settings!$C$25),IF(COUNTIFS($A$6:$A31,$A31,$AM$6:$AM31,1)>Settings!$C$25,"Over max trades/day; ",""),"")&IF(ISNUMBER(Settings!$C$26),IF(SUMIFS($Q$5:$Q30,$A$5:$A30,$A31)<=-Settings!$C$26,"Traded after daily max loss; ",""),"")&IF(AND($AG31="",NOT(ISNUMBER($O31))),"Symbol not in Instruments; ","")&IF(AND($AH31="",NOT(ISNUMBER($O31))),"Forex cross: type Gross P&L; ","")) | BH31: =IF(ISNUMBER($Q31),1,0) -> 1 | BI31: =IF($Y31="",0,1) -> 1 | BJ31: =IF($AB31="",0,1) -> 0 | BK31: =IF(AND($BH31=1,$W31<>"OK"),1,0) -> 0 | BL31: =IF(N($AZ31)=0,0,IFERROR(INDEX($AT$6:$AT$1005,MATCH($AZ31,$AY$6:$AY$1005,0)),0)) -> 852.79588 | BM31: =IF(ISNUMBER(SEARCH("daily max loss",$BG31)),1,0) -> 0
A32: 46300 | B32: 0.64583333 | C32: Crypto Main | E32: BTCUSDT | F32: Long | G32: 0.1 | H32: 63800 | I32: 63300 | J32: 64800 | K32: 64350 | L32: Market | M32: Manual | N32: 20 | Q32: =IF($AM32=0,"",IF(ISNUMBER($AK32),$AK32-N($AL32),"")) -> 47.311 | R32: =IF(OR($Q32="",NOT(ISNUMBER($V32))),"",$AK32/$V32) -> 1.1 | S32: =IF($Q32="","",IF(AND(ISNUMBER($R32),ABS(N($R32))<N(Settings!$C$8)),"Scratch",IF($Q32>0,"Win",IF($Q32<0,"Loss","Scratch")))) -> Win | T32: =IF(OR($AM32=0,NOT(ISNUMBER($H32)),NOT(ISNUMBER($I32)),NOT(ISNUMBER($J32))),"",IF($H32=$I32,"",ROUND(ABS($J32-$H32)/ABS($H32-$I32),6))) -> 2 | U32: =IF(OR($S32<>"Win",NOT(ISNUMBER($T32)),NOT(ISNUMBER($R32))),"",MAX(0,$T32-$R32)) -> 0.9 | V32: =IF(OR($AM32=0,NOT(ISNUMBER($H32)),NOT(ISNUMBER($I32)),NOT(ISNUMBER($G32))),"",IF(OR($AG32="",$AH32=""),"",IF(ROUND(ABS($H32-$I32)*ABS($G32)*$AG32*$AH32,6)=0,"",ROUND(ABS($H32-$I32)*ABS($G32)*$AG32*$AH32,6)))) -> 50 | W32: =IF($AM32=0,"",IF($BG32="","OK",LEFT($BG32,LEN($BG32)-2))) -> OK | X32: US | Y32: Trend Pullback | Z32: No | AA32: Anxious | AB32: Took profit too early | AC32: Pullback in uptrend | AD32: Market entry + early exit = taker fees twice. | AF32: =IF($AM32=0,"",IF($D32<>"",$D32,IF(IFERROR(INDEX(Accounts!$C$7:$C$16,MATCH($C32,Accounts!$B$7:$B$16,0))&"","")<>"",INDEX(Accounts!$C$7:$C$16,MATCH($C32,Accounts!$B$7:$B$16,0)),Settings!$C$6))) -> Crypto | AG32: =IF($AM32=0,"",IF(AND($BE32>0,N(INDEX(Instruments!$D$6:$D$205,MAX(1,$BE32)))>0),INDEX(Instruments!$D$6:$D$205,MAX(1,$BE32)),IF(N(INDEX(Settings!$D$14:$D$18,$BF32))>0,INDEX(Settings!$D$14:$D$18,$BF32),""))) -> 1 | AH32: =IF($AM32=0,"",IF($AF32<>"Forex",1,IF(MID(UPPER(SUBSTITUTE(TRIM($E32),"/","")),4,3)=UPPER(TRIM(Settings!$C$7)),1,IF(LEFT(UPPER(SUBSTITUTE(TRIM($E32),"/","")),3)=UPPER(TRIM(Settings!$C$7)),IF(AND(ISNUMBER($K32),N($K32)<>0),1/$K32,""),"")))) -> 1 | AI32: =IF($AM32=0,"",IF(OR(NOT(ISNUMBER($H32)),NOT(ISNUMBER($K32)),NOT(ISNUMBER($G32)),$AG32="",$AH32=""),"",ROUND(($K32-$H32)*IF($F32="Short",-1,1)*$G32*$AG32*$AH32,6))) -> 55 | AJ32: =IF($AM32=0,"",IF(INDEX(Settings!$E$14:$E$18,$BF32)="% of notional",IF(OR($AG32="",NOT(ISNUMBER($H32)),NOT(ISNUMBER($G32))),"",ROUND(ABS($H32*$G32*$AG32*N($AH32))*IF($L32="Limit",N(INDEX(Settings!$G$14:$G$18,$BF32)),N(INDEX(Settings!$H$14:$H$18,$BF32)))+IF(ISNUMBER($K32),ABS($K32*$G32*$AG32*N($AH32))*IF($M32="Target",N(INDEX(Settings!$G$14:$G$18,$BF32)),N(INDEX(Settings!$H$14:$H$18,$BF32))),0),6)),IF(NOT(ISNUMBER($G32)),"",ROUND(ABS($G32)*2*IF(AND($BE32>0,ISNUMBER(INDEX(Instruments!$G$6:$G$205,MAX(1,$BE32)))),INDEX(Instruments!$G$6:$G$205,MAX(1,$BE32)),N(INDEX(Settings!$F$14:$F$18,$BF32))),6)))) -> 7.689 | AK32: =IF($AM32=0,"",IF(ISNUMBER($O32),$O32,$AI32)) -> 55 | AL32: =IF($AM32=0,"",IF(ISNUMBER($P32),$P32,N($AJ32))) -> 7.689 | AM32: =IF(AND($A32<>"",$E32<>"",OR(AND(ISNUMBER($G32),ISNUMBER($H32),ISNUMBER($K32)),ISNUMBER($O32))),1,0) -> 1 | AN32: =IF($A32="","",$A32-WEEKDAY($A32,3)) -> 46300 | AO32: =IF($A32="","",WEEKDAY($A32,2)) -> 1 | AP32: =IF(OR($AM32=0,$C32=""),"",IFERROR(N(INDEX(Accounts!$E$7:$E$16,MATCH($C32,Accounts!$B$7:$B$16,0))),0)+SUMIFS($Q$6:$Q32,$C$6:$C32,$C32)) -> 5200.1069 | AQ32: =IF(OR($AM32=0,$C32=""),"",SUMIFS($Q$6:$Q$1005,$C$6:$C$1005,$C32,$A$6:$A$1005,$A32)) -> 47.311 | AR32: =IF(OR($AM32=0,$C32=""),"",IFERROR(N(INDEX(Accounts!$E$7:$E$16,MATCH($C32,Accounts!$B$7:$B$16,0))),0)+SUMIFS($Q$6:$Q$1005,$C$6:$C$1005,$C32,$A$6:$A$1005,"<="&$A32)) -> 5200.1069 | AS32: =IF(OR($AM32=0,$Q32=""),0,IF(AND($A32>=Lists!$W$6,$A32<=Lists!$W$7,OR(Dashboard!$D$6="All accounts",$C32=Dashboard!$D$6),OR(Dashboard!$D$7="All markets",$AF32=Dashboard!$D$7)),1,0)) -> 1 | AT32: =IF($AS32=1,N(AT31)+$Q32,N(AT31)) -> 1138.1069 | AU32: =MAX(N(AU31),$AT32) -> 1138.1069 | AV32: =$AT32-$AU32 -> 0 | AW32: =IF($AS32=1,IF($S32="Win",N(AW31)+1,IF($S32="Loss",0,N(AW31))),N(AW31)) -> 4 | AX32: =IF($AS32=1,IF($S32="Loss",N(AX31)+1,IF($S32="Win",0,N(AX31))),N(AX31)) -> 0 | AY32: =IF($AS32=1,COUNTIF($AS$6:$AS32,1),"") -> 27 | AZ32: =MIN(26,N(Lists!$W$8)) -> 26 | BA32: =IF($AS32=1,IF(COUNTIFS($A$6:$A32,$A32,$AS$6:$AS32,1)=1,1,0),0) -> 0 | BB32: =IF($BA32=1,SUMIFS($Q$6:$Q$1005,$A$6:$A$1005,$A32,$AS$6:$AS$1005,1),"") | BC32: =IF(ISNUMBER($R32),1,0) -> 1 | BD32: =IF(ISNUMBER($U32),$U32*$V32,"") -> 45 | BE32: =IF($AM32=0,"",IFERROR(MATCH($AF32&"|"&UPPER(TRIM($E32)),Lists!$A$6:$A$205,0),0)) -> 46 | BF32: =IF($AM32=0,"",IFERROR(MATCH($AF32,Settings!$B$14:$B$18,0),IFERROR(MATCH(Settings!$C$6,Settings!$B$14:$B$18,0),1))) -> 5 | BG32: =IF($AM32=0,"",IF(NOT(ISNUMBER($I32)),"No stop; ","")&IF(AND(ISNUMBER($H32),ISNUMBER($I32)),IF(OR(AND($F32<>"Short",$I32>=$H32),AND($F32="Short",$I32<=$H32)),"Stop on wrong side; ",""),"")&IF($F32="","No direction; ","")&IF(AND(ISNUMBER(Settings!$C$22),ISNUMBER($V32)),IF($V32>Settings!$C$22,"Risk over max $; ",""),"")&IF(AND(ISNUMBER(Settings!$C$23),ISNUMBER($V32),ISNUMBER($AP32),IFERROR(N(INDEX(Accounts!$E$7:$E$16,MATCH($C32,Accounts!$B$7:$B$16,0))),0)>0),IF($V32>Settings!$C$23*($AP32-N($Q32)),"Risk over max %; ",""),"")&IF(AND(ISNUMBER(Settings!$C$24),ISNUMBER($N32)),IF($N32>Settings!$C$24,"Leverage over max; ",""),"")&IF(AND(ISNUMBER(Settings!$C$27),ISNUMBER($T32)),IF($T32<Settings!$C$27,"R:R below min; ",""),"")&IF(ISNUMBER(Settings!$C$25),IF(COUNTIFS($A$6:$A32,$A32,$AM$6:$AM32,1)>Settings!$C$25,"Over max trades/day; ",""),"")&IF(ISNUMBER(Settings!$C$26),IF(SUMIFS($Q$5:$Q31,$A$5:$A31,$A32)<=-Settings!$C$26,"Traded after daily max loss; ",""),"")&IF(AND($AG32="",NOT(ISNUMBER($O32))),"Symbol not in Instruments; ","")&IF(AND($AH32="",NOT(ISNUMBER($O32))),"Forex cross: type Gross P&L; ","")) | BH32: =IF(ISNUMBER($Q32),1,0) -> 1 | BI32: =IF($Y32="",0,1) -> 1 | BJ32: =IF($AB32="",0,1) -> 1 | BK32: =IF(AND($BH32=1,$W32<>"OK"),1,0) -> 0 | BL32: =IF(N($AZ32)=0,0,IFERROR(INDEX($AT$6:$AT$1005,MATCH($AZ32,$AY$6:$AY$1005,0)),0)) -> 1090.7959 | BM32: =IF(ISNUMBER(SEARCH("daily max loss",$BG32)),1,0) -> 0
A33: 46301 | B33: 0.425 | C33: Prop Eval 50K | E33: MGC | F33: Short | G33: 1 | H33: 4066 | I33: 4072 | J33: 4054 | K33: 4061 | L33: Limit | M33: Manual | Q33: =IF($AM33=0,"",IF(ISNUMBER($AK33),$AK33-N($AL33),"")) -> 49 | R33: =IF(OR($Q33="",NOT(ISNUMBER($V33))),"",$AK33/$V33) -> 0.83333333 | S33: =IF($Q33="","",IF(AND(ISNUMBER($R33),ABS(N($R33))<N(Settings!$C$8)),"Scratch",IF($Q33>0,"Win",IF($Q33<0,"Loss","Scratch")))) -> Win | T33: =IF(OR($AM33=0,NOT(ISNUMBER($H33)),NOT(ISNUMBER($I33)),NOT(ISNUMBER($J33))),"",IF($H33=$I33,"",ROUND(ABS($J33-$H33)/ABS($H33-$I33),6))) -> 2 | U33: =IF(OR($S33<>"Win",NOT(ISNUMBER($T33)),NOT(ISNUMBER($R33))),"",MAX(0,$T33-$R33)) -> 1.1666667 | V33: =IF(OR($AM33=0,NOT(ISNUMBER($H33)),NOT(ISNUMBER($I33)),NOT(ISNUMBER($G33))),"",IF(OR($AG33="",$AH33=""),"",IF(ROUND(ABS($H33-$I33)*ABS($G33)*$AG33*$AH33,6)=0,"",ROUND(ABS($H33-$I33)*ABS($G33)*$AG33*$AH33,6)))) -> 60 | W33: =IF($AM33=0,"",IF($BG33="","OK",LEFT($BG33,LEN($BG33)-2))) -> OK | X33: NY Open | Y33: Trend Pullback | Z33: No | AA33: Anxious | AB33: Took profit too early | AC33: Downtrend pullback to the 20 EMA | AD33: Took +5 instead of +12. Again. | AF33: =IF($AM33=0,"",IF($D33<>"",$D33,IF(IFERROR(INDEX(Accounts!$C$7:$C$16,MATCH($C33,Accounts!$B$7:$B$16,0))&"","")<>"",INDEX(Accounts!$C$7:$C$16,MATCH($C33,Accounts!$B$7:$B$16,0)),Settings!$C$6))) -> Futures | AG33: =IF($AM33=0,"",IF(AND($BE33>0,N(INDEX(Instruments!$D$6:$D$205,MAX(1,$BE33)))>0),INDEX(Instruments!$D$6:$D$205,MAX(1,$BE33)),IF(N(INDEX(Settings!$D$14:$D$18,$BF33))>0,INDEX(Settings!$D$14:$D$18,$BF33),""))) -> 10 | AH33: =IF($AM33=0,"",IF($AF33<>"Forex",1,IF(MID(UPPER(SUBSTITUTE(TRIM($E33),"/","")),4,3)=UPPER(TRIM(Settings!$C$7)),1,IF(LEFT(UPPER(SUBSTITUTE(TRIM($E33),"/","")),3)=UPPER(TRIM(Settings!$C$7)),IF(AND(ISNUMBER($K33),N($K33)<>0),1/$K33,""),"")))) -> 1 | AI33: =IF($AM33=0,"",IF(OR(NOT(ISNUMBER($H33)),NOT(ISNUMBER($K33)),NOT(ISNUMBER($G33)),$AG33="",$AH33=""),"",ROUND(($K33-$H33)*IF($F33="Short",-1,1)*$G33*$AG33*$AH33,6))) -> 50 | AJ33: =IF($AM33=0,"",IF(INDEX(Settings!$E$14:$E$18,$BF33)="% of notional",IF(OR($AG33="",NOT(ISNUMBER($H33)),NOT(ISNUMBER($G33))),"",ROUND(ABS($H33*$G33*$AG33*N($AH33))*IF($L33="Limit",N(INDEX(Settings!$G$14:$G$18,$BF33)),N(INDEX(Settings!$H$14:$H$18,$BF33)))+IF(ISNUMBER($K33),ABS($K33*$G33*$AG33*N($AH33))*IF($M33="Target",N(INDEX(Settings!$G$14:$G$18,$BF33)),N(INDEX(Settings!$H$14:$H$18,$BF33))),0),6)),IF(NOT(ISNUMBER($G33)),"",ROUND(ABS($G33)*2*IF(AND($BE33>0,ISNUMBER(INDEX(Instruments!$G$6:$G$205,MAX(1,$BE33)))),INDEX(Instruments!$G$6:$G$205,MAX(1,$BE33)),N(INDEX(Settings!$F$14:$F$18,$BF33))),6)))) -> 1 | AK33: =IF($AM33=0,"",IF(ISNUMBER($O33),$O33,$AI33)) -> 50 | AL33: =IF($AM33=0,"",IF(ISNUMBER($P33),$P33,N($AJ33))) -> 1 | AM33: =IF(AND($A33<>"",$E33<>"",OR(AND(ISNUMBER($G33),ISNUMBER($H33),ISNUMBER($K33)),ISNUMBER($O33))),1,0) -> 1 | AN33: =IF($A33="","",$A33-WEEKDAY($A33,3)) -> 46300 | AO33: =IF($A33="","",WEEKDAY($A33,2)) -> 2 | AP33: =IF(OR($AM33=0,$C33=""),"",IFERROR(N(INDEX(Accounts!$E$7:$E$16,MATCH($C33,Accounts!$B$7:$B$16,0))),0)+SUMIFS($Q$6:$Q33,$C$6:$C33,$C33)) -> 50987 | AQ33: =IF(OR($AM33=0,$C33=""),"",SUMIFS($Q$6:$Q$1005,$C$6:$C$1005,$C33,$A$6:$A$1005,$A33)) -> 49 | AR33: =IF(OR($AM33=0,$C33=""),"",IFERROR(N(INDEX(Accounts!$E$7:$E$16,MATCH($C33,Accounts!$B$7:$B$16,0))),0)+SUMIFS($Q$6:$Q$1005,$C$6:$C$1005,$C33,$A$6:$A$1005,"<="&$A33)) -> 50987 | AS33: =IF(OR($AM33=0,$Q33=""),0,IF(AND($A33>=Lists!$W$6,$A33<=Lists!$W$7,OR(Dashboard!$D$6="All accounts",$C33=Dashboard!$D$6),OR(Dashboard!$D$7="All markets",$AF33=Dashboard!$D$7)),1,0)) -> 1 | AT33: =IF($AS33=1,N(AT32)+$Q33,N(AT32)) -> 1187.1069 | AU33: =MAX(N(AU32),$AT33) -> 1187.1069 | AV33: =$AT33-$AU33 -> 0 | AW33: =IF($AS33=1,IF($S33="Win",N(AW32)+1,IF($S33="Loss",0,N(AW32))),N(AW32)) -> 5 | AX33: =IF($AS33=1,IF($S33="Loss",N(AX32)+1,IF($S33="Win",0,N(AX32))),N(AX32)) -> 0 | AY33: =IF($AS33=1,COUNTIF($AS$6:$AS33,1),"") -> 28 | AZ33: =MIN(27,N(Lists!$W$8)) -> 27 | BA33: =IF($AS33=1,IF(COUNTIFS($A$6:$A33,$A33,$AS$6:$AS33,1)=1,1,0),0) -> 1 | BB33: =IF($BA33=1,SUMIFS($Q$6:$Q$1005,$A$6:$A$1005,$A33,$AS$6:$AS$1005,1),"") -> 49 | BC33: =IF(ISNUMBER($R33),1,0) -> 1 | BD33: =IF(ISNUMBER($U33),$U33*$V33,"") -> 70 | BE33: =IF($AM33=0,"",IFERROR(MATCH($AF33&"|"&UPPER(TRIM($E33)),Lists!$A$6:$A$205,0),0)) -> 14 | BF33: =IF($AM33=0,"",IFERROR(MATCH($AF33,Settings!$B$14:$B$18,0),IFERROR(MATCH(Settings!$C$6,Settings!$B$14:$B$18,0),1))) -> 1 | BG33: =IF($AM33=0,"",IF(NOT(ISNUMBER($I33)),"No stop; ","")&IF(AND(ISNUMBER($H33),ISNUMBER($I33)),IF(OR(AND($F33<>"Short",$I33>=$H33),AND($F33="Short",$I33<=$H33)),"Stop on wrong side; ",""),"")&IF($F33="","No direction; ","")&IF(AND(ISNUMBER(Settings!$C$22),ISNUMBER($V33)),IF($V33>Settings!$C$22,"Risk over max $; ",""),"")&IF(AND(ISNUMBER(Settings!$C$23),ISNUMBER($V33),ISNUMBER($AP33),IFERROR(N(INDEX(Accounts!$E$7:$E$16,MATCH($C33,Accounts!$B$7:$B$16,0))),0)>0),IF($V33>Settings!$C$23*($AP33-N($Q33)),"Risk over max %; ",""),"")&IF(AND(ISNUMBER(Settings!$C$24),ISNUMBER($N33)),IF($N33>Settings!$C$24,"Leverage over max; ",""),"")&IF(AND(ISNUMBER(Settings!$C$27),ISNUMBER($T33)),IF($T33<Settings!$C$27,"R:R below min; ",""),"")&IF(ISNUMBER(Settings!$C$25),IF(COUNTIFS($A$6:$A33,$A33,$AM$6:$AM33,1)>Settings!$C$25,"Over max trades/day; ",""),"")&IF(ISNUMBER(Settings!$C$26),IF(SUMIFS($Q$5:$Q32,$A$5:$A32,$A33)<=-Settings!$C$26,"Traded after daily max loss; ",""),"")&IF(AND($AG33="",NOT(ISNUMBER($O33))),"Symbol not in Instruments; ","")&IF(AND($AH33="",NOT(ISNUMBER($O33))),"Forex cross: type Gross P&L; ","")) | BH33: =IF(ISNUMBER($Q33),1,0) -> 1 | BI33: =IF($Y33="",0,1) -> 1 | BJ33: =IF($AB33="",0,1) -> 1 | BK33: =IF(AND($BH33=1,$W33<>"OK"),1,0) -> 0 | BL33: =IF(N($AZ33)=0,0,IFERROR(INDEX($AT$6:$AT$1005,MATCH($AZ33,$AY$6:$AY$1005,0)),0)) -> 1138.1069 | BM33: =IF(ISNUMBER(SEARCH("daily max loss",$BG33)),1,0) -> 0
Q34: =IF($AM34=0,"",IF(ISNUMBER($AK34),$AK34-N($AL34),"")) | R34: =IF(OR($Q34="",NOT(ISNUMBER($V34))),"",$AK34/$V34) | S34: =IF($Q34="","",IF(AND(ISNUMBER($R34),ABS(N($R34))<N(Settings!$C$8)),"Scratch",IF($Q34>0,"Win",IF($Q34<0,"Loss","Scratch")))) | T34: =IF(OR($AM34=0,NOT(ISNUMBER($H34)),NOT(ISNUMBER($I34)),NOT(ISNUMBER($J34))),"",IF($H34=$I34,"",ROUND(ABS($J34-$H34)/ABS($H34-$I34),6))) | U34: =IF(OR($S34<>"Win",NOT(ISNUMBER($T34)),NOT(ISNUMBER($R34))),"",MAX(0,$T34-$R34)) | V34: =IF(OR($AM34=0,NOT(ISNUMBER($H34)),NOT(ISNUMBER($I34)),NOT(ISNUMBER($G34))),"",IF(OR($AG34="",$AH34=""),"",IF(ROUND(ABS($H34-$I34)*ABS($G34)*$AG34*$AH34,6)=0,"",ROUND(ABS($H34-$I34)*ABS($G34)*$AG34*$AH34,6)))) | W34: =IF($AM34=0,"",IF($BG34="","OK",LEFT($BG34,LEN($BG34)-2))) | AF34: =IF($AM34=0,"",IF($D34<>"",$D34,IF(IFERROR(INDEX(Accounts!$C$7:$C$16,MATCH($C34,Accounts!$B$7:$B$16,0))&"","")<>"",INDEX(Accounts!$C$7:$C$16,MATCH($C34,Accounts!$B$7:$B$16,0)),Settings!$C$6))) | AG34: =IF($AM34=0,"",IF(AND($BE34>0,N(INDEX(Instruments!$D$6:$D$205,MAX(1,$BE34)))>0),INDEX(Instruments!$D$6:$D$205,MAX(1,$BE34)),IF(N(INDEX(Settings!$D$14:$D$18,$BF34))>0,INDEX(Settings!$D$14:$D$18,$BF34),""))) | AH34: =IF($AM34=0,"",IF($AF34<>"Forex",1,IF(MID(UPPER(SUBSTITUTE(TRIM($E34),"/","")),4,3)=UPPER(TRIM(Settings!$C$7)),1,IF(LEFT(UPPER(SUBSTITUTE(TRIM($E34),"/","")),3)=UPPER(TRIM(Settings!$C$7)),IF(AND(ISNUMBER($K34),N($K34)<>0),1/$K34,""),"")))) | AI34: =IF($AM34=0,"",IF(OR(NOT(ISNUMBER($H34)),NOT(ISNUMBER($K34)),NOT(ISNUMBER($G34)),$AG34="",$AH34=""),"",ROUND(($K34-$H34)*IF($F34="Short",-1,1)*$G34*$AG34*$AH34,6))) | AJ34: =IF($AM34=0,"",IF(INDEX(Settings!$E$14:$E$18,$BF34)="% of notional",IF(OR($AG34="",NOT(ISNUMBER($H34)),NOT(ISNUMBER($G34))),"",ROUND(ABS($H34*$G34*$AG34*N($AH34))*IF($L34="Limit",N(INDEX(Settings!$G$14:$G$18,$BF34)),N(INDEX(Settings!$H$14:$H$18,$BF34)))+IF(ISNUMBER($K34),ABS($K34*$G34*$AG34*N($AH34))*IF($M34="Target",N(INDEX(Settings!$G$14:$G$18,$BF34)),N(INDEX(Settings!$H$14:$H$18,$BF34))),0),6)),IF(NOT(ISNUMBER($G34)),"",ROUND(ABS($G34)*2*IF(AND($BE34>0,ISNUMBER(INDEX(Instruments!$G$6:$G$205,MAX(1,$BE34)))),INDEX(Instruments!$G$6:$G$205,MAX(1,$BE34)),N(INDEX(Settings!$F$14:$F$18,$BF34))),6)))) | AK34: =IF($AM34=0,"",IF(ISNUMBER($O34),$O34,$AI34)) | AL34: =IF($AM34=0,"",IF(ISNUMBER($P34),$P34,N($AJ34))) | AM34: =IF(AND($A34<>"",$E34<>"",OR(AND(ISNUMBER($G34),ISNUMBER($H34),ISNUMBER($K34)),ISNUMBER($O34))),1,0) -> 0 | AN34: =IF($A34="","",$A34-WEEKDAY($A34,3)) | AO34: =IF($A34="","",WEEKDAY($A34,2)) | AP34: =IF(OR($AM34=0,$C34=""),"",IFERROR(N(INDEX(Accounts!$E$7:$E$16,MATCH($C34,Accounts!$B$7:$B$16,0))),0)+SUMIFS($Q$6:$Q34,$C$6:$C34,$C34)) | AQ34: =IF(OR($AM34=0,$C34=""),"",SUMIFS($Q$6:$Q$1005,$C$6:$C$1005,$C34,$A$6:$A$1005,$A34)) | AR34: =IF(OR($AM34=0,$C34=""),"",IFERROR(N(INDEX(Accounts!$E$7:$E$16,MATCH($C34,Accounts!$B$7:$B$16,0))),0)+SUMIFS($Q$6:$Q$1005,$C$6:$C$1005,$C34,$A$6:$A$1005,"<="&$A34)) | AS34: =IF(OR($AM34=0,$Q34=""),0,IF(AND($A34>=Lists!$W$6,$A34<=Lists!$W$7,OR(Dashboard!$D$6="All accounts",$C34=Dashboard!$D$6),OR(Dashboard!$D$7="All markets",$AF34=Dashboard!$D$7)),1,0)) -> 0 | AT34: =IF($AS34=1,N(AT33)+$Q34,N(AT33)) -> 1187.1069 | AU34: =MAX(N(AU33),$AT34) -> 1187.1069 | AV34: =$AT34-$AU34 -> 0 | AW34: =IF($AS34=1,IF($S34="Win",N(AW33)+1,IF($S34="Loss",0,N(AW33))),N(AW33)) -> 5 | AX34: =IF($AS34=1,IF($S34="Loss",N(AX33)+1,IF($S34="Win",0,N(AX33))),N(AX33)) -> 0 | AY34: =IF($AS34=1,COUNTIF($AS$6:$AS34,1),"") | AZ34: =MIN(28,N(Lists!$W$8)) -> 28 | BA34: =IF($AS34=1,IF(COUNTIFS($A$6:$A34,$A34,$AS$6:$AS34,1)=1,1,0),0) -> 0 | BB34: =IF($BA34=1,SUMIFS($Q$6:$Q$1005,$A$6:$A$1005,$A34,$AS$6:$AS$1005,1),"") | BC34: =IF(ISNUMBER($R34),1,0) -> 0 | BD34: =IF(ISNUMBER($U34),$U34*$V34,"") | BE34: =IF($AM34=0,"",IFERROR(MATCH($AF34&"|"&UPPER(TRIM($E34)),Lists!$A$6:$A$205,0),0)) | BF34: =IF($AM34=0,"",IFERROR(MATCH($AF34,Settings!$B$14:$B$18,0),IFERROR(MATCH(Settings!$C$6,Settings!$B$14:$B$18,0),1))) | BG34: =IF($AM34=0,"",IF(NOT(ISNUMBER($I34)),"No stop; ","")&IF(AND(ISNUMBER($H34),ISNUMBER($I34)),IF(OR(AND($F34<>"Short",$I34>=$H34),AND($F34="Short",$I34<=$H34)),"Stop on wrong side; ",""),"")&IF($F34="","No direction; ","")&IF(AND(ISNUMBER(Settings!$C$22),ISNUMBER($V34)),IF($V34>Settings!$C$22,"Risk over max $; ",""),"")&IF(AND(ISNUMBER(Settings!$C$23),ISNUMBER($V34),ISNUMBER($AP34),IFERROR(N(INDEX(Accounts!$E$7:$E$16,MATCH($C34,Accounts!$B$7:$B$16,0))),0)>0),IF($V34>Settings!$C$23*($AP34-N($Q34)),"Risk over max %; ",""),"")&IF(AND(ISNUMBER(Settings!$C$24),ISNUMBER($N34)),IF($N34>Settings!$C$24,"Leverage over max; ",""),"")&IF(AND(ISNUMBER(Settings!$C$27),ISNUMBER($T34)),IF($T34<Settings!$C$27,"R:R below min; ",""),"")&IF(ISNUMBER(Settings!$C$25),IF(COUNTIFS($A$6:$A34,$A34,$AM$6:$AM34,1)>Settings!$C$25,"Over max trades/day; ",""),"")&IF(ISNUMBER(Settings!$C$26),IF(SUMIFS($Q$5:$Q33,$A$5:$A33,$A34)<=-Settings!$C$26,"Traded after daily max loss; ",""),"")&IF(AND($AG34="",NOT(ISNUMBER($O34))),"Symbol not in Instruments; ","")&IF(AND($AH34="",NOT(ISNUMBER($O34))),"Forex cross: type Gross P&L; ","")) | BH34: =IF(ISNUMBER($Q34),1,0) -> 0 | BI34: =IF($Y34="",0,1) -> 0 | BJ34: =IF($AB34="",0,1) -> 0 | BK34: =IF(AND($BH34=1,$W34<>"OK"),1,0) -> 0 | BL34: =IF(N($AZ34)=0,0,IFERROR(INDEX($AT$6:$AT$1005,MATCH($AZ34,$AY$6:$AY$1005,0)),0)) -> 1187.1069 | BM34: =IF(ISNUMBER(SEARCH("daily max loss",$BG34)),1,0) -> 0
Q35: =IF($AM35=0,"",IF(ISNUMBER($AK35),$AK35-N($AL35),"")) | R35: =IF(OR($Q35="",NOT(ISNUMBER($V35))),"",$AK35/$V35) | S35: =IF($Q35="","",IF(AND(ISNUMBER($R35),ABS(N($R35))<N(Settings!$C$8)),"Scratch",IF($Q35>0,"Win",IF($Q35<0,"Loss","Scratch")))) | T35: =IF(OR($AM35=0,NOT(ISNUMBER($H35)),NOT(ISNUMBER($I35)),NOT(ISNUMBER($J35))),"",IF($H35=$I35,"",ROUND(ABS($J35-$H35)/ABS($H35-$I35),6))) | U35: =IF(OR($S35<>"Win",NOT(ISNUMBER($T35)),NOT(ISNUMBER($R35))),"",MAX(0,$T35-$R35)) | V35: =IF(OR($AM35=0,NOT(ISNUMBER($H35)),NOT(ISNUMBER($I35)),NOT(ISNUMBER($G35))),"",IF(OR($AG35="",$AH35=""),"",IF(ROUND(ABS($H35-$I35)*ABS($G35)*$AG35*$AH35,6)=0,"",ROUND(ABS($H35-$I35)*ABS($G35)*$AG35*$AH35,6)))) | W35: =IF($AM35=0,"",IF($BG35="","OK",LEFT($BG35,LEN($BG35)-2))) | AF35: =IF($AM35=0,"",IF($D35<>"",$D35,IF(IFERROR(INDEX(Accounts!$C$7:$C$16,MATCH($C35,Accounts!$B$7:$B$16,0))&"","")<>"",INDEX(Accounts!$C$7:$C$16,MATCH($C35,Accounts!$B$7:$B$16,0)),Settings!$C$6))) | AG35: =IF($AM35=0,"",IF(AND($BE35>0,N(INDEX(Instruments!$D$6:$D$205,MAX(1,$BE35)))>0),INDEX(Instruments!$D$6:$D$205,MAX(1,$BE35)),IF(N(INDEX(Settings!$D$14:$D$18,$BF35))>0,INDEX(Settings!$D$14:$D$18,$BF35),""))) | AH35: =IF($AM35=0,"",IF($AF35<>"Forex",1,IF(MID(UPPER(SUBSTITUTE(TRIM($E35),"/","")),4,3)=UPPER(TRIM(Settings!$C$7)),1,IF(LEFT(UPPER(SUBSTITUTE(TRIM($E35),"/","")),3)=UPPER(TRIM(Settings!$C$7)),IF(AND(ISNUMBER($K35),N($K35)<>0),1/$K35,""),"")))) | AI35: =IF($AM35=0,"",IF(OR(NOT(ISNUMBER($H35)),NOT(ISNUMBER($K35)),NOT(ISNUMBER($G35)),$AG35="",$AH35=""),"",ROUND(($K35-$H35)*IF($F35="Short",-1,1)*$G35*$AG35*$AH35,6))) | AJ35: =IF($AM35=0,"",IF(INDEX(Settings!$E$14:$E$18,$BF35)="% of notional",IF(OR($AG35="",NOT(ISNUMBER($H35)),NOT(ISNUMBER($G35))),"",ROUND(ABS($H35*$G35*$AG35*N($AH35))*IF($L35="Limit",N(INDEX(Settings!$G$14:$G$18,$BF35)),N(INDEX(Settings!$H$14:$H$18,$BF35)))+IF(ISNUMBER($K35),ABS($K35*$G35*$AG35*N($AH35))*IF($M35="Target",N(INDEX(Settings!$G$14:$G$18,$BF35)),N(INDEX(Settings!$H$14:$H$18,$BF35))),0),6)),IF(NOT(ISNUMBER($G35)),"",ROUND(ABS($G35)*2*IF(AND($BE35>0,ISNUMBER(INDEX(Instruments!$G$6:$G$205,MAX(1,$BE35)))),INDEX(Instruments!$G$6:$G$205,MAX(1,$BE35)),N(INDEX(Settings!$F$14:$F$18,$BF35))),6)))) | AK35: =IF($AM35=0,"",IF(ISNUMBER($O35),$O35,$AI35)) | AL35: =IF($AM35=0,"",IF(ISNUMBER($P35),$P35,N($AJ35))) | AM35: =IF(AND($A35<>"",$E35<>"",OR(AND(ISNUMBER($G35),ISNUMBER($H35),ISNUMBER($K35)),ISNUMBER($O35))),1,0) -> 0 | AN35: =IF($A35="","",$A35-WEEKDAY($A35,3)) | AO35: =IF($A35="","",WEEKDAY($A35,2)) | AP35: =IF(OR($AM35=0,$C35=""),"",IFERROR(N(INDEX(Accounts!$E$7:$E$16,MATCH($C35,Accounts!$B$7:$B$16,0))),0)+SUMIFS($Q$6:$Q35,$C$6:$C35,$C35)) | AQ35: =IF(OR($AM35=0,$C35=""),"",SUMIFS($Q$6:$Q$1005,$C$6:$C$1005,$C35,$A$6:$A$1005,$A35)) | AR35: =IF(OR($AM35=0,$C35=""),"",IFERROR(N(INDEX(Accounts!$E$7:$E$16,MATCH($C35,Accounts!$B$7:$B$16,0))),0)+SUMIFS($Q$6:$Q$1005,$C$6:$C$1005,$C35,$A$6:$A$1005,"<="&$A35)) | AS35: =IF(OR($AM35=0,$Q35=""),0,IF(AND($A35>=Lists!$W$6,$A35<=Lists!$W$7,OR(Dashboard!$D$6="All accounts",$C35=Dashboard!$D$6),OR(Dashboard!$D$7="All markets",$AF35=Dashboard!$D$7)),1,0)) -> 0 | AT35: =IF($AS35=1,N(AT34)+$Q35,N(AT34)) -> 1187.1069 | AU35: =MAX(N(AU34),$AT35) -> 1187.1069 | AV35: =$AT35-$AU35 -> 0 | AW35: =IF($AS35=1,IF($S35="Win",N(AW34)+1,IF($S35="Loss",0,N(AW34))),N(AW34)) -> 5 | AX35: =IF($AS35=1,IF($S35="Loss",N(AX34)+1,IF($S35="Win",0,N(AX34))),N(AX34)) -> 0 | AY35: =IF($AS35=1,COUNTIF($AS$6:$AS35,1),"") | AZ35: =MIN(29,N(Lists!$W$8)) -> 28 | BA35: =IF($AS35=1,IF(COUNTIFS($A$6:$A35,$A35,$AS$6:$AS35,1)=1,1,0),0) -> 0 | BB35: =IF($BA35=1,SUMIFS($Q$6:$Q$1005,$A$6:$A$1005,$A35,$AS$6:$AS$1005,1),"") | BC35: =IF(ISNUMBER($R35),1,0) -> 0 | BD35: =IF(ISNUMBER($U35),$U35*$V35,"") | BE35: =IF($AM35=0,"",IFERROR(MATCH($AF35&"|"&UPPER(TRIM($E35)),Lists!$A$6:$A$205,0),0)) | BF35: =IF($AM35=0,"",IFERROR(MATCH($AF35,Settings!$B$14:$B$18,0),IFERROR(MATCH(Settings!$C$6,Settings!$B$14:$B$18,0),1))) | BG35: =IF($AM35=0,"",IF(NOT(ISNUMBER($I35)),"No stop; ","")&IF(AND(ISNUMBER($H35),ISNUMBER($I35)),IF(OR(AND($F35<>"Short",$I35>=$H35),AND($F35="Short",$I35<=$H35)),"Stop on wrong side; ",""),"")&IF($F35="","No direction; ","")&IF(AND(ISNUMBER(Settings!$C$22),ISNUMBER($V35)),IF($V35>Settings!$C$22,"Risk over max $; ",""),"")&IF(AND(ISNUMBER(Settings!$C$23),ISNUMBER($V35),ISNUMBER($AP35),IFERROR(N(INDEX(Accounts!$E$7:$E$16,MATCH($C35,Accounts!$B$7:$B$16,0))),0)>0),IF($V35>Settings!$C$23*($AP35-N($Q35)),"Risk over max %; ",""),"")&IF(AND(ISNUMBER(Settings!$C$24),ISNUMBER($N35)),IF($N35>Settings!$C$24,"Leverage over max; ",""),"")&IF(AND(ISNUMBER(Settings!$C$27),ISNUMBER($T35)),IF($T35<Settings!$C$27,"R:R below min; ",""),"")&IF(ISNUMBER(Settings!$C$25),IF(COUNTIFS($A$6:$A35,$A35,$AM$6:$AM35,1)>Settings!$C$25,"Over max trades/day; ",""),"")&IF(ISNUMBER(Settings!$C$26),IF(SUMIFS($Q$5:$Q34,$A$5:$A34,$A35)<=-Settings!$C$26,"Traded after daily max loss; ",""),"")&IF(AND($AG35="",NOT(ISNUMBER($O35))),"Symbol not in Instruments; ","")&IF(AND($AH35="",NOT(ISNUMBER($O35))),"Forex cross: type Gross P&L; ","")) | BH35: =IF(ISNUMBER($Q35),1,0) -> 0 | BI35: =IF($Y35="",0,1) -> 0 | BJ35: =IF($AB35="",0,1) -> 0 | BK35: =IF(AND($BH35=1,$W35<>"OK"),1,0) -> 0 | BL35: =IF(N($AZ35)=0,0,IFERROR(INDEX($AT$6:$AT$1005,MATCH($AZ35,$AY$6:$AY$1005,0)),0)) -> 1187.1069 | BM35: =IF(ISNUMBER(SEARCH("daily max loss",$BG35)),1,0) -> 0
Q36: =IF($AM36=0,"",IF(ISNUMBER($AK36),$AK36-N($AL36),"")) | R36: =IF(OR($Q36="",NOT(ISNUMBER($V36))),"",$AK36/$V36) | S36: =IF($Q36="","",IF(AND(ISNUMBER($R36),ABS(N($R36))<N(Settings!$C$8)),"Scratch",IF($Q36>0,"Win",IF($Q36<0,"Loss","Scratch")))) | T36: =IF(OR($AM36=0,NOT(ISNUMBER($H36)),NOT(ISNUMBER($I36)),NOT(ISNUMBER($J36))),"",IF($H36=$I36,"",ROUND(ABS($J36-$H36)/ABS($H36-$I36),6))) | U36: =IF(OR($S36<>"Win",NOT(ISNUMBER($T36)),NOT(ISNUMBER($R36))),"",MAX(0,$T36-$R36)) | V36: =IF(OR($AM36=0,NOT(ISNUMBER($H36)),NOT(ISNUMBER($I36)),NOT(ISNUMBER($G36))),"",IF(OR($AG36="",$AH36=""),"",IF(ROUND(ABS($H36-$I36)*ABS($G36)*$AG36*$AH36,6)=0,"",ROUND(ABS($H36-$I36)*ABS($G36)*$AG36*$AH36,6)))) | W36: =IF($AM36=0,"",IF($BG36="","OK",LEFT($BG36,LEN($BG36)-2))) | AF36: =IF($AM36=0,"",IF($D36<>"",$D36,IF(IFERROR(INDEX(Accounts!$C$7:$C$16,MATCH($C36,Accounts!$B$7:$B$16,0))&"","")<>"",INDEX(Accounts!$C$7:$C$16,MATCH($C36,Accounts!$B$7:$B$16,0)),Settings!$C$6))) | AG36: =IF($AM36=0,"",IF(AND($BE36>0,N(INDEX(Instruments!$D$6:$D$205,MAX(1,$BE36)))>0),INDEX(Instruments!$D$6:$D$205,MAX(1,$BE36)),IF(N(INDEX(Settings!$D$14:$D$18,$BF36))>0,INDEX(Settings!$D$14:$D$18,$BF36),""))) | AH36: =IF($AM36=0,"",IF($AF36<>"Forex",1,IF(MID(UPPER(SUBSTITUTE(TRIM($E36),"/","")),4,3)=UPPER(TRIM(Settings!$C$7)),1,IF(LEFT(UPPER(SUBSTITUTE(TRIM($E36),"/","")),3)=UPPER(TRIM(Settings!$C$7)),IF(AND(ISNUMBER($K36),N($K36)<>0),1/$K36,""),"")))) | AI36: =IF($AM36=0,"",IF(OR(NOT(ISNUMBER($H36)),NOT(ISNUMBER($K36)),NOT(ISNUMBER($G36)),$AG36="",$AH36=""),"",ROUND(($K36-$H36)*IF($F36="Short",-1,1)*$G36*$AG36*$AH36,6))) | AJ36: =IF($AM36=0,"",IF(INDEX(Settings!$E$14:$E$18,$BF36)="% of notional",IF(OR($AG36="",NOT(ISNUMBER($H36)),NOT(ISNUMBER($G36))),"",ROUND(ABS($H36*$G36*$AG36*N($AH36))*IF($L36="Limit",N(INDEX(Settings!$G$14:$G$18,$BF36)),N(INDEX(Settings!$H$14:$H$18,$BF36)))+IF(ISNUMBER($K36),ABS($K36*$G36*$AG36*N($AH36))*IF($M36="Target",N(INDEX(Settings!$G$14:$G$18,$BF36)),N(INDEX(Settings!$H$14:$H$18,$BF36))),0),6)),IF(NOT(ISNUMBER($G36)),"",ROUND(ABS($G36)*2*IF(AND($BE36>0,ISNUMBER(INDEX(Instruments!$G$6:$G$205,MAX(1,$BE36)))),INDEX(Instruments!$G$6:$G$205,MAX(1,$BE36)),N(INDEX(Settings!$F$14:$F$18,$BF36))),6)))) | AK36: =IF($AM36=0,"",IF(ISNUMBER($O36),$O36,$AI36)) | AL36: =IF($AM36=0,"",IF(ISNUMBER($P36),$P36,N($AJ36))) | AM36: =IF(AND($A36<>"",$E36<>"",OR(AND(ISNUMBER($G36),ISNUMBER($H36),ISNUMBER($K36)),ISNUMBER($O36))),1,0) -> 0 | AN36: =IF($A36="","",$A36-WEEKDAY($A36,3)) | AO36: =IF($A36="","",WEEKDAY($A36,2)) | AP36: =IF(OR($AM36=0,$C36=""),"",IFERROR(N(INDEX(Accounts!$E$7:$E$16,MATCH($C36,Accounts!$B$7:$B$16,0))),0)+SUMIFS($Q$6:$Q36,$C$6:$C36,$C36)) | AQ36: =IF(OR($AM36=0,$C36=""),"",SUMIFS($Q$6:$Q$1005,$C$6:$C$1005,$C36,$A$6:$A$1005,$A36)) | AR36: =IF(OR($AM36=0,$C36=""),"",IFERROR(N(INDEX(Accounts!$E$7:$E$16,MATCH($C36,Accounts!$B$7:$B$16,0))),0)+SUMIFS($Q$6:$Q$1005,$C$6:$C$1005,$C36,$A$6:$A$1005,"<="&$A36)) | AS36: =IF(OR($AM36=0,$Q36=""),0,IF(AND($A36>=Lists!$W$6,$A36<=Lists!$W$7,OR(Dashboard!$D$6="All accounts",$C36=Dashboard!$D$6),OR(Dashboard!$D$7="All markets",$AF36=Dashboard!$D$7)),1,0)) -> 0 | AT36: =IF($AS36=1,N(AT35)+$Q36,N(AT35)) -> 1187.1069 | AU36: =MAX(N(AU35),$AT36) -> 1187.1069 | AV36: =$AT36-$AU36 -> 0 | AW36: =IF($AS36=1,IF($S36="Win",N(AW35)+1,IF($S36="Loss",0,N(AW35))),N(AW35)) -> 5 | AX36: =IF($AS36=1,IF($S36="Loss",N(AX35)+1,IF($S36="Win",0,N(AX35))),N(AX35)) -> 0 | AY36: =IF($AS36=1,COUNTIF($AS$6:$AS36,1),"") | AZ36: =MIN(30,N(Lists!$W$8)) -> 28 | BA36: =IF($AS36=1,IF(COUNTIFS($A$6:$A36,$A36,$AS$6:$AS36,1)=1,1,0),0) -> 0 | BB36: =IF($BA36=1,SUMIFS($Q$6:$Q$1005,$A$6:$A$1005,$A36,$AS$6:$AS$1005,1),"") | BC36: =IF(ISNUMBER($R36),1,0) -> 0 | BD36: =IF(ISNUMBER($U36),$U36*$V36,"") | BE36: =IF($AM36=0,"",IFERROR(MATCH($AF36&"|"&UPPER(TRIM($E36)),Lists!$A$6:$A$205,0),0)) | BF36: =IF($AM36=0,"",IFERROR(MATCH($AF36,Settings!$B$14:$B$18,0),IFERROR(MATCH(Settings!$C$6,Settings!$B$14:$B$18,0),1))) | BG36: =IF($AM36=0,"",IF(NOT(ISNUMBER($I36)),"No stop; ","")&IF(AND(ISNUMBER($H36),ISNUMBER($I36)),IF(OR(AND($F36<>"Short",$I36>=$H36),AND($F36="Short",$I36<=$H36)),"Stop on wrong side; ",""),"")&IF($F36="","No direction; ","")&IF(AND(ISNUMBER(Settings!$C$22),ISNUMBER($V36)),IF($V36>Settings!$C$22,"Risk over max $; ",""),"")&IF(AND(ISNUMBER(Settings!$C$23),ISNUMBER($V36),ISNUMBER($AP36),IFERROR(N(INDEX(Accounts!$E$7:$E$16,MATCH($C36,Accounts!$B$7:$B$16,0))),0)>0),IF($V36>Settings!$C$23*($AP36-N($Q36)),"Risk over max %; ",""),"")&IF(AND(ISNUMBER(Settings!$C$24),ISNUMBER($N36)),IF($N36>Settings!$C$24,"Leverage over max; ",""),"")&IF(AND(ISNUMBER(Settings!$C$27),ISNUMBER($T36)),IF($T36<Settings!$C$27,"R:R below min; ",""),"")&IF(ISNUMBER(Settings!$C$25),IF(COUNTIFS($A$6:$A36,$A36,$AM$6:$AM36,1)>Settings!$C$25,"Over max trades/day; ",""),"")&IF(ISNUMBER(Settings!$C$26),IF(SUMIFS($Q$5:$Q35,$A$5:$A35,$A36)<=-Settings!$C$26,"Traded after daily max loss; ",""),"")&IF(AND($AG36="",NOT(ISNUMBER($O36))),"Symbol not in Instruments; ","")&IF(AND($AH36="",NOT(ISNUMBER($O36))),"Forex cross: type Gross P&L; ","")) | BH36: =IF(ISNUMBER($Q36),1,0) -> 0 | BI36: =IF($Y36="",0,1) -> 0 | BJ36: =IF($AB36="",0,1) -> 0 | BK36: =IF(AND($BH36=1,$W36<>"OK"),1,0) -> 0 | BL36: =IF(N($AZ36)=0,0,IFERROR(INDEX($AT$6:$AT$1005,MATCH($AZ36,$AY$6:$AY$1005,0)),0)) -> 1187.1069 | BM36: =IF(ISNUMBER(SEARCH("daily max loss",$BG36)),1,0) -> 0
Q37: =IF($AM37=0,"",IF(ISNUMBER($AK37),$AK37-N($AL37),"")) | R37: =IF(OR($Q37="",NOT(ISNUMBER($V37))),"",$AK37/$V37) | S37: =IF($Q37="","",IF(AND(ISNUMBER($R37),ABS(N($R37))<N(Settings!$C$8)),"Scratch",IF($Q37>0,"Win",IF($Q37<0,"Loss","Scratch")))) | T37: =IF(OR($AM37=0,NOT(ISNUMBER($H37)),NOT(ISNUMBER($I37)),NOT(ISNUMBER($J37))),"",IF($H37=$I37,"",ROUND(ABS($J37-$H37)/ABS($H37-$I37),6))) | U37: =IF(OR($S37<>"Win",NOT(ISNUMBER($T37)),NOT(ISNUMBER($R37))),"",MAX(0,$T37-$R37)) | V37: =IF(OR($AM37=0,NOT(ISNUMBER($H37)),NOT(ISNUMBER($I37)),NOT(ISNUMBER($G37))),"",IF(OR($AG37="",$AH37=""),"",IF(ROUND(ABS($H37-$I37)*ABS($G37)*$AG37*$AH37,6)=0,"",ROUND(ABS($H37-$I37)*ABS($G37)*$AG37*$AH37,6)))) | W37: =IF($AM37=0,"",IF($BG37="","OK",LEFT($BG37,LEN($BG37)-2))) | AF37: =IF($AM37=0,"",IF($D37<>"",$D37,IF(IFERROR(INDEX(Accounts!$C$7:$C$16,MATCH($C37,Accounts!$B$7:$B$16,0))&"","")<>"",INDEX(Accounts!$C$7:$C$16,MATCH($C37,Accounts!$B$7:$B$16,0)),Settings!$C$6))) | AG37: =IF($AM37=0,"",IF(AND($BE37>0,N(INDEX(Instruments!$D$6:$D$205,MAX(1,$BE37)))>0),INDEX(Instruments!$D$6:$D$205,MAX(1,$BE37)),IF(N(INDEX(Settings!$D$14:$D$18,$BF37))>0,INDEX(Settings!$D$14:$D$18,$BF37),""))) | AH37: =IF($AM37=0,"",IF($AF37<>"Forex",1,IF(MID(UPPER(SUBSTITUTE(TRIM($E37),"/","")),4,3)=UPPER(TRIM(Settings!$C$7)),1,IF(LEFT(UPPER(SUBSTITUTE(TRIM($E37),"/","")),3)=UPPER(TRIM(Settings!$C$7)),IF(AND(ISNUMBER($K37),N($K37)<>0),1/$K37,""),"")))) | AI37: =IF($AM37=0,"",IF(OR(NOT(ISNUMBER($H37)),NOT(ISNUMBER($K37)),NOT(ISNUMBER($G37)),$AG37="",$AH37=""),"",ROUND(($K37-$H37)*IF($F37="Short",-1,1)*$G37*$AG37*$AH37,6))) | AJ37: =IF($AM37=0,"",IF(INDEX(Settings!$E$14:$E$18,$BF37)="% of notional",IF(OR($AG37="",NOT(ISNUMBER($H37)),NOT(ISNUMBER($G37))),"",ROUND(ABS($H37*$G37*$AG37*N($AH37))*IF($L37="Limit",N(INDEX(Settings!$G$14:$G$18,$BF37)),N(INDEX(Settings!$H$14:$H$18,$BF37)))+IF(ISNUMBER($K37),ABS($K37*$G37*$AG37*N($AH37))*IF($M37="Target",N(INDEX(Settings!$G$14:$G$18,$BF37)),N(INDEX(Settings!$H$14:$H$18,$BF37))),0),6)),IF(NOT(ISNUMBER($G37)),"",ROUND(ABS($G37)*2*IF(AND($BE37>0,ISNUMBER(INDEX(Instruments!$G$6:$G$205,MAX(1,$BE37)))),INDEX(Instruments!$G$6:$G$205,MAX(1,$BE37)),N(INDEX(Settings!$F$14:$F$18,$BF37))),6)))) | AK37: =IF($AM37=0,"",IF(ISNUMBER($O37),$O37,$AI37)) | AL37: =IF($AM37=0,"",IF(ISNUMBER($P37),$P37,N($AJ37))) | AM37: =IF(AND($A37<>"",$E37<>"",OR(AND(ISNUMBER($G37),ISNUMBER($H37),ISNUMBER($K37)),ISNUMBER($O37))),1,0) -> 0 | AN37: =IF($A37="","",$A37-WEEKDAY($A37,3)) | AO37: =IF($A37="","",WEEKDAY($A37,2)) | AP37: =IF(OR($AM37=0,$C37=""),"",IFERROR(N(INDEX(Accounts!$E$7:$E$16,MATCH($C37,Accounts!$B$7:$B$16,0))),0)+SUMIFS($Q$6:$Q37,$C$6:$C37,$C37)) | AQ37: =IF(OR($AM37=0,$C37=""),"",SUMIFS($Q$6:$Q$1005,$C$6:$C$1005,$C37,$A$6:$A$1005,$A37)) | AR37: =IF(OR($AM37=0,$C37=""),"",IFERROR(N(INDEX(Accounts!$E$7:$E$16,MATCH($C37,Accounts!$B$7:$B$16,0))),0)+SUMIFS($Q$6:$Q$1005,$C$6:$C$1005,$C37,$A$6:$A$1005,"<="&$A37)) | AS37: =IF(OR($AM37=0,$Q37=""),0,IF(AND($A37>=Lists!$W$6,$A37<=Lists!$W$7,OR(Dashboard!$D$6="All accounts",$C37=Dashboard!$D$6),OR(Dashboard!$D$7="All markets",$AF37=Dashboard!$D$7)),1,0)) -> 0 | AT37: =IF($AS37=1,N(AT36)+$Q37,N(AT36)) -> 1187.1069 | AU37: =MAX(N(AU36),$AT37) -> 1187.1069 | AV37: =$AT37-$AU37 -> 0 | AW37: =IF($AS37=1,IF($S37="Win",N(AW36)+1,IF($S37="Loss",0,N(AW36))),N(AW36)) -> 5 | AX37: =IF($AS37=1,IF($S37="Loss",N(AX36)+1,IF($S37="Win",0,N(AX36))),N(AX36)) -> 0 | AY37: =IF($AS37=1,COUNTIF($AS$6:$AS37,1),"") | AZ37: =MIN(31,N(Lists!$W$8)) -> 28 | BA37: =IF($AS37=1,IF(COUNTIFS($A$6:$A37,$A37,$AS$6:$AS37,1)=1,1,0),0) -> 0 | BB37: =IF($BA37=1,SUMIFS($Q$6:$Q$1005,$A$6:$A$1005,$A37,$AS$6:$AS$1005,1),"") | BC37: =IF(ISNUMBER($R37),1,0) -> 0 | BD37: =IF(ISNUMBER($U37),$U37*$V37,"") | BE37: =IF($AM37=0,"",IFERROR(MATCH($AF37&"|"&UPPER(TRIM($E37)),Lists!$A$6:$A$205,0),0)) | BF37: =IF($AM37=0,"",IFERROR(MATCH($AF37,Settings!$B$14:$B$18,0),IFERROR(MATCH(Settings!$C$6,Settings!$B$14:$B$18,0),1))) | BG37: =IF($AM37=0,"",IF(NOT(ISNUMBER($I37)),"No stop; ","")&IF(AND(ISNUMBER($H37),ISNUMBER($I37)),IF(OR(AND($F37<>"Short",$I37>=$H37),AND($F37="Short",$I37<=$H37)),"Stop on wrong side; ",""),"")&IF($F37="","No direction; ","")&IF(AND(ISNUMBER(Settings!$C$22),ISNUMBER($V37)),IF($V37>Settings!$C$22,"Risk over max $; ",""),"")&IF(AND(ISNUMBER(Settings!$C$23),ISNUMBER($V37),ISNUMBER($AP37),IFERROR(N(INDEX(Accounts!$E$7:$E$16,MATCH($C37,Accounts!$B$7:$B$16,0))),0)>0),IF($V37>Settings!$C$23*($AP37-N($Q37)),"Risk over max %; ",""),"")&IF(AND(ISNUMBER(Settings!$C$24),ISNUMBER($N37)),IF($N37>Settings!$C$24,"Leverage over max; ",""),"")&IF(AND(ISNUMBER(Settings!$C$27),ISNUMBER($T37)),IF($T37<Settings!$C$27,"R:R below min; ",""),"")&IF(ISNUMBER(Settings!$C$25),IF(COUNTIFS($A$6:$A37,$A37,$AM$6:$AM37,1)>Settings!$C$25,"Over max trades/day; ",""),"")&IF(ISNUMBER(Settings!$C$26),IF(SUMIFS($Q$5:$Q36,$A$5:$A36,$A37)<=-Settings!$C$26,"Traded after daily max loss; ",""),"")&IF(AND($AG37="",NOT(ISNUMBER($O37))),"Symbol not in Instruments; ","")&IF(AND($AH37="",NOT(ISNUMBER($O37))),"Forex cross: type Gross P&L; ","")) | BH37: =IF(ISNUMBER($Q37),1,0) -> 0 | BI37: =IF($Y37="",0,1) -> 0 | BJ37: =IF($AB37="",0,1) -> 0 | BK37: =IF(AND($BH37=1,$W37<>"OK"),1,0) -> 0 | BL37: =IF(N($AZ37)=0,0,IFERROR(INDEX($AT$6:$AT$1005,MATCH($AZ37,$AY$6:$AY$1005,0)),0)) -> 1187.1069 | BM37: =IF(ISNUMBER(SEARCH("daily max loss",$BG37)),1,0) -> 0
Q38: =IF($AM38=0,"",IF(ISNUMBER($AK38),$AK38-N($AL38),"")) | R38: =IF(OR($Q38="",NOT(ISNUMBER($V38))),"",$AK38/$V38) | S38: =IF($Q38="","",IF(AND(ISNUMBER($R38),ABS(N($R38))<N(Settings!$C$8)),"Scratch",IF($Q38>0,"Win",IF($Q38<0,"Loss","Scratch")))) | T38: =IF(OR($AM38=0,NOT(ISNUMBER($H38)),NOT(ISNUMBER($I38)),NOT(ISNUMBER($J38))),"",IF($H38=$I38,"",ROUND(ABS($J38-$H38)/ABS($H38-$I38),6))) | U38: =IF(OR($S38<>"Win",NOT(ISNUMBER($T38)),NOT(ISNUMBER($R38))),"",MAX(0,$T38-$R38)) | V38: =IF(OR($AM38=0,NOT(ISNUMBER($H38)),NOT(ISNUMBER($I38)),NOT(ISNUMBER($G38))),"",IF(OR($AG38="",$AH38=""),"",IF(ROUND(ABS($H38-$I38)*ABS($G38)*$AG38*$AH38,6)=0,"",ROUND(ABS($H38-$I38)*ABS($G38)*$AG38*$AH38,6)))) | W38: =IF($AM38=0,"",IF($BG38="","OK",LEFT($BG38,LEN($BG38)-2))) | AF38: =IF($AM38=0,"",IF($D38<>"",$D38,IF(IFERROR(INDEX(Accounts!$C$7:$C$16,MATCH($C38,Accounts!$B$7:$B$16,0))&"","")<>"",INDEX(Accounts!$C$7:$C$16,MATCH($C38,Accounts!$B$7:$B$16,0)),Settings!$C$6))) | AG38: =IF($AM38=0,"",IF(AND($BE38>0,N(INDEX(Instruments!$D$6:$D$205,MAX(1,$BE38)))>0),INDEX(Instruments!$D$6:$D$205,MAX(1,$BE38)),IF(N(INDEX(Settings!$D$14:$D$18,$BF38))>0,INDEX(Settings!$D$14:$D$18,$BF38),""))) | AH38: =IF($AM38=0,"",IF($AF38<>"Forex",1,IF(MID(UPPER(SUBSTITUTE(TRIM($E38),"/","")),4,3)=UPPER(TRIM(Settings!$C$7)),1,IF(LEFT(UPPER(SUBSTITUTE(TRIM($E38),"/","")),3)=UPPER(TRIM(Settings!$C$7)),IF(AND(ISNUMBER($K38),N($K38)<>0),1/$K38,""),"")))) | AI38: =IF($AM38=0,"",IF(OR(NOT(ISNUMBER($H38)),NOT(ISNUMBER($K38)),NOT(ISNUMBER($G38)),$AG38="",$AH38=""),"",ROUND(($K38-$H38)*IF($F38="Short",-1,1)*$G38*$AG38*$AH38,6))) | AJ38: =IF($AM38=0,"",IF(INDEX(Settings!$E$14:$E$18,$BF38)="% of notional",IF(OR($AG38="",NOT(ISNUMBER($H38)),NOT(ISNUMBER($G38))),"",ROUND(ABS($H38*$G38*$AG38*N($AH38))*IF($L38="Limit",N(INDEX(Settings!$G$14:$G$18,$BF38)),N(INDEX(Settings!$H$14:$H$18,$BF38)))+IF(ISNUMBER($K38),ABS($K38*$G38*$AG38*N($AH38))*IF($M38="Target",N(INDEX(Settings!$G$14:$G$18,$BF38)),N(INDEX(Settings!$H$14:$H$18,$BF38))),0),6)),IF(NOT(ISNUMBER($G38)),"",ROUND(ABS($G38)*2*IF(AND($BE38>0,ISNUMBER(INDEX(Instruments!$G$6:$G$205,MAX(1,$BE38)))),INDEX(Instruments!$G$6:$G$205,MAX(1,$BE38)),N(INDEX(Settings!$F$14:$F$18,$BF38))),6)))) | AK38: =IF($AM38=0,"",IF(ISNUMBER($O38),$O38,$AI38)) | AL38: =IF($AM38=0,"",IF(ISNUMBER($P38),$P38,N($AJ38))) | AM38: =IF(AND($A38<>"",$E38<>"",OR(AND(ISNUMBER($G38),ISNUMBER($H38),ISNUMBER($K38)),ISNUMBER($O38))),1,0) -> 0 | AN38: =IF($A38="","",$A38-WEEKDAY($A38,3)) | AO38: =IF($A38="","",WEEKDAY($A38,2)) | AP38: =IF(OR($AM38=0,$C38=""),"",IFERROR(N(INDEX(Accounts!$E$7:$E$16,MATCH($C38,Accounts!$B$7:$B$16,0))),0)+SUMIFS($Q$6:$Q38,$C$6:$C38,$C38)) | AQ38: =IF(OR($AM38=0,$C38=""),"",SUMIFS($Q$6:$Q$1005,$C$6:$C$1005,$C38,$A$6:$A$1005,$A38)) | AR38: =IF(OR($AM38=0,$C38=""),"",IFERROR(N(INDEX(Accounts!$E$7:$E$16,MATCH($C38,Accounts!$B$7:$B$16,0))),0)+SUMIFS($Q$6:$Q$1005,$C$6:$C$1005,$C38,$A$6:$A$1005,"<="&$A38)) | AS38: =IF(OR($AM38=0,$Q38=""),0,IF(AND($A38>=Lists!$W$6,$A38<=Lists!$W$7,OR(Dashboard!$D$6="All accounts",$C38=Dashboard!$D$6),OR(Dashboard!$D$7="All markets",$AF38=Dashboard!$D$7)),1,0)) -> 0 | AT38: =IF($AS38=1,N(AT37)+$Q38,N(AT37)) -> 1187.1069 | AU38: =MAX(N(AU37),$AT38) -> 1187.1069 | AV38: =$AT38-$AU38 -> 0 | AW38: =IF($AS38=1,IF($S38="Win",N(AW37)+1,IF($S38="Loss",0,N(AW37))),N(AW37)) -> 5 | AX38: =IF($AS38=1,IF($S38="Loss",N(AX37)+1,IF($S38="Win",0,N(AX37))),N(AX37)) -> 0 | AY38: =IF($AS38=1,COUNTIF($AS$6:$AS38,1),"") | AZ38: =MIN(32,N(Lists!$W$8)) -> 28 | BA38: =IF($AS38=1,IF(COUNTIFS($A$6:$A38,$A38,$AS$6:$AS38,1)=1,1,0),0) -> 0 | BB38: =IF($BA38=1,SUMIFS($Q$6:$Q$1005,$A$6:$A$1005,$A38,$AS$6:$AS$1005,1),"") | BC38: =IF(ISNUMBER($R38),1,0) -> 0 | BD38: =IF(ISNUMBER($U38),$U38*$V38,"") | BE38: =IF($AM38=0,"",IFERROR(MATCH($AF38&"|"&UPPER(TRIM($E38)),Lists!$A$6:$A$205,0),0)) | BF38: =IF($AM38=0,"",IFERROR(MATCH($AF38,Settings!$B$14:$B$18,0),IFERROR(MATCH(Settings!$C$6,Settings!$B$14:$B$18,0),1))) | BG38: =IF($AM38=0,"",IF(NOT(ISNUMBER($I38)),"No stop; ","")&IF(AND(ISNUMBER($H38),ISNUMBER($I38)),IF(OR(AND($F38<>"Short",$I38>=$H38),AND($F38="Short",$I38<=$H38)),"Stop on wrong side; ",""),"")&IF($F38="","No direction; ","")&IF(AND(ISNUMBER(Settings!$C$22),ISNUMBER($V38)),IF($V38>Settings!$C$22,"Risk over max $; ",""),"")&IF(AND(ISNUMBER(Settings!$C$23),ISNUMBER($V38),ISNUMBER($AP38),IFERROR(N(INDEX(Accounts!$E$7:$E$16,MATCH($C38,Accounts!$B$7:$B$16,0))),0)>0),IF($V38>Settings!$C$23*($AP38-N($Q38)),"Risk over max %; ",""),"")&IF(AND(ISNUMBER(Settings!$C$24),ISNUMBER($N38)),IF($N38>Settings!$C$24,"Leverage over max; ",""),"")&IF(AND(ISNUMBER(Settings!$C$27),ISNUMBER($T38)),IF($T38<Settings!$C$27,"R:R below min; ",""),"")&IF(ISNUMBER(Settings!$C$25),IF(COUNTIFS($A$6:$A38,$A38,$AM$6:$AM38,1)>Settings!$C$25,"Over max trades/day; ",""),"")&IF(ISNUMBER(Settings!$C$26),IF(SUMIFS($Q$5:$Q37,$A$5:$A37,$A38)<=-Settings!$C$26,"Traded after daily max loss; ",""),"")&IF(AND($AG38="",NOT(ISNUMBER($O38))),"Symbol not in Instruments; ","")&IF(AND($AH38="",NOT(ISNUMBER($O38))),"Forex cross: type Gross P&L; ","")) | BH38: =IF(ISNUMBER($Q38),1,0) -> 0 | BI38: =IF($Y38="",0,1) -> 0 | BJ38: =IF($AB38="",0,1) -> 0 | BK38: =IF(AND($BH38=1,$W38<>"OK"),1,0) -> 0 | BL38: =IF(N($AZ38)=0,0,IFERROR(INDEX($AT$6:$AT$1005,MATCH($AZ38,$AY$6:$AY$1005,0)),0)) -> 1187.1069 | BM38: =IF(ISNUMBER(SEARCH("daily max loss",$BG38)),1,0) -> 0
